Workbook
Name IQ_CH: 110000
Name IQ_CQ: 5000
Name IQ_CY: 10000
Name IQ_DAILY: 500000
Name IQ_FH: 100000
Name IQ_FQ: 500
Name IQ_FY: 1000
Name IQ_LTM: 2000
Name IQ_MONTH: 15000
Name IQ_NTM: 6000
Name IQ_WEEK: 50000
Name IQ_YTD: 3000

Sheet Quarterly
A1: ILMN key numbers: quarterly (last four reported quarters and 2026-27 consensus)
A2: $M unless noted. A = reported, E = Bloomberg consensus (10 Oct 2026). Non-GAAP unless noted. 2024 comparisons on a Core Illumina (ex-GRAIL) basis. n/a = not disclosed / no consensus.
A4: Metric | B4: Q3'25 | C4: Q4'25 | D4: Q1'26 | E4: Q2'26 | F4: Q3'26E | G4: Q4'26E | H4: Q1'27E | I4: Q2'27E | J4: Q3'27E | K4: Q4'27E
A5: Revenue
A6: Consolidated revenue ($M) | B6: =Data!I4 -> 1084 | C6: =Data!J4 -> 1159 | D6: =Data!K4 -> 1091 | E6: =Data!L4 -> 1159 | F6: =Data!M4 -> 1154.2 | G6: =Data!N4 -> 1219.8 | H6: =Data!O4 -> 1159.6 | I6: =Data!P4 -> 1217.8 | ... K6: =Data!R4 -> 1292.3
A7: y/y | B7: =Data!I5 -> 0.0037037037 | C7: =Data!J5 -> 0.049818841 | D7: =Data!K5 -> 0.04803074 | E7: =Data!L5 -> 0.094428706 | F7: =Data!M5 -> 0.064760148 | G7: =Data!N5 -> 0.052459016 | H7: =Data!O5 -> 0.062878093 | I7: =Data!P5 -> 0.050733391 | ... K7: =Data!R5 -> 0.059435973
A8: q/q | B8: =Data!I6 -> 0.023607177 | C8: =Data!J6 -> 0.069188192 | D8: =Data!K6 -> -0.058671268 | E8: =Data!L6 -> 0.062328139 | F8: =Data!M6 -> -0.0041415013 | G8: =Data!N6 -> 0.056835904 | H8: =Data!O6 -> -0.049352353 | I8: =Data!P6 -> 0.050189721 | ... K8: =Data!R6 -> 0.051334201
A9: 2-yr stack | B9: =Data!I7 -> -0.016296296 | C9: =Data!J7 -> 0.059818841 | D9: =Data!K7 -> 0.033826194 | E9: =Data!L7 -> 0.064208926 | F9: =Data!M7 -> 0.068463851 | G9: =Data!N7 -> 0.10227786 | H9: =Data!O7 -> 0.11090883 | I9: =Data!P7 -> 0.1451621 | ... K9: =Data!R7 -> 0.11189499
A10: Revenue ex-China ($M) | B10: =Data!I9 -> 1032 | C10: =Data!J9 -> 1104 | D10: =Data!K9 -> 1039 | E10: =Data!L9 -> 1103 | F10: =Data!M9 -> 1103.4 | G10: =Data!N9 -> 1167.9 | H10: =Data!O9 -> 1115 | I10: =Data!P9 -> 1170.8 | ... K10: =Data!R9 -> 1243.4
A11: y/y | B11: =Data!I10 -> 0.026865672 | C11: =Data!J10 -> 0.078125 | D11: =Data!K10 -> 0.072239422 | E11: =Data!L10 -> 0.10742972 | F11: =Data!M10 -> 0.069186047 | G11: =Data!N10 -> 0.057880435 | H11: =Data!O10 -> 0.073147257 | I11: =Data!P10 -> 0.061468722 | ... K11: =Data!R10 -> 0.064645946
A12: q/q | B12: =Data!I11 -> 0.036144578 | C12: =Data!J11 -> 0.069767442 | D12: =Data!K11 -> -0.058876812 | E12: =Data!L11 -> 0.06159769 | F12: =Data!M11 -> 0.00036264733 | G12: =Data!N11 -> 0.058455682 | H12: =Data!O11 -> -0.045294974 | I12: =Data!P11 -> 0.050044843 | ... K12: =Data!R11 -> 0.051323243
A13: 2-yr stack | B13: =Data!I12 -> n/a | C13: =Data!J12 -> n/a | D13: =Data!K12 -> 0.063036968 | E13: =Data!L12 -> 0.086780751 | F13: =Data!M12 -> 0.096051718 | G13: =Data!N12 -> 0.13600543 | H13: =Data!O12 -> 0.14538668 | I13: =Data!P12 -> 0.16889844 | ... K13: =Data!R12 -> 0.12252638
A14: Instrument placements
A15: NovaSeq X placements (units; lower bounds) | B15: =Data!I14 -> 55 | C15: =Data!J14 -> 100 | D15: =Data!K14 -> 83 | E15: =Data!L14 -> 95 | F15: =Data!M14 -> n/a | G15: =Data!N14 -> n/a | H15: =Data!O14 -> n/a | I15: =Data!P14 -> n/a | ... K15: =Data!R14 -> n/a
A16: y/y | B16: =Data!I15 -> -0.051724138 | C16: =Data!J15 -> 0.098901099 | D16: =Data!K15 -> 0.38333333 | E16: =Data!L15 -> 0.9 | F16: =Data!M15 -> n/a | G16: =Data!N15 -> n/a | H16: =Data!O15 -> n/a | I16: =Data!P15 -> n/a | ... K16: =Data!R15 -> n/a
A17: q/q | B17: =Data!I16 -> 0.1 | C17: =Data!J16 -> 0.81818182 | D17: =Data!K16 -> -0.17 | E17: =Data!L16 -> 0.14457831 | F17: =Data!M16 -> n/a | G17: =Data!N16 -> n/a | H17: =Data!O16 -> n/a | I17: =Data!P16 -> n/a | ... K17: =Data!R16 -> n/a
A18: 2-yr stack | B18: =Data!I17 -> -0.45378599 | C18: =Data!J17 -> 0.25079983 | D18: =Data!K17 -> 0.47424242 | E18: =Data!L17 -> 0.70645161 | F18: =Data!M17 -> n/a | G18: =Data!N17 -> n/a | H18: =Data!O17 -> n/a | I18: =Data!P17 -> n/a | ... K18: =Data!R17 -> n/a
A19: Clinical share of X placements | B19: =Data!I160 -> >50% | C19: =Data!J160 -> >60% | D19: =Data!K160 -> >60% | E19: =Data!L160 -> ~60-70% | F19: =Data!M160 -> n/a | G19: =Data!N160 -> n/a | H19: =Data!O160 -> n/a | I19: =Data!P160 -> n/a | ... K19: =Data!R160 -> n/a
A20: Instruments
A21: Instruments revenue ($M) | B21: =Data!I19 -> 111 | C21: =Data!J19 -> 158 | D21: =Data!K19 -> 120 | E21: =Data!L19 -> 130 | F21: =Data!M19 -> 115.2 | G21: =Data!N19 -> 131.5 | H21: =Data!O19 -> 111.1 | I21: =Data!P19 -> 114 | ... K21: =Data!R19 -> 126.8
A22: y/y | B22: =Data!I20 -> 0.037383178 | C22: =Data!J20 -> -0.0062893082 | D22: =Data!K20 -> 0.071428571 | E22: =Data!L20 -> 0.28712871 | F22: =Data!M20 -> 0.037837838 | G22: =Data!N20 -> -0.16772152 | H22: =Data!O20 -> -0.074166667 | I22: =Data!P20 -> -0.12307692 | ... K22: =Data!R20 -> -0.035741445
A23: q/q | B23: =Data!I21 -> 0.099009901 | C23: =Data!J21 -> 0.42342342 | D23: =Data!K21 -> -0.24050633 | E23: =Data!L21 -> 0.083333333 | F23: =Data!M21 -> -0.11384615 | G23: =Data!N21 -> 0.14149306 | H23: =Data!O21 -> -0.15513308 | I23: =Data!P21 -> 0.02610261 | ... K23: =Data!R21 -> 0.13620072
A24: 2-yr stack | B24: =Data!I22 -> -0.37470473 | C24: =Data!J22 -> -0.0541935 | D24: =Data!K22 -> 0.053884712 | E24: =Data!L22 -> 0.12879538 | F24: =Data!M22 -> 0.075221015 | G24: =Data!N22 -> -0.17401083 | H24: =Data!O22 -> -0.0027380952 | I24: =Data!P22 -> 0.16405179 | ... K24: =Data!R22 -> -0.20346296
A25: Sequencing instruments ex-China ($M) | B25: =Data!I24 -> 104 | C25: =Data!J24 -> 150 | D25: =Data!K24 -> 114 | E25: =Data!L24 -> 122 | F25: =Data!M24 -> n/a | G25: =Data!N24 -> n/a | H25: =Data!O24 -> n/a | I25: =Data!P24 -> n/a | ... K25: =Data!R24 -> n/a
A26: y/y | B26: =Data!I25 -> 0.06122449 | C26: =Data!J25 -> 0.041666667 | D26: =Data!K25 -> 0.10679612 | E26: =Data!L25 -> 0.32608696 | F26: =Data!M25 -> n/a | G26: =Data!N25 -> n/a | H26: =Data!O25 -> n/a | I26: =Data!P25 -> n/a | ... K26: =Data!R25 -> n/a
A27: q/q | B27: =Data!I26 -> 0.13043478 | C27: =Data!J26 -> 0.44230769 | D27: =Data!K26 -> -0.24 | E27: =Data!L26 -> 0.070175439 | F27: =Data!M26 -> n/a | G27: =Data!N26 -> n/a | H27: =Data!O26 -> n/a | I27: =Data!P26 -> n/a | ... K27: =Data!R26 -> n/a
A28: 2-yr stack | B28: =Data!I27 -> n/a | C28: =Data!J27 -> n/a | D28: =Data!K27 -> 0.13679612 | E28: =Data!L27 -> 0.15491579 | F28: =Data!M27 -> n/a | G28: =Data!N27 -> n/a | H28: =Data!O27 -> n/a | I28: =Data!P27 -> n/a | ... K28: =Data!R27 -> n/a
A29: Consumables
A30: Consumables revenue ($M) | B30: =Data!I29 -> 816 | C30: =Data!J29 -> 832 | D30: =Data!K29 -> 797 | E30: =Data!L29 -> 852 | F30: =Data!M29 -> 861 | G30: =Data!N29 -> 894.2 | H30: =Data!O29 -> 862.8 | I30: =Data!P29 -> 914.1 | ... K30: =Data!R29 -> 966.6
A31: y/y | B31: =Data!I30 -> 0.011152416 | C31: =Data!J30 -> 0.068035944 | D31: =Data!K30 -> 0.037760417 | E31: =Data!L30 -> 0.050554871 | F31: =Data!M30 -> 0.055147059 | G31: =Data!N30 -> 0.074759615 | H31: =Data!O30 -> 0.082559598 | I31: =Data!P30 -> 0.072887324 | ... K31: =Data!R30 -> 0.080966227
A32: q/q | B32: =Data!I31 -> 0.0061652281 | C32: =Data!J31 -> 0.019607843 | D32: =Data!K31 -> -0.042067308 | E32: =Data!L31 -> 0.069008783 | F32: =Data!M31 -> 0.01056338 | G32: =Data!N31 -> 0.038559814 | H32: =Data!O31 -> -0.035115187 | I32: =Data!P31 -> 0.05945758 | ... K32: =Data!R31 -> 0.037681159
A33: 2-yr stack | B33: =Data!I32 -> 0.064677221 | C33: =Data!J32 -> 0.098459224 | D33: =Data!K32 -> 0.037760417 | E33: =Data!L32 -> 0.045646895 | F33: =Data!M32 -> 0.066299475 | G33: =Data!N32 -> 0.14279556 | H33: =Data!O32 -> 0.12032002 | I33: =Data!P32 -> 0.12344219 | ... K33: =Data!R32 -> 0.15572584
A34: Sequencing consumables ($M) | B34: =Data!I34 -> 747 | C34: =Data!J34 -> 755 | D34: =Data!K34 -> 726 | E34: =Data!L34 -> 775 | F34: =Data!M34 -> 789.2 | G34: =Data!N34 -> 814.9 | H34: =Data!O34 -> 792.1 | I34: =Data!P34 -> 838.9 | ... K34: =Data!R34 -> 888.1
A35: y/y | B35: =Data!I35 -> 0.008097166 | C35: =Data!J35 -> 0.081661891 | D35: =Data!K35 -> 0.043103448 | E35: =Data!L35 -> 0.047297297 | F35: =Data!M35 -> 0.056492637 | G35: =Data!N35 -> 0.079337748 | H35: =Data!O35 -> 0.091046832 | I35: =Data!P35 -> 0.082451613 | ... K35: =Data!R35 -> 0.089826973
A36: q/q | B36: =Data!I36 -> 0.0094594595 | C36: =Data!J36 -> 0.010709505 | D36: =Data!K36 -> -0.038410596 | E36: =Data!L36 -> 0.067493113 | F36: =Data!M36 -> 0.018322581 | G36: =Data!N36 -> 0.032564622 | H36: =Data!O36 -> -0.027978893 | I36: =Data!P36 -> 0.059083449 | ... K36: =Data!R36 -> 0.032914631
A37: 2-yr stack | B37: =Data!I37 -> 0.083568864 | C37: =Data!J37 -> 0.1051223 | D37: =Data!K37 -> 0.041668728 | E37: =Data!L37 -> 0.051367854 | F37: =Data!M37 -> 0.064589803 | G37: =Data!N37 -> 0.16099964 | H37: =Data!O37 -> 0.13415028 | I37: =Data!P37 -> 0.12974891 | ... K37: =Data!R37 -> 0.16916472
A38: Sequencing consumables ex-China ($M) | B38: =Data!I39 -> 707 | C38: =Data!J39 -> 713 | D38: =Data!K39 -> 687 | E38: =Data!L39 -> 734 | F38: =Data!M39 -> n/a | G38: =Data!N39 -> n/a | H38: =Data!O39 -> n/a | I38: =Data!P39 -> n/a | ... K38: =Data!R39 -> n/a
A39: y/y | B39: =Data!I40 -> 0.033625731 | C39: =Data!J40 -> 0.1140625 | D39: =Data!K40 -> 0.0734375 | E39: =Data!L40 -> 0.063768116 | F39: =Data!M40 -> n/a | G39: =Data!N40 -> n/a | H39: =Data!O40 -> n/a | I39: =Data!P40 -> n/a | ... K39: =Data!R40 -> n/a
A40: q/q | B40: =Data!I41 -> 0.024637681 | C40: =Data!J41 -> 0.0084865629 | D40: =Data!K41 -> -0.036465638 | E40: =Data!L41 -> 0.068413392 | F40: =Data!M41 -> n/a | G40: =Data!N41 -> n/a | H40: =Data!O41 -> n/a | I40: =Data!P41 -> n/a | ... K40: =Data!R41 -> n/a
A41: 2-yr stack | B41: =Data!I42 -> 0.12362573 | C41: =Data!J42 -> 0.1340625 | D41: =Data!K42 -> 0.070322235 | E41: =Data!L42 -> 0.07996841 | F41: =Data!M42 -> n/a | G41: =Data!N42 -> n/a | H41: =Data!O42 -> n/a | I41: =Data!P42 -> n/a | ... K41: =Data!R42 -> n/a
A42: Clinical vs research (ex-China sequencing consumables)
A43: Clinical, y/y | B43: =Data!I44 -> 0.12 | C43: =Data!J44 -> 0.2 | D43: =Data!K44 -> 0.2 | E43: =Data!L44 -> 0.15 | F43: =Data!M44 -> n/a | G43: =Data!N44 -> n/a | H43: =Data!O44 -> n/a | I43: =Data!P44 -> n/a | ... K43: =Data!R44 -> n/a
A44: 2-yr stack | B44: =Data!I45 -> 0.23 | C44: =Data!J45 -> 0.28 | D44: =Data!K45 -> 0.28 | E44: =Data!L45 -> 0.25 | F44: =Data!M45 -> n/a | G44: =Data!N45 -> n/a | H44: =Data!O45 -> n/a | I44: =Data!P45 -> n/a | ... K44: =Data!R45 -> n/a
A45: Research & applied, y/y | B45: =Data!I47 -> -0.08 | C45: =Data!J47 -> 0 | D45: =Data!K47 -> -0.12 | E45: =Data!L47 -> -0.07 | F45: =Data!M47 -> n/a | G45: =Data!N47 -> n/a | H45: =Data!O47 -> n/a | I45: =Data!P47 -> n/a | ... K45: =Data!R47 -> n/a
A46: 2-yr stack | B46: =Data!I48 -> -0.02 | C46: =Data!J48 -> -0.05 | D46: =Data!K48 -> -0.23 | E46: =Data!L48 -> -0.16 | F46: =Data!M48 -> n/a | G46: =Data!N48 -> n/a | H46: =Data!O48 -> n/a | I46: =Data!P48 -> n/a | ... K46: =Data!R48 -> n/a
A47: Volume and implied pricing
A48: Sequencing volume (Gb), y/y | B48: =Data!I158 -> >30% | C48: =Data!J158 -> >30% | D48: =Data!K158 -> >30% | E48: =Data!L158 -> >30% | F48: =Data!M158 -> n/a | G48: =Data!N158 -> n/a | H48: =Data!O158 -> n/a | I48: =Data!P158 -> n/a | ... K48: =Data!R158 -> n/a
A49: 2-yr stack | B49: =Data!I159 -> >70% | C49: =Data!J159 -> >60% | D49: =Data!K159 -> >60% | E49: =Data!L159 -> >60% | F49: =Data!M159 -> n/a | G49: =Data!N159 -> n/a | H49: =Data!O159 -> n/a | I49: =Data!P159 -> n/a | ... K49: =Data!R159 -> n/a
A50: X share of high-throughput Gb | B50: =Data!I96 -> 0.78 | C50: =Data!J96 -> 0.8 | D50: =Data!K96 -> 0.82 | E50: =Data!L96 -> 0.83 | F50: =Data!M96 -> n/a | G50: =Data!N96 -> n/a | H50: =Data!O96 -> n/a | I50: =Data!P96 -> n/a | ... K50: =Data!R96 -> n/a
A51: X share of high-throughput consumables revenue | B51: =Data!I98 -> 0.51 | C51: =Data!J98 -> 0.55 | D51: =Data!K98 -> 0.55 | E51: =Data!L98 -> 0.59 | F51: =Data!M98 -> n/a | G51: =Data!N98 -> n/a | H51: =Data!O98 -> n/a | I51: =Data!P98 -> n/a | ... K51: =Data!R98 -> n/a
A52: Implied revenue per Gb, y/y (at 30% Gb growth) | B52: =Data!I155 -> -0.22454064 | C52: =Data!J155 -> -0.16795239 | D52: =Data!K155 -> -0.19761273 | E52: =Data!L155 -> -0.19438669 | F52: =Data!M155 -> -0.18731336 | G52: =Data!N155 -> -0.16974019 | H52: =Data!O155 -> -0.16073321 | I52: =Data!P155 -> -0.16734491 | ... K52: =Data!R155 -> -0.16167156
A53: 2-yr stack | B53: =Data!I156 -> -0.39725472 | C53: =Data!J156 -> -0.38067515 | D53: =Data!K156 -> -0.42948559 | E53: =Data!L156 -> -0.42202473 | F53: =Data!M156 -> -0.411854 | G53: =Data!N156 -> -0.33769259 | H53: =Data!O156 -> -0.35834594 | I53: =Data!P156 -> -0.36173161 | ... K53: =Data!R156 -> -0.33141175
A54: Margins (single reportable segment since the GRAIL spin, Jun 2024: no segment margins)
A55: Adj. gross margin | B55: =Data!I100 -> 0.69188192 | C55: =Data!J100 -> 0.67040552 | D55: =Data!K100 -> 0.68194317 | E55: =Data!L100 -> 0.68162209 | F55: =Data!M100 -> 0.68844221 | G55: =Data!N100 -> 0.68683391 | H55: =Data!O100 -> 0.68747844 | I55: =Data!P100 -> 0.69149286 | ... K55: =Data!R100 -> 0.68993268
A56: y/y change (bps) | B56: =Data!I118 -> -127.47711 | C56: =Data!J118 -> -44.133186 | D56: =Data!K118 -> 75.915864 | E56: =Data!L118 -> -124.28903 | F56: =Data!M118 -> -34.397078 | G56: =Data!N118 -> 164.28385 | H56: =Data!O118 -> 55.352694 | I56: =Data!P118 -> 98.70768 | ... K56: =Data!R118 -> 30.98771
A57: q/q change (bps) | B57: =Data!I119 -> -21.690727 | C57: =Data!J119 -> -214.76397 | D57: =Data!K119 -> 115.37649 | E57: =Data!L119 -> -3.210834 | F57: =Data!M119 -> 68.20123 | G57: =Data!N119 -> -16.083039 | H57: =Data!O119 -> 6.4453364 | I57: =Data!P119 -> 40.144151 | ... K57: =Data!R119 -> -33.637748
A58: Adj. operating margin | B58: =Data!I102 -> 0.24446494 | C58: =Data!J102 -> 0.23727351 | D58: =Data!K102 -> 0.21906508 | E58: =Data!L102 -> 0.22433132 | F58: =Data!M102 -> 0.23999307 | G58: =Data!N102 -> 0.25536973 | H58: =Data!O102 -> 0.23447741 | I58: =Data!P102 -> 0.24618164 | ... K58: =Data!R102 -> 0.26719802
A59: y/y change (bps) | B59: =Data!I121 -> 185.39019 | C59: =Data!J121 -> 398.09744 | D59: =Data!K121 -> 154.14742 | E59: =Data!L121 -> -136.2902 | F59: =Data!M121 -> -44.718759 | G59: =Data!N121 -> 180.96221 | H59: =Data!O121 -> 154.12328 | I59: =Data!P121 -> 218.50319 | ... K59: =Data!R121 -> 118.28286
A60: q/q change (bps) | B60: =Data!I122 -> 65.046047 | C60: =Data!J122 -> -71.91433 | D60: =Data!K122 -> -182.08434 | E60: =Data!L122 -> 52.662422 | F60: =Data!M122 -> 156.61749 | G60: =Data!N122 -> 153.76664 | H60: =Data!O122 -> -208.92327 | I60: =Data!P122 -> 117.04233 | ... K60: =Data!R122 -> 106.89721
A61: Adj. EBITDA margin | B61: =Data!I104 -> 0.29059041 | C61: =Data!J104 -> 0.28041415 | D61: =Data!K104 -> 0.26672777 | E61: =Data!L104 -> 0.26919758 | F61: =Data!M104 -> 0.28617224 | G61: =Data!N104 -> 0.2995573 | H61: =Data!O104 -> 0.28009659 | I61: =Data!P104 -> 0.2910987 | ... K61: =Data!R104 -> 0.3097578
A62: y/y change (bps) | B62: =Data!I124 -> 128.12628 | C62: =Data!J124 -> 322.25744 | D62: =Data!K124 -> 131.25467 | E62: =Data!L124 -> -169.21396 | F62: =Data!M124 -> -44.181654 | G62: =Data!N124 -> 191.43154 | H62: =Data!O124 -> 133.68812 | I62: =Data!P124 -> 219.01118 | ... K62: =Data!R124 -> 102.00492
A63: q/q change (bps) | B63: =Data!I125 -> 44.714257 | C63: =Data!J125 -> -101.76256 | D63: =Data!K125 -> -136.86377 | E63: =Data!L125 -> 24.698114 | F63: =Data!M125 -> 169.74656 | G63: =Data!N125 -> 133.85064 | H63: =Data!O125 -> -194.60719 | I63: =Data!P125 -> 110.02118 | ... K63: =Data!R125 -> 88.303637
A64: Adj. net margin | B64: =Data!I106 -> 0.1900369 | C64: =Data!J106 -> 0.17946506 | D64: =Data!K106 -> 0.16223648 | E64: =Data!L106 -> 0.17256255 | F64: =Data!M106 -> 0.17943164 | G64: =Data!N106 -> 0.19273651 | H64: =Data!O106 -> 0.17497413 | I64: =Data!P106 -> 0.18705863 | ... K64: =Data!R106 -> 0.2039774
A65: y/y change (bps) | B65: =Data!I127 -> 224.44308 | C65: =Data!J127 -> 417.83897 | D65: =Data!K127 -> 143.01802 | E65: =Data!L127 -> -40.191269 | F65: =Data!M127 -> -106.05259 | G65: =Data!N127 -> 132.71458 | H65: =Data!O127 -> 127.37649 | I65: =Data!P127 -> 144.96076 | ... K65: =Data!R127 -> 112.4089
A66: q/q change (bps) | B66: =Data!I128 -> 134.5522 | C66: =Data!J128 -> -105.71844 | D66: =Data!K128 -> -172.28576 | E66: =Data!L128 -> 103.26074 | F66: =Data!M128 -> 68.69087 | G66: =Data!N128 -> 133.04873 | H66: =Data!O128 -> -177.62385 | I66: =Data!P128 -> 120.84501 | ... K66: =Data!R128 -> 88.09816
A67: GAAP gross margin | B67: =Data!I85 -> 0.676 | C67: =Data!J85 -> 0.655 | D67: =Data!K85 -> 0.661 | E67: =Data!L85 -> 0.664 | F67: =Data!M85 -> 0.6798 | G67: =Data!N85 -> 0.6744 | H67: =Data!O85 -> 0.6799 | I67: =Data!P85 -> 0.6848 | ... K67: =Data!R85 -> 0.6804
A68: y/y change (bps) | B68: =Data!I130 -> -130 | C68: =Data!J130 -> -40 | D68: =Data!K130 -> 50 | E68: =Data!L130 -> 80 | F68: =Data!M130 -> 38 | G68: =Data!N130 -> 194 | H68: =Data!O130 -> 189 | I68: =Data!P130 -> 208 | ... K68: =Data!R130 -> 60
A69: q/q change (bps) | B69: =Data!I131 -> 200 | C69: =Data!J131 -> -210 | D69: =Data!K131 -> 60 | E69: =Data!L131 -> 30 | F69: =Data!M131 -> 158 | G69: =Data!N131 -> -54 | H69: =Data!O131 -> 55 | I69: =Data!P131 -> 49 | ... K69: =Data!R131 -> -42
A70: GAAP operating margin | B70: =Data!I87 -> 0.21 | C70: =Data!J87 -> 0.174 | D70: =Data!K87 -> 0.192 | E70: =Data!L87 -> 0.211 | F70: =Data!M87 -> 0.2177 | G70: =Data!N87 -> 0.2278 | H70: =Data!O87 -> 0.218 | I70: =Data!P87 -> 0.2302 | ... K70: =Data!R87 -> 0.2432
A71: y/y change (bps) | B71: =Data!I133 -> -4760 | C71: =Data!J133 -> 160 | D71: =Data!K133 -> 340 | E71: =Data!L133 -> 90 | F71: =Data!M133 -> 77 | G71: =Data!N133 -> 538 | H71: =Data!O133 -> 260 | I71: =Data!P133 -> 192 | ... K71: =Data!R133 -> 154
A72: q/q change (bps) | B72: =Data!I134 -> 80 | C72: =Data!J134 -> -360 | D72: =Data!K134 -> 180 | E72: =Data!L134 -> 190 | F72: =Data!M134 -> 67 | G72: =Data!N134 -> 101 | H72: =Data!O134 -> -98 | I72: =Data!P134 -> 122 | ... K72: =Data!R134 -> 87
A73: Costs as % of revenue (non-GAAP)
A74: COGS | B74: =Data!I108 -> 0.30811808 | C74: =Data!J108 -> 0.32959448 | D74: =Data!K108 -> 0.31805683 | E74: =Data!L108 -> 0.31837791 | F74: =Data!M108 -> 0.31155779 | G74: =Data!N108 -> 0.31316609 | H74: =Data!O108 -> 0.31252156 | I74: =Data!P108 -> 0.30850714 | ... K74: =Data!R108 -> 0.31006732
A75: y/y change (bps) | B75: =Data!I136 -> 127.47711 | C75: =Data!J136 -> 44.133186 | D75: =Data!K136 -> -75.915864 | E75: =Data!L136 -> 124.28903 | F75: =Data!M136 -> 34.397078 | G75: =Data!N136 -> -164.28385 | H75: =Data!O136 -> -55.352694 | I75: =Data!P136 -> -98.70768 | ... K75: =Data!R136 -> -30.98771
A76: q/q change (bps) | B76: =Data!I137 -> 21.690727 | C76: =Data!J137 -> 214.76397 | D76: =Data!K137 -> -115.37649 | E76: =Data!L137 -> 3.210834 | F76: =Data!M137 -> -68.20123 | G76: =Data!N137 -> 16.083039 | H76: =Data!O137 -> -6.4453364 | I76: =Data!P137 -> -40.144151 | ... K76: =Data!R137 -> 33.637748
A77: R&D | B77: =Data!I110 -> 0.2103321 | C77: =Data!J110 -> 0.20534944 | D77: =Data!K110 -> 0.21906508 | E77: =Data!L110 -> 0.21742882 | F77: =Data!M110 -> 0.21356784 | G77: =Data!N110 -> 0.20429579 | H77: =Data!O110 -> 0.21222835 | I77: =Data!P110 -> 0.21243225 | ... K77: =Data!R110 -> 0.19979881
A78: y/y change (bps) | B78: =Data!I139 -> -202.23452 | C78: =Data!J139 -> -256.28822 | D78: =Data!K139 -> -124.43087 | E78: =Data!L139 -> -120.32938 | F78: =Data!M139 -> 32.357359 | G78: =Data!N139 -> -10.53653 | H78: =Data!O139 -> -68.367233 | I78: =Data!P139 -> -49.965631 | ... K78: =Data!R139 -> -44.969779
A79: q/q change (bps) | B79: =Data!I140 -> -191.29653 | C79: =Data!J140 -> -49.826641 | D79: =Data!K140 -> 137.15639 | E79: =Data!L140 -> -16.3626 | F79: =Data!M140 -> -38.609788 | G79: =Data!N140 -> -92.72053 | H79: =Data!O140 -> 79.325684 | I79: =Data!P140 -> 2.0390028 | ... K79: =Data!R140 -> -74.904855
A80: SG&A | B80: =Data!I112 -> 0.23616236 | C80: =Data!J112 -> 0.22778257 | D80: =Data!K112 -> 0.24472961 | E80: =Data!L112 -> 0.23986195 | F80: =Data!M112 -> 0.23479466 | G80: =Data!N112 -> 0.22380718 | H80: =Data!O112 -> 0.2396516 | I80: =Data!P112 -> 0.23320742 | ... K80: =Data!R112 -> 0.22038226
A81: y/y change (bps) | B81: =Data!I142 -> -119.85787 | C81: =Data!J142 -> -176.88443 | D81: =Data!K142 -> 64.971371 | E81: =Data!L142 -> 122.88768 | F81: =Data!M142 -> -13.676987 | G81: =Data!N142 -> -39.753897 | H81: =Data!O142 -> -50.780019 | I81: =Data!P142 -> -66.545267 | ... K81: =Data!R142 -> -34.249173
A82: q/q change (bps) | B82: =Data!I143 -> 85.891794 | C82: =Data!J143 -> -83.797904 | D82: =Data!K143 -> 169.47035 | E82: =Data!L143 -> -48.676559 | F82: =Data!M143 -> -50.67287 | G82: =Data!N143 -> -109.87481 | H82: =Data!O143 -> 158.44422 | I82: =Data!P143 -> -64.441808 | ... K82: =Data!R143 -> -76.522298
A83: Total opex (R&D + SG&A) | B83: =Data!I114 -> 0.44649446 | C83: =Data!J114 -> 0.43313201 | D83: =Data!K114 -> 0.46379468 | E83: =Data!L114 -> 0.45729077 | F83: =Data!M114 -> 0.4483625 | G83: =Data!N114 -> 0.42810297 | H83: =Data!O114 -> 0.45187996 | I83: =Data!P114 -> 0.44563968 | ... K83: =Data!R114 -> 0.42018107
A84: y/y change (bps) | B84: =Data!I145 -> -322.09239 | C84: =Data!J145 -> -433.17265 | D84: =Data!K145 -> -59.459502 | E84: =Data!L145 -> 2.5582928 | F84: =Data!M145 -> 18.680372 | G84: =Data!N145 -> -50.290427 | H84: =Data!O145 -> -119.14725 | I84: =Data!P145 -> -116.5109 | ... K84: =Data!R145 -> -79.218952
A85: q/q change (bps) | B85: =Data!I146 -> -105.40474 | C85: =Data!J146 -> -133.62455 | D85: =Data!K146 -> 306.62673 | E85: =Data!L146 -> -65.039159 | F85: =Data!M146 -> -89.282657 | G85: =Data!N146 -> -202.59534 | H85: =Data!O146 -> 237.76991 | I85: =Data!P146 -> -62.402805 | ... K85: =Data!R146 -> -151.42715
A86: Stock-based compensation (inside non-GAAP costs) | B86: =Data!I116 -> 0.064575646 | C86: =Data!J116 -> 0.054357204 | D86: =Data!K116 -> 0.054995417 | E86: =Data!L116 -> 0.062985332 | F86: =Data!M116 -> 0.064633512 | G86: =Data!N116 -> 0.060583702 | H86: =Data!O116 -> 0.068040704 | I86: =Data!P116 -> 0.060436853 | ... K86: =Data!R116 -> 0.056720576
A87: y/y change (bps) | B87: =Data!I148 -> n/a | C87: =Data!J148 -> n/a | D87: =Data!K148 -> -151.29463 | E87: =Data!L148 -> -21.704752 | F87: =Data!M148 -> 0.57866633 | G87: =Data!N148 -> 62.264978 | H87: =Data!O148 -> 130.45287 | I87: =Data!P148 -> -25.484788 | ... K87: =Data!R148 -> -38.631265
A88: q/q change (bps) | B88: =Data!I149 -> -5.8016161 | C88: =Data!J149 -> -102.18441 | D88: =Data!K149 -> 6.3821256 | E88: =Data!L149 -> 79.899151 | F88: =Data!M149 -> 16.481802 | G88: =Data!N149 -> -40.498101 | H88: =Data!O149 -> 74.570014 | I88: =Data!P149 -> -76.038503 | ... K88: =Data!R149 -> -34.811815
A89: Adj. tax rate | B89: =Data!I89 -> 0.186 | C89: =Data!J89 -> 0.195 | D89: =Data!K89 -> 0.205 | E89: =Data!L89 -> 0.205 | F89: =Data!M89 -> 0.204 | G89: =Data!N89 -> 0.204 | H89: =Data!O89 -> 0.2045 | I89: =Data!P89 -> 0.204 | ... K89: =Data!R89 -> 0.2041
A90: y/y change (bps) | B90: =Data!I151 -> -240 | C90: =Data!J151 -> -420 | D90: =Data!K151 -> -150 | E90: =Data!L151 -> -170 | F90: =Data!M151 -> 180 | G90: =Data!N151 -> 90 | H90: =Data!O151 -> -5 | I90: =Data!P151 -> -10 | ... K90: =Data!R151 -> 1
A91: q/q change (bps) | B91: =Data!I152 -> -360 | C91: =Data!J152 -> 90 | D91: =Data!K152 -> 100 | E91: =Data!L152 -> 0 | F91: =Data!M152 -> -10 | G91: =Data!N152 -> 0 | H91: =Data!O152 -> 5 | I91: =Data!P152 -> -5 | ... K91: =Data!R152 -> 0
A92: Non-GAAP EPS
A93: Non-GAAP EPS ($) | B93: =Data!I91 -> 1.34 | C93: =Data!J91 -> 1.35 | D93: =Data!K91 -> 1.15 | E93: =Data!L91 -> 1.31 | F93: =Data!M91 -> 1.36 | G93: =Data!N91 -> 1.54 | H93: =Data!O91 -> 1.35 | I93: =Data!P91 -> 1.47 | ... K93: =Data!R91 -> 1.71
A94: y/y | B94: =Data!I92 -> 0.1754386 | C94: =Data!J92 -> 0.42105263 | D94: =Data!K92 -> 0.18556701 | E94: =Data!L92 -> 0.10084034 | F94: =Data!M92 -> 0.014925373 | G94: =Data!N92 -> 0.14074074 | H94: =Data!O92 -> 0.17391304 | I94: =Data!P92 -> 0.1221374 | ... K94: =Data!R92 -> 0.11038961
A95: q/q | B95: =Data!I93 -> 0.12605042 | C95: =Data!J93 -> 0.0074626866 | D95: =Data!K93 -> -0.14814815 | E95: =Data!L93 -> 0.13913043 | F95: =Data!M93 -> 0.038167939 | G95: =Data!N93 -> 0.13235294 | H95: =Data!O93 -> -0.12337662 | I95: =Data!P93 -> 0.088888889 | ... K95: =Data!R93 -> 0.10322581
A96: 2-yr stack | B96: =Data!I94 -> n/a | C96: =Data!J94 -> n/a | D96: =Data!K94 -> 0.17536293 | E96: =Data!L94 -> 0.19258346 | F96: =Data!M94 -> 0.19036397 | G96: =Data!N94 -> 0.56179337 | H96: =Data!O94 -> 0.35948005 | I96: =Data!P94 -> 0.22297774 | ... K96: =Data!R94 -> 0.25113035
A98: Notes:
A99: 1. 2024 is Core Illumina (ex-GRAIL, spun 24 Jun 2024). Q3'24/Q4'24 y/y used in the 2-yr stacks are reported Core growth or derived from 10-Q/10-K line items (Q4'23, Q4'24 derived as FY less 9M).
A100: 2. Ex-China lines are the company's 'Rest of World' disclosure; consensus has no ex-China split by line, so ex-China estimates exist only for total revenue (total less consensus Greater China).
A101: 3. X placements are disclosed as lower bounds ('55+', '100+', '95+'; Q1'26 = 83). No consensus for placements, Gb volume or clinical/research split.
A102: 4. Gb volume is disclosed only as a floor ('>30%'); the 2-yr stack is the sum of the floors. Implied revenue per Gb = (1 + sequencing consumables growth) / 1.30 - 1.
...

Sheet Annual
A1: ILMN key numbers: annual (FY25 reported, FY26-FY30 consensus)
A2: $M unless noted. A = reported, E = Bloomberg consensus (10 Oct 2026). Non-GAAP unless noted. 2024 comparisons on a Core Illumina (ex-GRAIL) basis. n/a = not disclosed / no consensus.
A4: Metric | B4: FY25 | C4: FY26E | D4: FY27E | E4: FY28E | F4: FY29E | G4: FY30E
A5: Revenue
A6: Consolidated revenue ($M) | B6: =Data!W4 -> 4343 | C6: =Data!X4 -> 4624.8 | D6: =Data!Y4 -> 4918.3 | E6: =Data!Z4 -> 5262.8 | F6: =Data!AA4 -> 5649.7 | G6: =Data!AB4 -> 6087.9
A7: y/y | B7: =Data!W5 -> 0.0025392428 | C7: =Data!X5 -> 0.064886023 | D7: =Data!Y5 -> 0.063462204 | E7: =Data!Z5 -> 0.070044528 | F7: =Data!AA5 -> 0.073515999 | G7: =Data!AB5 -> 0.07756164
A8: 2-yr stack | B8: =Data!W7 -> -0.02134539 | C8: =Data!X7 -> 0.067425266 | D8: =Data!Y7 -> 0.12834823 | E8: =Data!Z7 -> 0.13350673 | F8: =Data!AA7 -> 0.14356053 | G8: =Data!AB7 -> 0.15107764
A9: Revenue ex-China ($M) | B9: =Data!W9 -> 4100 | C9: =Data!X9 -> 4414.1 | D9: =Data!Y9 -> 4729 | E9: =Data!Z9 -> 5075.7 | F9: =Data!AA9 -> 5419.8 | G9: =Data!AB9 -> 5881
A10: y/y | B10: =Data!W10 -> 0.01888668 | C10: =Data!X10 -> 0.076609756 | D10: =Data!Y10 -> 0.071339571 | E10: =Data!Z10 -> 0.073313597 | F10: =Data!AA10 -> 0.067793605 | G10: =Data!AB10 -> 0.085095391
A11: 2-yr stack | B11: =Data!W12 -> 0.011486581 | C11: =Data!X12 -> 0.095496436 | D11: =Data!Y12 -> 0.14794933 | E11: =Data!Z12 -> 0.14465317 | F11: =Data!AA12 -> 0.1411072 | G11: =Data!AB12 -> 0.152889
A12: Instrument placements
A13: NovaSeq X placements (units; lower bounds) | B13: =Data!W14 -> 265 | C13: =Data!X14 -> n/a | D13: =Data!Y14 -> n/a | E13: =Data!Z14 -> n/a | F13: =Data!AA14 -> n/a | G13: =Data!AB14 -> n/a
A14: y/y | B14: =Data!W15 -> -0.0037593985 | C14: =Data!X15 -> n/a | D14: =Data!Y15 -> n/a | E14: =Data!Z15 -> n/a | F14: =Data!AA15 -> n/a | G14: =Data!AB15 -> n/a
A15: 2-yr stack | B15: =Data!W17 -> -0.24807758 | C15: =Data!X17 -> n/a | D15: =Data!Y17 -> n/a | E15: =Data!Z17 -> n/a | F15: =Data!AA17 -> n/a | G15: =Data!AB17 -> n/a
A16: Clinical share of X placements | B16: =Data!W160 -> n/a | C16: =Data!X160 -> n/a | D16: =Data!Y160 -> n/a | E16: =Data!Z160 -> n/a | F16: =Data!AA160 -> n/a | G16: =Data!AB160 -> n/a
A17: Instruments
A18: Instruments revenue ($M) | B18: =Data!W19 -> 482 | C18: =Data!X19 -> 500.4 | D18: =Data!Y19 -> 469.7 | E18: =Data!Z19 -> 468.5 | F18: =Data!AA19 -> 464.6 | G18: =Data!AB19 -> 482.5
A19: y/y | B19: =Data!W20 -> -0.037924152 | C19: =Data!X20 -> 0.038174274 | D19: =Data!Y20 -> -0.061350919 | E19: =Data!Z20 -> -0.0025548222 | F19: =Data!AA20 -> -0.0083244397 | G19: =Data!AB20 -> 0.038527766
A20: 2-yr stack | B20: =Data!W22 -> -0.32627642 | C20: =Data!X22 -> 0.00025012216 | D20: =Data!Y22 -> -0.023176645 | E20: =Data!Z22 -> -0.063905741 | F20: =Data!AA22 -> -0.010879262 | G20: =Data!AB22 -> 0.030203326
A21: Sequencing instruments ex-China ($M) | B21: =Data!W24 -> 449 | C21: =Data!X24 -> n/a | D21: =Data!Y24 -> n/a | E21: =Data!Z24 -> n/a | F21: =Data!AA24 -> n/a | G21: =Data!AB24 -> n/a
A22: y/y | B22: =Data!W25 -> -0.0088300221 | C22: =Data!X25 -> n/a | D22: =Data!Y25 -> n/a | E22: =Data!Z25 -> n/a | F22: =Data!AA25 -> n/a | G22: =Data!AB25 -> n/a
A23: 2-yr stack | B23: =Data!W27 -> n/a | C23: =Data!X27 -> n/a | D23: =Data!Y27 -> n/a | E23: =Data!Z27 -> n/a | F23: =Data!AA27 -> n/a | G23: =Data!AB27 -> n/a
A24: Consumables
A25: Consumables revenue ($M) | B25: =Data!W29 -> 3227 | C25: =Data!X29 -> 3402.1 | D25: =Data!Y29 -> 3668.6 | E25: =Data!Z29 -> 3963.8 | F25: =Data!AA29 -> 4341.2 | G25: =Data!AB29 -> 4791.6
A26: y/y | B26: =Data!W30 -> 0.018302304 | C26: =Data!X30 -> 0.054260923 | D26: =Data!Y30 -> 0.07833397 | E26: =Data!Z30 -> 0.080466663 | F26: =Data!AA30 -> 0.095211666 | G26: =Data!AB30 -> 0.10375012
A27: 2-yr stack | B27: =Data!W32 -> 0.046197211 | C27: =Data!X32 -> 0.072563227 | D27: =Data!Y32 -> 0.13259489 | E27: =Data!Z32 -> 0.15880063 | F27: =Data!AA32 -> 0.17567833 | G27: =Data!AB32 -> 0.19896178
A28: Sequencing consumables ($M) | B28: =Data!W34 -> 2939 | C28: =Data!X34 -> 3104.4 | D28: =Data!Y34 -> 3378.4 | E28: =Data!Z34 -> 3694.2 | F28: =Data!AA34 -> 4034 | G28: =Data!AB34 -> 4478.8
A29: y/y | B29: =Data!W35 -> 0.023328691 | C29: =Data!X35 -> 0.056277645 | D29: =Data!Y35 -> 0.088261822 | E29: =Data!Z35 -> 0.093476202 | F29: =Data!AA35 -> 0.091982026 | G29: =Data!AB35 -> 0.11026277
A30: 2-yr stack | B30: =Data!W37 -> 0.052719372 | C30: =Data!X37 -> 0.079606336 | D30: =Data!Y37 -> 0.14453947 | E30: =Data!Z37 -> 0.18173802 | F30: =Data!AA37 -> 0.18545823 | G30: =Data!AB37 -> 0.20224479
A31: Sequencing consumables ex-China ($M) | B31: =Data!W39 -> 2750 | C31: =Data!X39 -> n/a | D31: =Data!Y39 -> n/a | E31: =Data!Z39 -> n/a | F31: =Data!AA39 -> n/a | G31: =Data!AB39 -> n/a
A32: y/y | B32: =Data!W40 -> 0.039697543 | C32: =Data!X40 -> n/a | D32: =Data!Y40 -> n/a | E32: =Data!Z40 -> n/a | F32: =Data!AA40 -> n/a | G32: =Data!AB40 -> n/a
A33: 2-yr stack | B33: =Data!W42 -> 0.079697543 | C33: =Data!X42 -> n/a | D33: =Data!Y42 -> n/a | E33: =Data!Z42 -> n/a | F33: =Data!AA42 -> n/a | G33: =Data!AB42 -> n/a
A34: Clinical vs research (ex-China sequencing consumables)
A35: Clinical, y/y | B35: =Data!W44 -> 0.12 | C35: =Data!X44 -> 0.15 | D35: =Data!Y44 -> n/a | E35: =Data!Z44 -> n/a | F35: =Data!AA44 -> n/a | G35: =Data!AB44 -> n/a
A36: 2-yr stack | B36: =Data!W45 -> 0.2 | C36: =Data!X45 -> 0.27 | D36: =Data!Y45 -> n/a | E36: =Data!Z45 -> n/a | F36: =Data!AA45 -> n/a | G36: =Data!AB45 -> n/a
A37: Research & applied, y/y | B37: =Data!W47 -> -0.07 | C37: =Data!X47 -> -0.075 | D37: =Data!Y47 -> n/a | E37: =Data!Z47 -> n/a | F37: =Data!AA47 -> n/a | G37: =Data!AB47 -> n/a
A38: 2-yr stack | B38: =Data!W48 -> -0.09 | C38: =Data!X48 -> -0.145 | D38: =Data!Y48 -> n/a | E38: =Data!Z48 -> n/a | F38: =Data!AA48 -> n/a | G38: =Data!AB48 -> n/a
A39: Volume and implied pricing
A40: Sequencing volume (Gb), y/y | B40: =Data!W158 -> >30% | C40: =Data!X158 -> n/a | D40: =Data!Y158 -> n/a | E40: =Data!Z158 -> n/a | F40: =Data!AA158 -> n/a | G40: =Data!AB158 -> n/a
A41: 2-yr stack | B41: =Data!W159 -> >60% | C41: =Data!X159 -> n/a | D41: =Data!Y159 -> n/a | E41: =Data!Z159 -> n/a | F41: =Data!AA159 -> n/a | G41: =Data!AB159 -> n/a
A42: X share of high-throughput Gb | B42: =Data!W96 -> n/a | C42: =Data!X96 -> n/a | D42: =Data!Y96 -> n/a | E42: =Data!Z96 -> n/a | F42: =Data!AA96 -> n/a | G42: =Data!AB96 -> n/a
A43: X share of high-throughput consumables revenue | B43: =Data!W98 -> n/a | C43: =Data!X98 -> n/a | D43: =Data!Y98 -> n/a | E43: =Data!Z98 -> n/a | F43: =Data!AA98 -> n/a | G43: =Data!AB98 -> n/a
A44: Implied revenue per Gb, y/y (at 30% Gb growth) | B44: =Data!W155 -> -0.21282408 | C44: =Data!X155 -> -0.18747873 | D44: =Data!Y155 -> -0.16287552 | E44: =Data!Z155 -> -0.15886446 | F44: =Data!AA155 -> -0.16001383 | G44: =Data!AB155 -> -0.14595172
A45: 2-yr stack | B45: =Data!W156 -> -0.4209851 | C45: =Data!X156 -> -0.40030282 | D45: =Data!Y156 -> -0.35035426 | E45: =Data!Z156 -> -0.32173998 | F45: =Data!AA156 -> -0.31887829 | G45: =Data!AB156 -> -0.30596554
A46: Margins (single reportable segment since the GRAIL spin, Jun 2024: no segment margins)
A47: Adj. gross margin | B47: =Data!W100 -> 0.68247755 | C47: =Data!X100 -> 0.68469988 | D47: =Data!Y100 -> 0.69050282 | E47: =Data!Z100 -> 0.69529528 | F47: =Data!AA100 -> 0.70030267 | G47: =Data!AB100 -> 0.70260681
A48: y/y change (bps) | B48: =Data!W118 -> -38.105386 | C48: =Data!X118 -> 22.223288 | D48: =Data!Y118 -> 58.029371 | E48: =Data!Z118 -> 47.924641 | F48: =Data!AA118 -> 50.073909 | G48: =Data!AB118 -> 23.041393
A49: Adj. operating margin | B49: =Data!W102 -> 0.23117661 | C49: =Data!X102 -> 0.23499395 | D49: =Data!Y102 -> 0.25220096 | E49: =Data!Z102 -> 0.26499202 | F49: =Data!AA102 -> 0.27679346 | G49: =Data!AB102 -> 0.2879975
A50: y/y change (bps) | B50: =Data!W121 -> 183.41888 | C50: =Data!X121 -> 38.173397 | D50: =Data!Y121 -> 172.07018 | E50: =Data!Z121 -> 127.91056 | F50: =Data!AA121 -> 118.01439 | G50: =Data!AB121 -> 112.04045
A51: Adj. EBITDA margin | B51: =Data!W104 -> 0.27814875 | C51: =Data!X104 -> 0.28050943 | D51: =Data!Y104 -> 0.29676921 | E51: =Data!Z104 -> 0.30928403 | F51: =Data!AA104 -> 0.32072499 | G51: =Data!AB104 -> 0.33016311
A52: y/y change (bps) | B52: =Data!W124 -> 136.05809 | C52: =Data!X124 -> 23.606823 | D52: =Data!Y124 -> 162.59781 | E52: =Data!Z124 -> 125.14822 | F52: =Data!AA124 -> 114.40963 | G52: =Data!AB124 -> 94.381162
A53: Adj. net margin | B53: =Data!W106 -> 0.17407322 | C53: =Data!X106 -> 0.17752119 | D53: =Data!Y106 -> 0.19039099 | E53: =Data!Z106 -> 0.20392187 | F53: =Data!AA106 -> 0.21627697 | G53: =Data!AB106 -> 0.23669903
A54: y/y change (bps) | B54: =Data!W127 -> 210.2613 | C54: =Data!X127 -> 34.479688 | D54: =Data!Y127 -> 128.69799 | E54: =Data!Z127 -> 135.30878 | F54: =Data!AA127 -> 123.55104 | G54: =Data!AB127 -> 204.22055
A55: GAAP gross margin | B55: =Data!W85 -> 0.661 | C55: =Data!X85 -> 0.6749 | D55: =Data!Y85 -> 0.6823 | E55: =Data!Z85 -> 0.6864 | F55: =Data!AA85 -> 0.6897 | G55: =Data!AB85 -> 0.69
A56: y/y change (bps) | B56: =Data!W130 -> -100 | C56: =Data!X130 -> 139 | D56: =Data!Y130 -> 74 | E56: =Data!Z130 -> 41 | F56: =Data!AA130 -> 33 | G56: =Data!AB130 -> 3
A57: GAAP operating margin | B57: =Data!W87 -> 0.1858 | C57: =Data!X87 -> 0.2126 | D57: =Data!Y87 -> 0.2319 | E57: =Data!Z87 -> 0.25 | F57: =Data!AA87 -> 0.2644 | G57: =Data!AB87 -> 0.2789
A58: y/y change (bps) | B58: =Data!W133 -> -1542 | C58: =Data!X133 -> 268 | D58: =Data!Y133 -> 193 | E58: =Data!Z133 -> 181 | F58: =Data!AA133 -> 144 | G58: =Data!AB133 -> 145
A59: Costs as % of revenue (non-GAAP)
A60: COGS | B60: =Data!W108 -> 0.31752245 | C60: =Data!X108 -> 0.31530012 | D60: =Data!Y108 -> 0.30949718 | E60: =Data!Z108 -> 0.30470472 | F60: =Data!AA108 -> 0.29969733 | G60: =Data!AB108 -> 0.29739319
A61: y/y change (bps) | B61: =Data!W136 -> 38.105386 | C61: =Data!X136 -> -22.223288 | D61: =Data!Y136 -> -58.029371 | E61: =Data!Z136 -> -47.924641 | F61: =Data!AA136 -> -50.073909 | G61: =Data!AB136 -> -23.041393
A62: R&D | B62: =Data!W110 -> 0.2187428 | C62: =Data!X110 -> 0.2128092 | D62: =Data!Y110 -> 0.20738873 | E62: =Data!Z110 -> 0.20126169 | F62: =Data!AA110 -> 0.1944705 | G62: =Data!AB110 -> 0.17999639
A63: y/y change (bps) | B63: =Data!W139 -> -79.423294 | C63: =Data!X139 -> -59.33602 | D63: =Data!Y139 -> -54.204707 | E63: =Data!Z139 -> -61.270461 | F63: =Data!AA139 -> -67.911829 | G63: =Data!AB139 -> -144.74117
A64: SG&A | B64: =Data!W112 -> 0.23232788 | C64: =Data!X112 -> 0.235621 | D64: =Data!Y112 -> 0.22802594 | E64: =Data!Z112 -> 0.22127005 | F64: =Data!AA112 -> 0.21848948 | G64: =Data!AB112 -> 0.22487229
A65: y/y change (bps) | B65: =Data!W142 -> -144.40352 | C65: =Data!X142 -> 32.931159 | D65: =Data!Y142 -> -75.950559 | E65: =Data!Z142 -> -67.558976 | F65: =Data!AA142 -> -27.80569 | G65: =Data!AB142 -> 63.828103
A66: Total opex (R&D + SG&A) | B66: =Data!W114 -> 0.45107069 | C66: =Data!X114 -> 0.4484302 | D66: =Data!Y114 -> 0.43541468 | E66: =Data!Z114 -> 0.42253173 | F66: =Data!AA114 -> 0.41295998 | G66: =Data!AB114 -> 0.40486867
A67: y/y change (bps) | B67: =Data!W145 -> -223.82682 | C67: =Data!X145 -> -26.404861 | D67: =Data!Y145 -> -130.15527 | E67: =Data!Z145 -> -128.82944 | F67: =Data!AA145 -> -95.71752 | G67: =Data!AB145 -> -80.913062
A68: Stock-based compensation (inside non-GAAP costs) | B68: =Data!W116 -> 0.063320286 | C68: =Data!X116 -> 0.06097561 | D68: =Data!Y116 -> 0.060142732 | E68: =Data!Z116 -> 0.059208026 | F68: =Data!AA116 -> 0.057418978 | G68: =Data!AB116 -> 0.058066
A69: y/y change (bps) | B69: =Data!W148 -> n/a | C69: =Data!X148 -> -23.446758 | D69: =Data!Y148 -> -8.3287751 | E69: =Data!Z148 -> -9.347061 | F69: =Data!AA148 -> -17.890481 | G69: =Data!AB148 -> 6.4702177
A70: Adj. tax rate | B70: =Data!W89 -> 0.205 | C70: =Data!X89 -> 0.2049 | D70: =Data!Y89 -> 0.2046 | E70: =Data!Z89 -> 0.2043 | F70: =Data!AA89 -> 0.2065 | G70: =Data!AB89 -> 0.2112
A71: y/y change (bps) | B71: =Data!W151 -> -310 | C71: =Data!X151 -> -1 | D71: =Data!Y151 -> -3 | E71: =Data!Z151 -> -3 | F71: =Data!AA151 -> 22 | G71: =Data!AB151 -> 47
A72: Non-GAAP EPS
A73: Non-GAAP EPS ($) | B73: =Data!W91 -> 4.84 | C73: =Data!X91 -> 5.36 | D73: =Data!Y91 -> 6.11 | E73: =Data!Z91 -> 7.01 | F73: =Data!AA91 -> 7.99 | G73: =Data!AB91 -> 9.5
A74: y/y | B74: =Data!W92 -> 0.16346154 | C74: =Data!X92 -> 0.10743802 | D74: =Data!Y92 -> 0.13992537 | E74: =Data!Z92 -> 0.14729951 | F74: =Data!AA92 -> 0.13980029 | G74: =Data!AB92 -> 0.18898623
A75: 2-yr stack | B75: =Data!W94 -> n/a | C75: =Data!X94 -> 0.27089955 | D75: =Data!Y94 -> 0.24736339 | E75: =Data!Z94 -> 0.28722488 | F75: =Data!AA94 -> 0.28709979 | G75: =Data!AB94 -> 0.32878652
A77: Notes:
A78: 1. 2024 is Core Illumina (ex-GRAIL, spun 24 Jun 2024). Q3'24/Q4'24 y/y used in the 2-yr stacks are reported Core growth or derived from 10-Q/10-K line items (Q4'23, Q4'24 derived as FY less 9M).
A79: 2. Ex-China lines are the company's 'Rest of World' disclosure; consensus has no ex-China split by line, so ex-China estimates exist only for total revenue (total less consensus Greater China).
A80: 3. X placements are disclosed as lower bounds ('55+', '100+', '95+'; Q1'26 = 83). No consensus for placements, Gb volume or clinical/research split.
A81: 4. Gb volume is disclosed only as a floor ('>30%'); the 2-yr stack is the sum of the floors. Implied revenue per Gb = (1 + sequencing consumables growth) / 1.30 - 1.
A82: 5. Adj. EBITDA = adj. operating income + depreciation (ties to Bloomberg for 2025-26; Bloomberg's own EBITDA line diverges in 2027E+ and is broken for Q2'26).
A83: 6. Estimate margins use Bloomberg's consensus margin lines (gross and operating), because its gross-profit and operating-income dollar lines do not tie to them in 2028E-30E. Bloomberg's R&D and SG&A lines also do not tie to its operating income in outer years, so cost ratios for 2028E-30E are indicative.
A84: 9. GAAP operating margin y/y for Q3'25 and FY25 is distorted by the Q3'24 reversal of the EU fine (Q3'24 GAAP operating margin 68.6%).
A85: 7. FY26 is a 53-week year; management says the extra week falls in Q4'26, 'largely a consumables story', worth ~0.5pt of revenue.
A86: 8. FY26E clinical/research = company guidance (mid-teens; mid- to high-single-digit decline), not consensus.

Sheet Addendum
A1: A. GAAP to non-GAAP adjustments ($M)
A2: Stock-based compensation is NOT added back: it stays inside non-GAAP costs (only its book-vs-tax difference is adjusted in the tax line). Source: ILMN earnings decks' reconciliation tables.
A3: Item | B3: Q3'25 | C3: Q4'25 | D3: FY25 | E3: Q1'26 | F3: Q2'26
A4: GAAP gross profit | B4: 733 | C4: 759 | D4: 2870 | E4: 721 | F4: 770
A5: + Amortization of acquired intangibles (COGS) | B5: 16 | C5: 16 | D5: 66 | E5: 17 | F5: 18
A6: + Other acquisition-related (COGS; incl. SomaLogic inventory step-up) | B6: 0 | C6: 0 | D6: 0 | E6: 6 | F6: 2
A7: + Transformational initiatives (COGS) | B7: 1 | C7: 2 | D7: 5 | E7: 0 | F7: 0
A8: + Intangible impairment (COGS, Q2'25) | B8: 0 | C8: 0 | D8: 23 | E8: 0 | F8: 0
A9: NON-GAAP GROSS PROFIT | B9: 750 | C9: 777 | D9: 2964 | E9: 744 | F9: 790
A10: GAAP operating income | B10: 227 | C10: 202 | D10: 807 | E10: 209 | F10: 245
A11: + Cost-of-revenue items (above) | B11: 17 | C11: 18 | D11: 94 | E11: 23 | F11: 20
A12: + R&D items | B12: 1 | C12: 1 | D12: 17 | E12: 1 | F12: 0
A13: + SG&A items (acquisition, transformation, other) | B13: 20 | C13: 46 | D13: 76 | E13: 7 | F13: -5
A14: + Legal contingency and settlement | B14: 0 | C14: 8 | D14: 10 | E14: 0 | F14: 0
A15: NON-GAAP OPERATING INCOME | B15: 265 | C15: 275 | D15: 1004 | E15: 239 | F15: 260
... A19: NON-GAAP NET INCOME | B19: 206 | C19: 208 | D19: 756 | E19: 178 | F19: 200
A21: What sits inside the buckets:
A22: - Acquisition-related: intangible amortization ($16-18M a quarter); SomaLogic/GRAIL legal and deal costs; contingent-consideration fair-value changes (gains of $16M in both Q1'26 and Q2'26 reduce the add-back); SomaLogic inventory step-up ($6M Q1'26, $2M Q2'26); a lease impairment ($4M, Q3'25).
A23: - Transformational initiatives: severance ($47M FY25) and ERP upgrade costs ($14M FY25; ERP only in 2026).
A24: - Other (Q4'25): $19M Illumina Foundation donation; FY25 also $3M board changes and $2M legal accrual.
A25: - Strategic investments: mark-to-market on holdings (mainly GRAIL stock); FY25 gain of $333M ($192M in Q4'25) excluded; Q1'26 loss $37M excluded.
A26: - Tax: Q3'25 excludes a one-time $42M valuation allowance on foreign tax credits (FY $62M); GILTI/Pillar Two (GRAIL losses) items ended in 2025.
A27: - Definition notes: 2024 shown Core vs consolidated (FY24 non-GAAP EPS $4.16 Core vs $2.45 consolidated); inventory step-up add-back new from Q1'26; deferred-comp cost sits in non-GAAP opex (~60bps of Q2'26 margin) and is offset in other income; Q1'26/Q2'26 decks dropped the net-income reconciliation (non-GAAP NI here derived).
A29: B. Commentary on consumables margins
A30: Illumina does not disclose margin by product. What is said:
A31: - MGMT (Q4'23): NovaSeq X consumables were 'designed so margins at scale would be comparable' to the 6000's; early X margins lower, normalizing through 2024.
A32: - MGMT (Aug 2024 strategy update): consumables pull-through 'drives almost 70% gross margin'; the X transition's lower pricing is 'strategically a drag'.
A33: - MGMT (Q3'24): gross margin 70.5% (+450bps), about half from consumables mix; X-transition price impact 'closer towards 25 rather than 20' (%).
... A40: C. Walk-down of $1 of revenue (FY25 reported; FY26E consensus)
A41: Line | B41: FY25 non-GAAP $M | C41: per $1 | D41: FY25 GAAP $M | E41: per $1 | F41: FY26E non-GAAP $M | G41: per $1
A42: Revenue | B42: 4343 | C42: =B42/B$42 -> 1 | D42: 4343 | E42: =D42/D$42 -> 1 | F42: 4624.8 | G42: =F42/F$42 -> 1
A43: (-) Cost of revenue | B43: -1379 | C43: =B43/B$42 -> -0.31752245 | D43: -1473 | E43: =D43/D$42 -> -0.33916647 | F43: -1464.1 | G43: =F43/F$42 -> -0.31657585
A44: GROSS PROFIT | B44: 2964 | C44: =B44/B$42 -> 0.68247755 | D44: 2870 | E44: =D44/D$42 -> 0.66083353 | F44: 3160.7 | G44: =F44/F$42 -> 0.68342415
A45: (-) R&D | B45: -950 | C45: =B45/B$42 -> -0.2187428 | D45: -967 | E45: =D45/D$42 -> -0.22265715 | F45: -984.2 | G45: =F45/F$42 -> -0.2128092
A46: (-) SG&A | B46: -1009 | C46: =B46/B$42 -> -0.23232788 | D46: -1086 | E46: =D46/D$42 -> -0.25005756 | F46: -1089.7 | G46: =F46/F$42 -> -0.235621
A47: (-) Legal contingency / other | B47: 0 | C47: =B47/B$42 -> 0 | D47: -10 | E47: =D47/D$42 -> -0.0023025558 | F47: 0 | G47: =F47/F$42 -> 0
A48: OPERATING INCOME | B48: 1004 | C48: =B48/B$42 -> 0.23117661 | D48: 807 | E48: =D48/D$42 -> 0.18581626 | F48: 1088.5 | G48: =F48/F$42 -> 0.23536153
A49: (+/-) Other income / expense, net | B49: -54 | C49: =B49/B$42 -> -0.012433802 | D49: 279 | E49: =D49/D$42 -> 0.064241308 | F49: -57.8 | G49: =F49/F$42 -> -0.012497838
A50: PRE-TAX INCOME | B50: 950 | C50: =B50/B$42 -> 0.2187428 | D50: 1086 | E50: =D50/D$42 -> 0.25005756 | F50: 1030.7 | G50: =F50/F$42 -> 0.22286369
A51: (-) Income tax | B51: -194 | C51: =B51/B$42 -> -0.044669583 | D51: -236 | E51: =D51/D$42 -> -0.054340318 | F51: -211.2 | G51: =F51/F$42 -> -0.04566684
A52: NET INCOME | B52: 756 | C52: =B52/B$42 -> 0.17407322 | D52: 850 | E52: =D52/D$42 -> 0.19571725 | F52: 821 | G52: =F52/F$42 -> 0.17752119
A53: Memo: stock-based comp (non-cash, inside costs) | B53: 275 | C53: =B53/B$42 -> 0.063320286 | D53: 275 | E53: =D53/D$42 -> 0.063320286 | F53: 282 | G53: =F53/F$42 -> 0.06097561
... A56: Memo: free cash flow | B56: 931 | C56: =B56/B$42 -> 0.21436795 | D56: 931 | E56: =D56/D$42 -> 0.21436795 | F56: 997 | G56: =F56/F$42 -> 0.21557689
A58: How to read it: of each FY25 revenue dollar, ~32c goes to cost of revenue, ~22c to R&D and ~23c to SG&A, leaving ~23c of non-GAAP operating profit and ~17c of non-GAAP net income. ~6c of costs is non-cash stock comp; free cash flow is ~21c.
A59: GAAP vs non-GAAP: GAAP adds ~1.5c of intangible amortization and ~2c of acquisition/restructuring/legal costs, but FY25 GAAP net income is higher (~20c) because of a $333M gain on strategic investments (mainly GRAIL stock).
A60: Sources: FY25 10-K and Q4'25 deck reconciliation; FY26E = Bloomberg consensus (10 Oct 2026); FY26E other expense and tax derived from consensus pre-tax income and tax rate.

Sheet Data
A1: ILMN data: inputs (blue) and formulas (black). $M unless noted. Sources: ILMN decks, 10-Q/10-K, calls; Bloomberg consensus 10 Oct 2026.
A3: Metric | B3: Row | C3: Q1'24 | D3: Q2'24 | E3: Q3'24 | F3: Q4'24 | G3: Q1'25 | H3: Q2'25 | I3: Q3'25 | J3: Q4'25 | K3: Q1'26 | L3: Q2'26 | M3: Q3'26E | N3: Q4'26E | O3: Q1'27E | P3: Q2'27E | Q3: Q3'27E | R3: Q4'27E | T3: Annual | U3: FY23 | V3: FY24 | W3: FY25 | X3: FY26E | Y3: FY27E | Z3: FY28E | AA3: FY29E | AB3: FY30E
A4: Consolidated revenue ($M) | B4: value | C4: 1056 | D4: 1092 | E4: 1080 | F4: 1104 | G4: 1041 | H4: 1059 | I4: 1084 | J4: 1159 | K4: 1091 | L4: 1159 | M4: 1154.2 | N4: 1219.8 | O4: 1159.6 | P4: 1217.8 | Q4: 1229.2 | R4: 1292.3 | U4: 4438 | V4: 4332 | W4: 4343 | X4: 4624.8 | Y4: 4918.3 | Z4: 5262.8 | AA4: 5649.7 | AB4: 6087.9 | AD4: 2024 = Core Illumina (ex-GRAIL); Q3'24/Q4'24 y/y = reported Core growth
A5: Consolidated revenue ($M) y/y | B5: yoy | C5: n/a | D5: n/a | E5: -0.02 | F5: 0.01 | G5: =IF(AND(ISNUMBER(G4),ISNUMBER(C4)),G4/C4-1,"n/a") -> -0.014204545 | H5: =IF(AND(ISNUMBER(H4),ISNUMBER(D4)),H4/D4-1,"n/a") -> -0.03021978 | I5: =IF(AND(ISNUMBER(I4),ISNUMBER(E4)),I4/E4-1,"n/a") -> 0.0037037037 | J5: =IF(AND(ISNUMBER(J4),ISNUMBER(F4)),J4/F4-1,"n/a") -> 0.049818841 | K5: =IF(AND(ISNUMBER(K4),ISNUMBER(G4)),K4/G4-1,"n/a") -> 0.04803074 | L5: =IF(AND(ISNUMBER(L4),ISNUMBER(H4)),L4/H4-1,"n/a") -> 0.094428706 | M5: =IF(AND(ISNUMBER(M4),ISNUMBER(I4)),M4/I4-1,"n/a") -> 0.064760148 | N5: =IF(AND(ISNUMBER(N4),ISNUMBER(J4)),N4/J4-1,"n/a") -> 0.052459016 | ... R5: =IF(AND(ISNUMBER(R4),ISNUMBER(N4)),R4/N4-1,"n/a") -> 0.059435973 | U5: n/a | V5: =IF(AND(ISNUMBER(V4),ISNUMBER(U4)),V4/U4-1,"n/a") -> -0.023884633 | W5: =IF(AND(ISNUMBER(W4),ISNUMBER(V4)),W4/V4-1,"n/a") -> 0.0025392428 | X5: =IF(AND(ISNUMBER(X4),ISNUMBER(W4)),X4/W4-1,"n/a") -> 0.064886023 | Y5: =IF(AND(ISNUMBER(Y4),ISNUMBER(X4)),Y4/X4-1,"n/a") -> 0.063462204 | Z5: =IF(AND(ISNUMBER(Z4),ISNUMBER(Y4)),Z4/Y4-1,"n/a") -> 0.070044528 | AA5: =IF(AND(ISNUMBER(AA4),ISNUMBER(Z4)),AA4/Z4-1,"n/a") -> 0.073515999 | AB5: =IF(AND(ISNUMBER(AB4),ISNUMBER(AA4)),AB4/AA4-1,"n/a") -> 0.07756164
A6: Consolidated revenue ($M) q/q | B6: qoq | C6: n/a | D6: =IF(AND(ISNUMBER(D4),ISNUMBER(C4)),D4/C4-1,"n/a") -> 0.034090909 | E6: =IF(AND(ISNUMBER(E4),ISNUMBER(D4)),E4/D4-1,"n/a") -> -0.010989011 | F6: =IF(AND(ISNUMBER(F4),ISNUMBER(E4)),F4/E4-1,"n/a") -> 0.022222222 | G6: =IF(AND(ISNUMBER(G4),ISNUMBER(F4)),G4/F4-1,"n/a") -> -0.057065217 | H6: =IF(AND(ISNUMBER(H4),ISNUMBER(G4)),H4/G4-1,"n/a") -> 0.017291066 | I6: =IF(AND(ISNUMBER(I4),ISNUMBER(H4)),I4/H4-1,"n/a") -> 0.023607177 | J6: =IF(AND(ISNUMBER(J4),ISNUMBER(I4)),J4/I4-1,"n/a") -> 0.069188192 | K6: =IF(AND(ISNUMBER(K4),ISNUMBER(J4)),K4/J4-1,"n/a") -> -0.058671268 | ... R6: =IF(AND(ISNUMBER(R4),ISNUMBER(Q4)),R4/Q4-1,"n/a") -> 0.051334201 | U6: n/a | V6: n/a | W6: n/a | X6: n/a | Y6: n/a | Z6: n/a | AA6: n/a | AB6: n/a
A7: Consolidated revenue ($M) 2-yr stack | B7: stk | C7: n/a | D7: n/a | E7: n/a | F7: n/a | G7: =IF(AND(ISNUMBER(G5),ISNUMBER(C5)),G5+C5,"n/a") -> n/a | H7: =IF(AND(ISNUMBER(H5),ISNUMBER(D5)),H5+D5,"n/a") -> n/a | I7: =IF(AND(ISNUMBER(I5),ISNUMBER(E5)),I5+E5,"n/a") -> -0.016296296 | J7: =IF(AND(ISNUMBER(J5),ISNUMBER(F5)),J5+F5,"n/a") -> 0.059818841 | K7: =IF(AND(ISNUMBER(K5),ISNUMBER(G5)),K5+G5,"n/a") -> 0.033826194 | L7: =IF(AND(ISNUMBER(L5),ISNUMBER(H5)),L5+H5,"n/a") -> 0.064208926 | M7: =IF(AND(ISNUMBER(M5),ISNUMBER(I5)),M5+I5,"n/a") -> 0.068463851 | N7: =IF(AND(ISNUMBER(N5),ISNUMBER(J5)),N5+J5,"n/a") -> 0.10227786 | ... R7: =IF(AND(ISNUMBER(R5),ISNUMBER(N5)),R5+N5,"n/a") -> 0.11189499 | U7: n/a | V7: n/a | W7: =IF(AND(ISNUMBER(W5),ISNUMBER(V5)),W5+V5,"n/a") -> -0.02134539 | X7: =IF(AND(ISNUMBER(X5),ISNUMBER(W5)),X5+W5,"n/a") -> 0.067425266 | Y7: =IF(AND(ISNUMBER(Y5),ISNUMBER(X5)),Y5+X5,"n/a") -> 0.12834823 | Z7: =IF(AND(ISNUMBER(Z5),ISNUMBER(Y5)),Z5+Y5,"n/a") -> 0.13350673 | AA7: =IF(AND(ISNUMBER(AA5),ISNUMBER(Z5)),AA5+Z5,"n/a") -> 0.14356053 | AB7: =IF(AND(ISNUMBER(AB5),ISNUMBER(AA5)),AB5+AA5,"n/a") -> 0.15107764
A9: Revenue ex-China ($M) | B9: value | C9: 978 | D9: 1017 | E9: 1005 | F9: 1024 | G9: 969 | H9: 996 | I9: 1032 | J9: 1104 | K9: 1039 | L9: 1103 | M9: 1103.4 | N9: 1167.9 | O9: 1115 | P9: 1170.8 | Q9: 1182.7 | R9: 1243.4 | U9: 4054 | V9: 4024 | W9: 4100 | X9: 4414.1 | Y9: 4729 | Z9: 5075.7 | AA9: 5419.8 | AB9: 5881 | AD9: Total less Greater China; estimates = consensus total less consensus Greater China
A10: Revenue ex-China ($M) y/y | B10: yoy | C10: n/a | D10: n/a | E10: n/a | F10: n/a | G10: =IF(AND(ISNUMBER(G9),ISNUMBER(C9)),G9/C9-1,"n/a") -> -0.009202454 | H10: =IF(AND(ISNUMBER(H9),ISNUMBER(D9)),H9/D9-1,"n/a") -> -0.020648968 | I10: =IF(AND(ISNUMBER(I9),ISNUMBER(E9)),I9/E9-1,"n/a") -> 0.026865672 | J10: =IF(AND(ISNUMBER(J9),ISNUMBER(F9)),J9/F9-1,"n/a") -> 0.078125 | K10: =IF(AND(ISNUMBER(K9),ISNUMBER(G9)),K9/G9-1,"n/a") -> 0.072239422 | L10: =IF(AND(ISNUMBER(L9),ISNUMBER(H9)),L9/H9-1,"n/a") -> 0.10742972 | M10: =IF(AND(ISNUMBER(M9),ISNUMBER(I9)),M9/I9-1,"n/a") -> 0.069186047 | N10: =IF(AND(ISNUMBER(N9),ISNUMBER(J9)),N9/J9-1,"n/a") -> 0.057880435 | ... R10: =IF(AND(ISNUMBER(R9),ISNUMBER(N9)),R9/N9-1,"n/a") -> 0.064645946 | U10: n/a | V10: =IF(AND(ISNUMBER(V9),ISNUMBER(U9)),V9/U9-1,"n/a") -> -0.0074000987 | W10: =IF(AND(ISNUMBER(W9),ISNUMBER(V9)),W9/V9-1,"n/a") -> 0.01888668 | X10: =IF(AND(ISNUMBER(X9),ISNUMBER(W9)),X9/W9-1,"n/a") -> 0.076609756 | Y10: =IF(AND(ISNUMBER(Y9),ISNUMBER(X9)),Y9/X9-1,"n/a") -> 0.071339571 | Z10: =IF(AND(ISNUMBER(Z9),ISNUMBER(Y9)),Z9/Y9-1,"n/a") -> 0.073313597 | AA10: =IF(AND(ISNUMBER(AA9),ISNUMBER(Z9)),AA9/Z9-1,"n/a") -> 0.067793605 | AB10: =IF(AND(ISNUMBER(AB9),ISNUMBER(AA9)),AB9/AA9-1,"n/a") -> 0.085095391
A11: Revenue ex-China ($M) q/q | B11: qoq | C11: n/a | D11: =IF(AND(ISNUMBER(D9),ISNUMBER(C9)),D9/C9-1,"n/a") -> 0.039877301 | E11: =IF(AND(ISNUMBER(E9),ISNUMBER(D9)),E9/D9-1,"n/a") -> -0.01179941 | F11: =IF(AND(ISNUMBER(F9),ISNUMBER(E9)),F9/E9-1,"n/a") -> 0.018905473 | G11: =IF(AND(ISNUMBER(G9),ISNUMBER(F9)),G9/F9-1,"n/a") -> -0.053710938 | H11: =IF(AND(ISNUMBER(H9),ISNUMBER(G9)),H9/G9-1,"n/a") -> 0.027863777 | I11: =IF(AND(ISNUMBER(I9),ISNUMBER(H9)),I9/H9-1,"n/a") -> 0.036144578 | J11: =IF(AND(ISNUMBER(J9),ISNUMBER(I9)),J9/I9-1,"n/a") -> 0.069767442 | K11: =IF(AND(ISNUMBER(K9),ISNUMBER(J9)),K9/J9-1,"n/a") -> -0.058876812 | ... R11: =IF(AND(ISNUMBER(R9),ISNUMBER(Q9)),R9/Q9-1,"n/a") -> 0.051323243 | U11: n/a | V11: n/a | W11: n/a | X11: n/a | Y11: n/a | Z11: n/a | AA11: n/a | AB11: n/a
A12: Revenue ex-China ($M) 2-yr stack | B12: stk | C12: n/a | D12: n/a | E12: n/a | F12: n/a | G12: =IF(AND(ISNUMBER(G10),ISNUMBER(C10)),G10+C10,"n/a") -> n/a | H12: =IF(AND(ISNUMBER(H10),ISNUMBER(D10)),H10+D10,"n/a") -> n/a | I12: =IF(AND(ISNUMBER(I10),ISNUMBER(E10)),I10+E10,"n/a") -> n/a | J12: =IF(AND(ISNUMBER(J10),ISNUMBER(F10)),J10+F10,"n/a") -> n/a | K12: =IF(AND(ISNUMBER(K10),ISNUMBER(G10)),K10+G10,"n/a") -> 0.063036968 | L12: =IF(AND(ISNUMBER(L10),ISNUMBER(H10)),L10+H10,"n/a") -> 0.086780751 | M12: =IF(AND(ISNUMBER(M10),ISNUMBER(I10)),M10+I10,"n/a") -> 0.096051718 | N12: =IF(AND(ISNUMBER(N10),ISNUMBER(J10)),N10+J10,"n/a") -> 0.13600543 | ... R12: =IF(AND(ISNUMBER(R10),ISNUMBER(N10)),R10+N10,"n/a") -> 0.12252638 | U12: n/a | V12: n/a | W12: =IF(AND(ISNUMBER(W10),ISNUMBER(V10)),W10+V10,"n/a") -> 0.011486581 | X12: =IF(AND(ISNUMBER(X10),ISNUMBER(W10)),X10+W10,"n/a") -> 0.095496436 | Y12: =IF(AND(ISNUMBER(Y10),ISNUMBER(X10)),Y10+X10,"n/a") -> 0.14794933 | Z12: =IF(AND(ISNUMBER(Z10),ISNUMBER(Y10)),Z10+Y10,"n/a") -> 0.14465317 | AA12: =IF(AND(ISNUMBER(AA10),ISNUMBER(Z10)),AA10+Z10,"n/a") -> 0.1411072 | AB12: =IF(AND(ISNUMBER(AB10),ISNUMBER(AA10)),AB10+AA10,"n/a") -> 0.152889
A14: NovaSeq X placements (units) | B14: value | C14: 55 | D14: 62 | E14: 58 | F14: 91 | G14: 60 | H14: 50 | I14: 55 | J14: 100 | K14: 83 | L14: 95 | M14: n/a | N14: n/a | O14: n/a | P14: n/a | Q14: n/a | R14: n/a | U14: 352 | V14: 266 | W14: 265 | X14: n/a | Y14: n/a | Z14: n/a | AA14: n/a | AB14: n/a | AD14: Disclosed as lower bounds (e.g. '55+', '100+', '95+'); no consensus
A15: NovaSeq X placements (units) y/y | B15: yoy | C15: n/a | D15: n/a | E15: -0.40206186 | F15: 0.15189873 | G15: =IF(AND(ISNUMBER(G14),ISNUMBER(C14)),G14/C14-1,"n/a") -> 0.090909091 | H15: =IF(AND(ISNUMBER(H14),ISNUMBER(D14)),H14/D14-1,"n/a") -> -0.19354839 | I15: =IF(AND(ISNUMBER(I14),ISNUMBER(E14)),I14/E14-1,"n/a") -> -0.051724138 | J15: =IF(AND(ISNUMBER(J14),ISNUMBER(F14)),J14/F14-1,"n/a") -> 0.098901099 | K15: =IF(AND(ISNUMBER(K14),ISNUMBER(G14)),K14/G14-1,"n/a") -> 0.38333333 | L15: =IF(AND(ISNUMBER(L14),ISNUMBER(H14)),L14/H14-1,"n/a") -> 0.9 | M15: =IF(AND(ISNUMBER(M14),ISNUMBER(I14)),M14/I14-1,"n/a") -> n/a | N15: =IF(AND(ISNUMBER(N14),ISNUMBER(J14)),N14/J14-1,"n/a") -> n/a | ... R15: =IF(AND(ISNUMBER(R14),ISNUMBER(N14)),R14/N14-1,"n/a") -> n/a | U15: n/a | V15: =IF(AND(ISNUMBER(V14),ISNUMBER(U14)),V14/U14-1,"n/a") -> -0.24431818 | W15: =IF(AND(ISNUMBER(W14),ISNUMBER(V14)),W14/V14-1,"n/a") -> -0.0037593985 | X15: =IF(AND(ISNUMBER(X14),ISNUMBER(W14)),X14/W14-1,"n/a") -> n/a | Y15: =IF(AND(ISNUMBER(Y14),ISNUMBER(X14)),Y14/X14-1,"n/a") -> n/a | Z15: =IF(AND(ISNUMBER(Z14),ISNUMBER(Y14)),Z14/Y14-1,"n/a") -> n/a | AA15: =IF(AND(ISNUMBER(AA14),ISNUMBER(Z14)),AA14/Z14-1,"n/a") -> n/a | AB15: =IF(AND(ISNUMBER(AB14),ISNUMBER(AA14)),AB14/AA14-1,"n/a") -> n/a
A16: NovaSeq X placements (units) q/q | B16: qoq | C16: n/a | D16: =IF(AND(ISNUMBER(D14),ISNUMBER(C14)),D14/C14-1,"n/a") -> 0.12727273 | E16: =IF(AND(ISNUMBER(E14),ISNUMBER(D14)),E14/D14-1,"n/a") -> -0.064516129 | F16: =IF(AND(ISNUMBER(F14),ISNUMBER(E14)),F14/E14-1,"n/a") -> 0.56896552 | G16: =IF(AND(ISNUMBER(G14),ISNUMBER(F14)),G14/F14-1,"n/a") -> -0.34065934 | H16: =IF(AND(ISNUMBER(H14),ISNUMBER(G14)),H14/G14-1,"n/a") -> -0.16666667 | I16: =IF(AND(ISNUMBER(I14),ISNUMBER(H14)),I14/H14-1,"n/a") -> 0.1 | J16: =IF(AND(ISNUMBER(J14),ISNUMBER(I14)),J14/I14-1,"n/a") -> 0.81818182 | K16: =IF(AND(ISNUMBER(K14),ISNUMBER(J14)),K14/J14-1,"n/a") -> -0.17 | ... R16: =IF(AND(ISNUMBER(R14),ISNUMBER(Q14)),R14/Q14-1,"n/a") -> n/a | U16: n/a | V16: n/a | W16: n/a | X16: n/a | Y16: n/a | Z16: n/a | AA16: n/a | AB16: n/a
A17: NovaSeq X placements (units) 2-yr stack | B17: stk | C17: n/a | D17: n/a | E17: n/a | F17: n/a | G17: =IF(AND(ISNUMBER(G15),ISNUMBER(C15)),G15+C15,"n/a") -> n/a | H17: =IF(AND(ISNUMBER(H15),ISNUMBER(D15)),H15+D15,"n/a") -> n/a | I17: =IF(AND(ISNUMBER(I15),ISNUMBER(E15)),I15+E15,"n/a") -> -0.45378599 | J17: =IF(AND(ISNUMBER(J15),ISNUMBER(F15)),J15+F15,"n/a") -> 0.25079983 | K17: =IF(AND(ISNUMBER(K15),ISNUMBER(G15)),K15+G15,"n/a") -> 0.47424242 | L17: =IF(AND(ISNUMBER(L15),ISNUMBER(H15)),L15+H15,"n/a") -> 0.70645161 | M17: =IF(AND(ISNUMBER(M15),ISNUMBER(I15)),M15+I15,"n/a") -> n/a | N17: =IF(AND(ISNUMBER(N15),ISNUMBER(J15)),N15+J15,"n/a") -> n/a | ... R17: =IF(AND(ISNUMBER(R15),ISNUMBER(N15)),R15+N15,"n/a") -> n/a | U17: n/a | V17: n/a | W17: =IF(AND(ISNUMBER(W15),ISNUMBER(V15)),W15+V15,"n/a") -> -0.24807758 | X17: =IF(AND(ISNUMBER(X15),ISNUMBER(W15)),X15+W15,"n/a") -> n/a | Y17: =IF(AND(ISNUMBER(Y15),ISNUMBER(X15)),Y15+X15,"n/a") -> n/a | Z17: =IF(AND(ISNUMBER(Z15),ISNUMBER(Y15)),Z15+Y15,"n/a") -> n/a | AA17: =IF(AND(ISNUMBER(AA15),ISNUMBER(Z15)),AA15+Z15,"n/a") -> n/a | AB17: =IF(AND(ISNUMBER(AB15),ISNUMBER(AA15)),AB15+AA15,"n/a") -> n/a
A19: Instruments revenue ($M) | B19: value | C19: 114 | D19: 120 | E19: 107 | F19: 159 | G19: 112 | H19: 101 | I19: 111 | J19: 158 | K19: 120 | L19: 130 | M19: 115.2 | N19: 131.5 | O19: 111.1 | P19: 114 | Q19: 111.6 | R19: 126.8 | U19: 704 | V19: 501 | W19: 482 | X19: 500.4 | Y19: 469.7 | Z19: 468.5 | AA19: 464.6 | AB19: 482.5 | AD19: Sequencing + microarray instruments
A20: Instruments revenue ($M) y/y | B20: yoy | C20: n/a | D20: n/a | E20: -0.41208791 | F20: -0.047904192 | G20: =IF(AND(ISNUMBER(G19),ISNUMBER(C19)),G19/C19-1,"n/a") -> -0.01754386 | H20: =IF(AND(ISNUMBER(H19),ISNUMBER(D19)),H19/D19-1,"n/a") -> -0.15833333 | I20: =IF(AND(ISNUMBER(I19),ISNUMBER(E19)),I19/E19-1,"n/a") -> 0.037383178 | J20: =IF(AND(ISNUMBER(J19),ISNUMBER(F19)),J19/F19-1,"n/a") -> -0.0062893082 | K20: =IF(AND(ISNUMBER(K19),ISNUMBER(G19)),K19/G19-1,"n/a") -> 0.071428571 | L20: =IF(AND(ISNUMBER(L19),ISNUMBER(H19)),L19/H19-1,"n/a") -> 0.28712871 | M20: =IF(AND(ISNUMBER(M19),ISNUMBER(I19)),M19/I19-1,"n/a") -> 0.037837838 | N20: =IF(AND(ISNUMBER(N19),ISNUMBER(J19)),N19/J19-1,"n/a") -> -0.16772152 | ... R20: =IF(AND(ISNUMBER(R19),ISNUMBER(N19)),R19/N19-1,"n/a") -> -0.035741445 | U20: n/a | V20: =IF(AND(ISNUMBER(V19),ISNUMBER(U19)),V19/U19-1,"n/a") -> -0.28835227 | W20: =IF(AND(ISNUMBER(W19),ISNUMBER(V19)),W19/V19-1,"n/a") -> -0.037924152 | X20: =IF(AND(ISNUMBER(X19),ISNUMBER(W19)),X19/W19-1,"n/a") -> 0.038174274 | Y20: =IF(AND(ISNUMBER(Y19),ISNUMBER(X19)),Y19/X19-1,"n/a") -> -0.061350919 | Z20: =IF(AND(ISNUMBER(Z19),ISNUMBER(Y19)),Z19/Y19-1,"n/a") -> -0.0025548222 | AA20: =IF(AND(ISNUMBER(AA19),ISNUMBER(Z19)),AA19/Z19-1,"n/a") -> -0.0083244397 | AB20: =IF(AND(ISNUMBER(AB19),ISNUMBER(AA19)),AB19/AA19-1,"n/a") -> 0.038527766
A21: Instruments revenue ($M) q/q | B21: qoq | C21: n/a | D21: =IF(AND(ISNUMBER(D19),ISNUMBER(C19)),D19/C19-1,"n/a") -> 0.052631579 | E21: =IF(AND(ISNUMBER(E19),ISNUMBER(D19)),E19/D19-1,"n/a") -> -0.10833333 | F21: =IF(AND(ISNUMBER(F19),ISNUMBER(E19)),F19/E19-1,"n/a") -> 0.48598131 | G21: =IF(AND(ISNUMBER(G19),ISNUMBER(F19)),G19/F19-1,"n/a") -> -0.29559748 | H21: =IF(AND(ISNUMBER(H19),ISNUMBER(G19)),H19/G19-1,"n/a") -> -0.098214286 | I21: =IF(AND(ISNUMBER(I19),ISNUMBER(H19)),I19/H19-1,"n/a") -> 0.099009901 | J21: =IF(AND(ISNUMBER(J19),ISNUMBER(I19)),J19/I19-1,"n/a") -> 0.42342342 | K21: =IF(AND(ISNUMBER(K19),ISNUMBER(J19)),K19/J19-1,"n/a") -> -0.24050633 | ... R21: =IF(AND(ISNUMBER(R19),ISNUMBER(Q19)),R19/Q19-1,"n/a") -> 0.13620072 | U21: n/a | V21: n/a | W21: n/a | X21: n/a | Y21: n/a | Z21: n/a | AA21: n/a | AB21: n/a
A22: Instruments revenue ($M) 2-yr stack | B22: stk | C22: n/a | D22: n/a | E22: n/a | F22: n/a | G22: =IF(AND(ISNUMBER(G20),ISNUMBER(C20)),G20+C20,"n/a") -> n/a | H22: =IF(AND(ISNUMBER(H20),ISNUMBER(D20)),H20+D20,"n/a") -> n/a | I22: =IF(AND(ISNUMBER(I20),ISNUMBER(E20)),I20+E20,"n/a") -> -0.37470473 | J22: =IF(AND(ISNUMBER(J20),ISNUMBER(F20)),J20+F20,"n/a") -> -0.0541935 | K22: =IF(AND(ISNUMBER(K20),ISNUMBER(G20)),K20+G20,"n/a") -> 0.053884712 | L22: =IF(AND(ISNUMBER(L20),ISNUMBER(H20)),L20+H20,"n/a") -> 0.12879538 | M22: =IF(AND(ISNUMBER(M20),ISNUMBER(I20)),M20+I20,"n/a") -> 0.075221015 | N22: =IF(AND(ISNUMBER(N20),ISNUMBER(J20)),N20+J20,"n/a") -> -0.17401083 | ... R22: =IF(AND(ISNUMBER(R20),ISNUMBER(N20)),R20+N20,"n/a") -> -0.20346296 | U22: n/a | V22: n/a | W22: =IF(AND(ISNUMBER(W20),ISNUMBER(V20)),W20+V20,"n/a") -> -0.32627642 | X22: =IF(AND(ISNUMBER(X20),ISNUMBER(W20)),X20+W20,"n/a") -> 0.00025012216 | Y22: =IF(AND(ISNUMBER(Y20),ISNUMBER(X20)),Y20+X20,"n/a") -> -0.023176645 | Z22: =IF(AND(ISNUMBER(Z20),ISNUMBER(Y20)),Z20+Y20,"n/a") -> -0.063905741 | AA22: =IF(AND(ISNUMBER(AA20),ISNUMBER(Z20)),AA20+Z20,"n/a") -> -0.010879262 | AB22: =IF(AND(ISNUMBER(AB20),ISNUMBER(AA20)),AB20+AA20,"n/a") -> 0.030203326
A24: Sequencing instruments ex-China ($M) | B24: value | C24: 100 | D24: 111 | E24: 98 | F24: 144 | G24: 103 | H24: 92 | I24: 104 | J24: 150 | K24: 114 | L24: 122 | M24: n/a | N24: n/a | O24: n/a | P24: n/a | Q24: n/a | R24: n/a | U24: n/a | V24: 453 | W24: 449 | X24: n/a | Y24: n/a | Z24: n/a | AA24: n/a | AB24: n/a | AD24: Company 'Rest of World' disclosure; no consensus by region and line
A25: Sequencing instruments ex-China ($M) y/y | B25: yoy | C25: n/a | D25: n/a | E25: n/a | F25: n/a | G25: =IF(AND(ISNUMBER(G24),ISNUMBER(C24)),G24/C24-1,"n/a") -> 0.03 | H25: =IF(AND(ISNUMBER(H24),ISNUMBER(D24)),H24/D24-1,"n/a") -> -0.17117117 | I25: =IF(AND(ISNUMBER(I24),ISNUMBER(E24)),I24/E24-1,"n/a") -> 0.06122449 | J25: =IF(AND(ISNUMBER(J24),ISNUMBER(F24)),J24/F24-1,"n/a") -> 0.041666667 | K25: =IF(AND(ISNUMBER(K24),ISNUMBER(G24)),K24/G24-1,"n/a") -> 0.10679612 | L25: =IF(AND(ISNUMBER(L24),ISNUMBER(H24)),L24/H24-1,"n/a") -> 0.32608696 | M25: =IF(AND(ISNUMBER(M24),ISNUMBER(I24)),M24/I24-1,"n/a") -> n/a | N25: =IF(AND(ISNUMBER(N24),ISNUMBER(J24)),N24/J24-1,"n/a") -> n/a | ... R25: =IF(AND(ISNUMBER(R24),ISNUMBER(N24)),R24/N24-1,"n/a") -> n/a | U25: n/a | V25: =IF(AND(ISNUMBER(V24),ISNUMBER(U24)),V24/U24-1,"n/a") -> n/a | W25: =IF(AND(ISNUMBER(W24),ISNUMBER(V24)),W24/V24-1,"n/a") -> -0.0088300221 | X25: =IF(AND(ISNUMBER(X24),ISNUMBER(W24)),X24/W24-1,"n/a") -> n/a | Y25: =IF(AND(ISNUMBER(Y24),ISNUMBER(X24)),Y24/X24-1,"n/a") -> n/a | Z25: =IF(AND(ISNUMBER(Z24),ISNUMBER(Y24)),Z24/Y24-1,"n/a") -> n/a | AA25: =IF(AND(ISNUMBER(AA24),ISNUMBER(Z24)),AA24/Z24-1,"n/a") -> n/a | AB25: =IF(AND(ISNUMBER(AB24),ISNUMBER(AA24)),AB24/AA24-1,"n/a") -> n/a
A26: Sequencing instruments ex-China ($M) q/q | B26: qoq | C26: n/a | D26: =IF(AND(ISNUMBER(D24),ISNUMBER(C24)),D24/C24-1,"n/a") -> 0.11 | E26: =IF(AND(ISNUMBER(E24),ISNUMBER(D24)),E24/D24-1,"n/a") -> -0.11711712 | F26: =IF(AND(ISNUMBER(F24),ISNUMBER(E24)),F24/E24-1,"n/a") -> 0.46938776 | G26: =IF(AND(ISNUMBER(G24),ISNUMBER(F24)),G24/F24-1,"n/a") -> -0.28472222 | H26: =IF(AND(ISNUMBER(H24),ISNUMBER(G24)),H24/G24-1,"n/a") -> -0.10679612 | I26: =IF(AND(ISNUMBER(I24),ISNUMBER(H24)),I24/H24-1,"n/a") -> 0.13043478 | J26: =IF(AND(ISNUMBER(J24),ISNUMBER(I24)),J24/I24-1,"n/a") -> 0.44230769 | K26: =IF(AND(ISNUMBER(K24),ISNUMBER(J24)),K24/J24-1,"n/a") -> -0.24 | ... R26: =IF(AND(ISNUMBER(R24),ISNUMBER(Q24)),R24/Q24-1,"n/a") -> n/a | U26: n/a | V26: n/a | W26: n/a | X26: n/a | Y26: n/a | Z26: n/a | AA26: n/a | AB26: n/a
A27: Sequencing instruments ex-China ($M) 2-yr stack | B27: stk | C27: n/a | D27: n/a | E27: n/a | F27: n/a | G27: =IF(AND(ISNUMBER(G25),ISNUMBER(C25)),G25+C25,"n/a") -> n/a | H27: =IF(AND(ISNUMBER(H25),ISNUMBER(D25)),H25+D25,"n/a") -> n/a | I27: =IF(AND(ISNUMBER(I25),ISNUMBER(E25)),I25+E25,"n/a") -> n/a | J27: =IF(AND(ISNUMBER(J25),ISNUMBER(F25)),J25+F25,"n/a") -> n/a | K27: =IF(AND(ISNUMBER(K25),ISNUMBER(G25)),K25+G25,"n/a") -> 0.13679612 | L27: =IF(AND(ISNUMBER(L25),ISNUMBER(H25)),L25+H25,"n/a") -> 0.15491579 | M27: =IF(AND(ISNUMBER(M25),ISNUMBER(I25)),M25+I25,"n/a") -> n/a | N27: =IF(AND(ISNUMBER(N25),ISNUMBER(J25)),N25+J25,"n/a") -> n/a | ... R27: =IF(AND(ISNUMBER(R25),ISNUMBER(N25)),R25+N25,"n/a") -> n/a | U27: n/a | V27: n/a | W27: =IF(AND(ISNUMBER(W25),ISNUMBER(V25)),W25+V25,"n/a") -> n/a | X27: =IF(AND(ISNUMBER(X25),ISNUMBER(W25)),X25+W25,"n/a") -> n/a | Y27: =IF(AND(ISNUMBER(Y25),ISNUMBER(X25)),Y25+X25,"n/a") -> n/a | Z27: =IF(AND(ISNUMBER(Z25),ISNUMBER(Y25)),Z25+Y25,"n/a") -> n/a | AA27: =IF(AND(ISNUMBER(AA25),ISNUMBER(Z25)),AA25+Z25,"n/a") -> n/a | AB27: =IF(AND(ISNUMBER(AB25),ISNUMBER(AA25)),AB25+AA25,"n/a") -> n/a
A29: Consumables revenue ($M) | B29: value | C29: 768 | D29: 815 | E29: 807 | F29: 779 | G29: 768 | H29: 811 | I29: 816 | J29: 832 | K29: 797 | L29: 852 | M29: 861 | N29: 894.2 | O29: 862.8 | P29: 914.1 | Q29: 931.5 | R29: 966.6 | U29: 3083 | V29: 3169 | W29: 3227 | X29: 3402.1 | Y29: 3668.6 | Z29: 3963.8 | AA29: 4341.2 | AB29: 4791.6 | AD29: Sequencing + microarray consumables
A30: Consumables revenue ($M) y/y | B30: yoy | C30: n/a | D30: n/a | E30: 0.053524804 | F30: 0.03042328 | G30: =IF(AND(ISNUMBER(G29),ISNUMBER(C29)),G29/C29-1,"n/a") -> 0 | H30: =IF(AND(ISNUMBER(H29),ISNUMBER(D29)),H29/D29-1,"n/a") -> -0.0049079755 | I30: =IF(AND(ISNUMBER(I29),ISNUMBER(E29)),I29/E29-1,"n/a") -> 0.011152416 | J30: =IF(AND(ISNUMBER(J29),ISNUMBER(F29)),J29/F29-1,"n/a") -> 0.068035944 | K30: =IF(AND(ISNUMBER(K29),ISNUMBER(G29)),K29/G29-1,"n/a") -> 0.037760417 | L30: =IF(AND(ISNUMBER(L29),ISNUMBER(H29)),L29/H29-1,"n/a") -> 0.050554871 | M30: =IF(AND(ISNUMBER(M29),ISNUMBER(I29)),M29/I29-1,"n/a") -> 0.055147059 | N30: =IF(AND(ISNUMBER(N29),ISNUMBER(J29)),N29/J29-1,"n/a") -> 0.074759615 | ... R30: =IF(AND(ISNUMBER(R29),ISNUMBER(N29)),R29/N29-1,"n/a") -> 0.080966227 | U30: n/a | V30: =IF(AND(ISNUMBER(V29),ISNUMBER(U29)),V29/U29-1,"n/a") -> 0.027894908 | W30: =IF(AND(ISNUMBER(W29),ISNUMBER(V29)),W29/V29-1,"n/a") -> 0.018302304 | X30: =IF(AND(ISNUMBER(X29),ISNUMBER(W29)),X29/W29-1,"n/a") -> 0.054260923 | Y30: =IF(AND(ISNUMBER(Y29),ISNUMBER(X29)),Y29/X29-1,"n/a") -> 0.07833397 | Z30: =IF(AND(ISNUMBER(Z29),ISNUMBER(Y29)),Z29/Y29-1,"n/a") -> 0.080466663 | AA30: =IF(AND(ISNUMBER(AA29),ISNUMBER(Z29)),AA29/Z29-1,"n/a") -> 0.095211666 | AB30: =IF(AND(ISNUMBER(AB29),ISNUMBER(AA29)),AB29/AA29-1,"n/a") -> 0.10375012
A31: Consumables revenue ($M) q/q | B31: qoq | C31: n/a | D31: =IF(AND(ISNUMBER(D29),ISNUMBER(C29)),D29/C29-1,"n/a") -> 0.061197917 | E31: =IF(AND(ISNUMBER(E29),ISNUMBER(D29)),E29/D29-1,"n/a") -> -0.0098159509 | F31: =IF(AND(ISNUMBER(F29),ISNUMBER(E29)),F29/E29-1,"n/a") -> -0.034696406 | G31: =IF(AND(ISNUMBER(G29),ISNUMBER(F29)),G29/F29-1,"n/a") -> -0.014120668 | H31: =IF(AND(ISNUMBER(H29),ISNUMBER(G29)),H29/G29-1,"n/a") -> 0.055989583 | I31: =IF(AND(ISNUMBER(I29),ISNUMBER(H29)),I29/H29-1,"n/a") -> 0.0061652281 | J31: =IF(AND(ISNUMBER(J29),ISNUMBER(I29)),J29/I29-1,"n/a") -> 0.019607843 | K31: =IF(AND(ISNUMBER(K29),ISNUMBER(J29)),K29/J29-1,"n/a") -> -0.042067308 | ... R31: =IF(AND(ISNUMBER(R29),ISNUMBER(Q29)),R29/Q29-1,"n/a") -> 0.037681159 | U31: n/a | V31: n/a | W31: n/a | X31: n/a | Y31: n/a | Z31: n/a | AA31: n/a | AB31: n/a
A32: Consumables revenue ($M) 2-yr stack | B32: stk | C32: n/a | D32: n/a | E32: n/a | F32: n/a | G32: =IF(AND(ISNUMBER(G30),ISNUMBER(C30)),G30+C30,"n/a") -> n/a | H32: =IF(AND(ISNUMBER(H30),ISNUMBER(D30)),H30+D30,"n/a") -> n/a | I32: =IF(AND(ISNUMBER(I30),ISNUMBER(E30)),I30+E30,"n/a") -> 0.064677221 | J32: =IF(AND(ISNUMBER(J30),ISNUMBER(F30)),J30+F30,"n/a") -> 0.098459224 | K32: =IF(AND(ISNUMBER(K30),ISNUMBER(G30)),K30+G30,"n/a") -> 0.037760417 | L32: =IF(AND(ISNUMBER(L30),ISNUMBER(H30)),L30+H30,"n/a") -> 0.045646895 | M32: =IF(AND(ISNUMBER(M30),ISNUMBER(I30)),M30+I30,"n/a") -> 0.066299475 | N32: =IF(AND(ISNUMBER(N30),ISNUMBER(J30)),N30+J30,"n/a") -> 0.14279556 | ... R32: =IF(AND(ISNUMBER(R30),ISNUMBER(N30)),R30+N30,"n/a") -> 0.15572584 | U32: n/a | V32: n/a | W32: =IF(AND(ISNUMBER(W30),ISNUMBER(V30)),W30+V30,"n/a") -> 0.046197211 | X32: =IF(AND(ISNUMBER(X30),ISNUMBER(W30)),X30+W30,"n/a") -> 0.072563227 | Y32: =IF(AND(ISNUMBER(Y30),ISNUMBER(X30)),Y30+X30,"n/a") -> 0.13259489 | Z32: =IF(AND(ISNUMBER(Z30),ISNUMBER(Y30)),Z30+Y30,"n/a") -> 0.15880063 | AA32: =IF(AND(ISNUMBER(AA30),ISNUMBER(Z30)),AA30+Z30,"n/a") -> 0.17567833 | AB32: =IF(AND(ISNUMBER(AB30),ISNUMBER(AA30)),AB30+AA30,"n/a") -> 0.19896178
A34: Sequencing consumables ($M) | B34: value | C34: 697 | D34: 737 | E34: 741 | F34: 698 | G34: 696 | H34: 740 | I34: 747 | J34: 755 | K34: 726 | L34: 775 | M34: 789.2 | N34: 814.9 | O34: 792.1 | P34: 838.9 | Q34: 859.8 | R34: 888.1 | U34: 2790 | V34: 2872 | W34: 2939 | X34: 3104.4 | Y34: 3378.4 | Z34: 3694.2 | AA34: 4034 | AB34: 4478.8 | AD34: Q4'24 derived from FY; Q3'23/Q4'23 from 10-Q/10-K
A35: Sequencing consumables ($M) y/y | B35: yoy | C35: n/a | D35: n/a | E35: 0.075471698 | F35: 0.023460411 | G35: =IF(AND(ISNUMBER(G34),ISNUMBER(C34)),G34/C34-1,"n/a") -> -0.0014347202 | H35: =IF(AND(ISNUMBER(H34),ISNUMBER(D34)),H34/D34-1,"n/a") -> 0.0040705563 | I35: =IF(AND(ISNUMBER(I34),ISNUMBER(E34)),I34/E34-1,"n/a") -> 0.008097166 | J35: =IF(AND(ISNUMBER(J34),ISNUMBER(F34)),J34/F34-1,"n/a") -> 0.081661891 | K35: =IF(AND(ISNUMBER(K34),ISNUMBER(G34)),K34/G34-1,"n/a") -> 0.043103448 | L35: =IF(AND(ISNUMBER(L34),ISNUMBER(H34)),L34/H34-1,"n/a") -> 0.047297297 | M35: =IF(AND(ISNUMBER(M34),ISNUMBER(I34)),M34/I34-1,"n/a") -> 0.056492637 | N35: =IF(AND(ISNUMBER(N34),ISNUMBER(J34)),N34/J34-1,"n/a") -> 0.079337748 | ... R35: =IF(AND(ISNUMBER(R34),ISNUMBER(N34)),R34/N34-1,"n/a") -> 0.089826973 | U35: n/a | V35: =IF(AND(ISNUMBER(V34),ISNUMBER(U34)),V34/U34-1,"n/a") -> 0.029390681 | W35: =IF(AND(ISNUMBER(W34),ISNUMBER(V34)),W34/V34-1,"n/a") -> 0.023328691 | X35: =IF(AND(ISNUMBER(X34),ISNUMBER(W34)),X34/W34-1,"n/a") -> 0.056277645 | Y35: =IF(AND(ISNUMBER(Y34),ISNUMBER(X34)),Y34/X34-1,"n/a") -> 0.088261822 | Z35: =IF(AND(ISNUMBER(Z34),ISNUMBER(Y34)),Z34/Y34-1,"n/a") -> 0.093476202 | AA35: =IF(AND(ISNUMBER(AA34),ISNUMBER(Z34)),AA34/Z34-1,"n/a") -> 0.091982026 | AB35: =IF(AND(ISNUMBER(AB34),ISNUMBER(AA34)),AB34/AA34-1,"n/a") -> 0.11026277
A36: Sequencing consumables ($M) q/q | B36: qoq | C36: n/a | D36: =IF(AND(ISNUMBER(D34),ISNUMBER(C34)),D34/C34-1,"n/a") -> 0.057388809 | E36: =IF(AND(ISNUMBER(E34),ISNUMBER(D34)),E34/D34-1,"n/a") -> 0.0054274084 | F36: =IF(AND(ISNUMBER(F34),ISNUMBER(E34)),F34/E34-1,"n/a") -> -0.05802969 | G36: =IF(AND(ISNUMBER(G34),ISNUMBER(F34)),G34/F34-1,"n/a") -> -0.0028653295 | H36: =IF(AND(ISNUMBER(H34),ISNUMBER(G34)),H34/G34-1,"n/a") -> 0.063218391 | I36: =IF(AND(ISNUMBER(I34),ISNUMBER(H34)),I34/H34-1,"n/a") -> 0.0094594595 | J36: =IF(AND(ISNUMBER(J34),ISNUMBER(I34)),J34/I34-1,"n/a") -> 0.010709505 | K36: =IF(AND(ISNUMBER(K34),ISNUMBER(J34)),K34/J34-1,"n/a") -> -0.038410596 | ... R36: =IF(AND(ISNUMBER(R34),ISNUMBER(Q34)),R34/Q34-1,"n/a") -> 0.032914631 | U36: n/a | V36: n/a | W36: n/a | X36: n/a | Y36: n/a | Z36: n/a | AA36: n/a | AB36: n/a
A37: Sequencing consumables ($M) 2-yr stack | B37: stk | C37: n/a | D37: n/a | E37: n/a | F37: n/a | G37: =IF(AND(ISNUMBER(G35),ISNUMBER(C35)),G35+C35,"n/a") -> n/a | H37: =IF(AND(ISNUMBER(H35),ISNUMBER(D35)),H35+D35,"n/a") -> n/a | I37: =IF(AND(ISNUMBER(I35),ISNUMBER(E35)),I35+E35,"n/a") -> 0.083568864 | J37: =IF(AND(ISNUMBER(J35),ISNUMBER(F35)),J35+F35,"n/a") -> 0.1051223 | K37: =IF(AND(ISNUMBER(K35),ISNUMBER(G35)),K35+G35,"n/a") -> 0.041668728 | L37: =IF(AND(ISNUMBER(L35),ISNUMBER(H35)),L35+H35,"n/a") -> 0.051367854 | M37: =IF(AND(ISNUMBER(M35),ISNUMBER(I35)),M35+I35,"n/a") -> 0.064589803 | N37: =IF(AND(ISNUMBER(N35),ISNUMBER(J35)),N35+J35,"n/a") -> 0.16099964 | ... R37: =IF(AND(ISNUMBER(R35),ISNUMBER(N35)),R35+N35,"n/a") -> 0.16916472 | U37: n/a | V37: n/a | W37: =IF(AND(ISNUMBER(W35),ISNUMBER(V35)),W35+V35,"n/a") -> 0.052719372 | X37: =IF(AND(ISNUMBER(X35),ISNUMBER(W35)),X35+W35,"n/a") -> 0.079606336 | Y37: =IF(AND(ISNUMBER(Y35),ISNUMBER(X35)),Y35+X35,"n/a") -> 0.14453947 | Z37: =IF(AND(ISNUMBER(Z35),ISNUMBER(Y35)),Z35+Y35,"n/a") -> 0.18173802 | AA37: =IF(AND(ISNUMBER(AA35),ISNUMBER(Z35)),AA35+Z35,"n/a") -> 0.18545823 | AB37: =IF(AND(ISNUMBER(AB35),ISNUMBER(AA35)),AB35+AA35,"n/a") -> 0.20224479
A39: Sequencing consumables ex-China ($M) | B39: value | C39: 642 | D39: 679 | E39: 684 | F39: 640 | G39: 640 | H39: 690 | I39: 707 | J39: 713 | K39: 687 | L39: 734 | M39: n/a | N39: n/a | O39: n/a | P39: n/a | Q39: n/a | R39: n/a | U39: n/a | V39: 2645 | W39: 2750 | X39: n/a | Y39: n/a | Z39: n/a | AA39: n/a | AB39: n/a | AD39: Company 'Rest of World' disclosure; FY26 guide: mid-single-digit growth
A40: Sequencing consumables ex-China ($M) y/y | B40: yoy | C40: n/a | D40: n/a | E40: 0.09 | F40: 0.02 | G40: =IF(AND(ISNUMBER(G39),ISNUMBER(C39)),G39/C39-1,"n/a") -> -0.0031152648 | H40: =IF(AND(ISNUMBER(H39),ISNUMBER(D39)),H39/D39-1,"n/a") -> 0.016200295 | I40: =IF(AND(ISNUMBER(I39),ISNUMBER(E39)),I39/E39-1,"n/a") -> 0.033625731 | J40: =IF(AND(ISNUMBER(J39),ISNUMBER(F39)),J39/F39-1,"n/a") -> 0.1140625 | K40: =IF(AND(ISNUMBER(K39),ISNUMBER(G39)),K39/G39-1,"n/a") -> 0.0734375 | L40: =IF(AND(ISNUMBER(L39),ISNUMBER(H39)),L39/H39-1,"n/a") -> 0.063768116 | M40: =IF(AND(ISNUMBER(M39),ISNUMBER(I39)),M39/I39-1,"n/a") -> n/a | N40: =IF(AND(ISNUMBER(N39),ISNUMBER(J39)),N39/J39-1,"n/a") -> n/a | ... R40: =IF(AND(ISNUMBER(R39),ISNUMBER(N39)),R39/N39-1,"n/a") -> n/a | U40: n/a | V40: 0.04 | W40: =IF(AND(ISNUMBER(W39),ISNUMBER(V39)),W39/V39-1,"n/a") -> 0.039697543 | X40: =IF(AND(ISNUMBER(X39),ISNUMBER(W39)),X39/W39-1,"n/a") -> n/a | Y40: =IF(AND(ISNUMBER(Y39),ISNUMBER(X39)),Y39/X39-1,"n/a") -> n/a | Z40: =IF(AND(ISNUMBER(Z39),ISNUMBER(Y39)),Z39/Y39-1,"n/a") -> n/a | AA40: =IF(AND(ISNUMBER(AA39),ISNUMBER(Z39)),AA39/Z39-1,"n/a") -> n/a | AB40: =IF(AND(ISNUMBER(AB39),ISNUMBER(AA39)),AB39/AA39-1,"n/a") -> n/a
A41: Sequencing consumables ex-China ($M) q/q | B41: qoq | C41: n/a | D41: =IF(AND(ISNUMBER(D39),ISNUMBER(C39)),D39/C39-1,"n/a") -> 0.057632399 | E41: =IF(AND(ISNUMBER(E39),ISNUMBER(D39)),E39/D39-1,"n/a") -> 0.0073637703 | F41: =IF(AND(ISNUMBER(F39),ISNUMBER(E39)),F39/E39-1,"n/a") -> -0.064327485 | G41: =IF(AND(ISNUMBER(G39),ISNUMBER(F39)),G39/F39-1,"n/a") -> 0 | H41: =IF(AND(ISNUMBER(H39),ISNUMBER(G39)),H39/G39-1,"n/a") -> 0.078125 | I41: =IF(AND(ISNUMBER(I39),ISNUMBER(H39)),I39/H39-1,"n/a") -> 0.024637681 | J41: =IF(AND(ISNUMBER(J39),ISNUMBER(I39)),J39/I39-1,"n/a") -> 0.0084865629 | K41: =IF(AND(ISNUMBER(K39),ISNUMBER(J39)),K39/J39-1,"n/a") -> -0.036465638 | ... R41: =IF(AND(ISNUMBER(R39),ISNUMBER(Q39)),R39/Q39-1,"n/a") -> n/a | U41: n/a | V41: n/a | W41: n/a | X41: n/a | Y41: n/a | Z41: n/a | AA41: n/a | AB41: n/a
A42: Sequencing consumables ex-China ($M) 2-yr stack | B42: stk | C42: n/a | D42: n/a | E42: n/a | F42: n/a | G42: =IF(AND(ISNUMBER(G40),ISNUMBER(C40)),G40+C40,"n/a") -> n/a | H42: =IF(AND(ISNUMBER(H40),ISNUMBER(D40)),H40+D40,"n/a") -> n/a | I42: =IF(AND(ISNUMBER(I40),ISNUMBER(E40)),I40+E40,"n/a") -> 0.12362573 | J42: =IF(AND(ISNUMBER(J40),ISNUMBER(F40)),J40+F40,"n/a") -> 0.1340625 | K42: =IF(AND(ISNUMBER(K40),ISNUMBER(G40)),K40+G40,"n/a") -> 0.070322235 | L42: =IF(AND(ISNUMBER(L40),ISNUMBER(H40)),L40+H40,"n/a") -> 0.07996841 | M42: =IF(AND(ISNUMBER(M40),ISNUMBER(I40)),M40+I40,"n/a") -> n/a | N42: =IF(AND(ISNUMBER(N40),ISNUMBER(J40)),N40+J40,"n/a") -> n/a | ... R42: =IF(AND(ISNUMBER(R40),ISNUMBER(N40)),R40+N40,"n/a") -> n/a | U42: n/a | V42: n/a | W42: =IF(AND(ISNUMBER(W40),ISNUMBER(V40)),W40+V40,"n/a") -> 0.079697543 | X42: =IF(AND(ISNUMBER(X40),ISNUMBER(W40)),X40+W40,"n/a") -> n/a | Y42: =IF(AND(ISNUMBER(Y40),ISNUMBER(X40)),Y40+X40,"n/a") -> n/a | Z42: =IF(AND(ISNUMBER(Z40),ISNUMBER(Y40)),Z40+Y40,"n/a") -> n/a | AA42: =IF(AND(ISNUMBER(AA40),ISNUMBER(Z40)),AA40+Z40,"n/a") -> n/a | AB42: =IF(AND(ISNUMBER(AB40),ISNUMBER(AA40)),AB40+AA40,"n/a") -> n/a
A44: Clinical (ex-China seq. consumables), y/y | B44: value | C44: 0.07 | D44: 0.05 | E44: 0.11 | F44: 0.08 | G44: 0.08 | H44: 0.1 | I44: 0.12 | J44: 0.2 | K44: 0.2 | L44: 0.15 | M44: n/a | N44: n/a | O44: n/a | P44: n/a | Q44: n/a | R44: n/a | U44: n/a | V44: 0.08 | W44: 0.12 | X44: 0.15 | Y44: n/a | Z44: n/a | AA44: n/a | AB44: n/a | AD44: FY26E = guide 'mid-teens' (shown as 15%); H2'26 implied ~13%
A45: Clinical (ex-China seq. consumables), y/y 2-yr stack | B45: stk | C45: n/a | D45: n/a | E45: n/a | F45: n/a | G45: =IF(AND(ISNUMBER(G44),ISNUMBER(C44)),G44+C44,"n/a") -> 0.15 | H45: =IF(AND(ISNUMBER(H44),ISNUMBER(D44)),H44+D44,"n/a") -> 0.15 | I45: =IF(AND(ISNUMBER(I44),ISNUMBER(E44)),I44+E44,"n/a") -> 0.23 | J45: =IF(AND(ISNUMBER(J44),ISNUMBER(F44)),J44+F44,"n/a") -> 0.28 | K45: =IF(AND(ISNUMBER(K44),ISNUMBER(G44)),K44+G44,"n/a") -> 0.28 | L45: =IF(AND(ISNUMBER(L44),ISNUMBER(H44)),L44+H44,"n/a") -> 0.25 | M45: =IF(AND(ISNUMBER(M44),ISNUMBER(I44)),M44+I44,"n/a") -> n/a | N45: =IF(AND(ISNUMBER(N44),ISNUMBER(J44)),N44+J44,"n/a") -> n/a | ... R45: =IF(AND(ISNUMBER(R44),ISNUMBER(N44)),R44+N44,"n/a") -> n/a | U45: n/a | V45: =IF(AND(ISNUMBER(V44),ISNUMBER(U44)),V44+U44,"n/a") -> n/a | W45: =IF(AND(ISNUMBER(W44),ISNUMBER(V44)),W44+V44,"n/a") -> 0.2 | X45: =IF(AND(ISNUMBER(X44),ISNUMBER(W44)),X44+W44,"n/a") -> 0.27 | Y45: =IF(AND(ISNUMBER(Y44),ISNUMBER(X44)),Y44+X44,"n/a") -> n/a | Z45: =IF(AND(ISNUMBER(Z44),ISNUMBER(Y44)),Z44+Y44,"n/a") -> n/a | AA45: =IF(AND(ISNUMBER(AA44),ISNUMBER(Z44)),AA44+Z44,"n/a") -> n/a | AB45: =IF(AND(ISNUMBER(AB44),ISNUMBER(AA44)),AB44+AA44,"n/a") -> n/a
A47: Research & applied (ex-China seq. consumables), y/y | B47: value | C47: -0.05 | D47: -0.03 | E47: 0.06 | F47: -0.05 | G47: -0.11 | H47: -0.09 | I47: -0.08 | J47: 0 | K47: -0.12 | L47: -0.07 | M47: n/a | N47: n/a | O47: n/a | P47: n/a | Q47: n/a | R47: n/a | U47: n/a | V47: -0.02 | W47: -0.07 | X47: -0.075 | Y47: n/a | Z47: n/a | AA47: n/a | AB47: n/a | AD47: FY26E = guide 'mid- to high-single-digit decline' (shown as -7.5%)
A48: Research & applied (ex-China seq. consumables), y/y 2-yr stack | B48: stk | C48: n/a | D48: n/a | E48: n/a | F48: n/a | G48: =IF(AND(ISNUMBER(G47),ISNUMBER(C47)),G47+C47,"n/a") -> -0.16 | H48: =IF(AND(ISNUMBER(H47),ISNUMBER(D47)),H47+D47,"n/a") -> -0.12 | I48: =IF(AND(ISNUMBER(I47),ISNUMBER(E47)),I47+E47,"n/a") -> -0.02 | J48: =IF(AND(ISNUMBER(J47),ISNUMBER(F47)),J47+F47,"n/a") -> -0.05 | K48: =IF(AND(ISNUMBER(K47),ISNUMBER(G47)),K47+G47,"n/a") -> -0.23 | L48: =IF(AND(ISNUMBER(L47),ISNUMBER(H47)),L47+H47,"n/a") -> -0.16 | M48: =IF(AND(ISNUMBER(M47),ISNUMBER(I47)),M47+I47,"n/a") -> n/a | N48: =IF(AND(ISNUMBER(N47),ISNUMBER(J47)),N47+J47,"n/a") -> n/a | ... R48: =IF(AND(ISNUMBER(R47),ISNUMBER(N47)),R47+N47,"n/a") -> n/a | U48: n/a | V48: =IF(AND(ISNUMBER(V47),ISNUMBER(U47)),V47+U47,"n/a") -> n/a | W48: =IF(AND(ISNUMBER(W47),ISNUMBER(V47)),W47+V47,"n/a") -> -0.09 | X48: =IF(AND(ISNUMBER(X47),ISNUMBER(W47)),X47+W47,"n/a") -> -0.145 | Y48: =IF(AND(ISNUMBER(Y47),ISNUMBER(X47)),Y47+X47,"n/a") -> n/a | Z48: =IF(AND(ISNUMBER(Z47),ISNUMBER(Y47)),Z47+Y47,"n/a") -> n/a | AA48: =IF(AND(ISNUMBER(AA47),ISNUMBER(Z47)),AA47+Z47,"n/a") -> n/a | AB48: =IF(AND(ISNUMBER(AB47),ISNUMBER(AA47)),AB47+AA47,"n/a") -> n/a
A50: Adj. gross profit ($M) | B50: value | C50: 708 | D50: 758 | E50: 761 | F50: 745 | G50: 702 | H50: 735 | I50: 750 | J50: 777 | K50: 744 | L50: 790 | M50: 794.6 | N50: 837.8 | O50: 797.2 | P50: 842.1 | Q50: 852.2 | R50: 891.6 | U50: n/a | V50: 2973 | W50: 2964 | X50: 3166.6 | Y50: 3396.1 | Z50: 3659.2 | AA50: 3956.5 | AB50: 4277.4 | AD50: Estimates = consensus revenue x consensus gross-margin line
A51: Adj. gross profit ($M) y/y | B51: yoy | C51: n/a | D51: n/a | E51: n/a | F51: n/a | G51: =IF(AND(ISNUMBER(G50),ISNUMBER(C50)),G50/C50-1,"n/a") -> -0.0084745763 | H51: =IF(AND(ISNUMBER(H50),ISNUMBER(D50)),H50/D50-1,"n/a") -> -0.030343008 | I51: =IF(AND(ISNUMBER(I50),ISNUMBER(E50)),I50/E50-1,"n/a") -> -0.014454665 | J51: =IF(AND(ISNUMBER(J50),ISNUMBER(F50)),J50/F50-1,"n/a") -> 0.04295302 | K51: =IF(AND(ISNUMBER(K50),ISNUMBER(G50)),K50/G50-1,"n/a") -> 0.05982906 | L51: =IF(AND(ISNUMBER(L50),ISNUMBER(H50)),L50/H50-1,"n/a") -> 0.074829932 | M51: =IF(AND(ISNUMBER(M50),ISNUMBER(I50)),M50/I50-1,"n/a") -> 0.059466667 | N51: =IF(AND(ISNUMBER(N50),ISNUMBER(J50)),N50/J50-1,"n/a") -> 0.078249678 | ... R51: =IF(AND(ISNUMBER(R50),ISNUMBER(N50)),R50/N50-1,"n/a") -> 0.064215803 | U51: n/a | V51: =IF(AND(ISNUMBER(V50),ISNUMBER(U50)),V50/U50-1,"n/a") -> n/a | W51: =IF(AND(ISNUMBER(W50),ISNUMBER(V50)),W50/V50-1,"n/a") -> -0.0030272452 | X51: =IF(AND(ISNUMBER(X50),ISNUMBER(W50)),X50/W50-1,"n/a") -> 0.068353576 | Y51: =IF(AND(ISNUMBER(Y50),ISNUMBER(X50)),Y50/X50-1,"n/a") -> 0.07247521 | Z51: =IF(AND(ISNUMBER(Z50),ISNUMBER(Y50)),Z50/Y50-1,"n/a") -> 0.077471217 | AA51: =IF(AND(ISNUMBER(AA50),ISNUMBER(Z50)),AA50/Z50-1,"n/a") -> 0.081247267 | AB51: =IF(AND(ISNUMBER(AB50),ISNUMBER(AA50)),AB50/AA50-1,"n/a") -> 0.081107039
A52: Adj. gross profit ($M) q/q | B52: qoq | C52: n/a | D52: =IF(AND(ISNUMBER(D50),ISNUMBER(C50)),D50/C50-1,"n/a") -> 0.070621469 | E52: =IF(AND(ISNUMBER(E50),ISNUMBER(D50)),E50/D50-1,"n/a") -> 0.0039577836 | F52: =IF(AND(ISNUMBER(F50),ISNUMBER(E50)),F50/E50-1,"n/a") -> -0.021024967 | G52: =IF(AND(ISNUMBER(G50),ISNUMBER(F50)),G50/F50-1,"n/a") -> -0.057718121 | H52: =IF(AND(ISNUMBER(H50),ISNUMBER(G50)),H50/G50-1,"n/a") -> 0.047008547 | I52: =IF(AND(ISNUMBER(I50),ISNUMBER(H50)),I50/H50-1,"n/a") -> 0.020408163 | J52: =IF(AND(ISNUMBER(J50),ISNUMBER(I50)),J50/I50-1,"n/a") -> 0.036 | K52: =IF(AND(ISNUMBER(K50),ISNUMBER(J50)),K50/J50-1,"n/a") -> -0.042471042 | ... R52: =IF(AND(ISNUMBER(R50),ISNUMBER(Q50)),R50/Q50-1,"n/a") -> 0.046233279 | U52: n/a | V52: n/a | W52: n/a | X52: n/a | Y52: n/a | Z52: n/a | AA52: n/a | AB52: n/a
A53: Adj. gross profit ($M) 2-yr stack | B53: stk | C53: n/a | D53: n/a | E53: n/a | F53: n/a | G53: =IF(AND(ISNUMBER(G51),ISNUMBER(C51)),G51+C51,"n/a") -> n/a | H53: =IF(AND(ISNUMBER(H51),ISNUMBER(D51)),H51+D51,"n/a") -> n/a | I53: =IF(AND(ISNUMBER(I51),ISNUMBER(E51)),I51+E51,"n/a") -> n/a | J53: =IF(AND(ISNUMBER(J51),ISNUMBER(F51)),J51+F51,"n/a") -> n/a | K53: =IF(AND(ISNUMBER(K51),ISNUMBER(G51)),K51+G51,"n/a") -> 0.051354484 | L53: =IF(AND(ISNUMBER(L51),ISNUMBER(H51)),L51+H51,"n/a") -> 0.044486924 | M53: =IF(AND(ISNUMBER(M51),ISNUMBER(I51)),M51+I51,"n/a") -> 0.045012002 | N53: =IF(AND(ISNUMBER(N51),ISNUMBER(J51)),N51+J51,"n/a") -> 0.1212027 | ... R53: =IF(AND(ISNUMBER(R51),ISNUMBER(N51)),R51+N51,"n/a") -> 0.14246548 | U53: n/a | V53: n/a | W53: =IF(AND(ISNUMBER(W51),ISNUMBER(V51)),W51+V51,"n/a") -> n/a | X53: =IF(AND(ISNUMBER(X51),ISNUMBER(W51)),X51+W51,"n/a") -> 0.065326331 | Y53: =IF(AND(ISNUMBER(Y51),ISNUMBER(X51)),Y51+X51,"n/a") -> 0.14082879 | Z53: =IF(AND(ISNUMBER(Z51),ISNUMBER(Y51)),Z51+Y51,"n/a") -> 0.14994643 | AA53: =IF(AND(ISNUMBER(AA51),ISNUMBER(Z51)),AA51+Z51,"n/a") -> 0.15871848 | AB53: =IF(AND(ISNUMBER(AB51),ISNUMBER(AA51)),AB51+AA51,"n/a") -> 0.16235431
A55: Adj. operating income ($M) | B55: value | C55: 218 | D55: 242 | E55: 244 | F55: 218 | G55: 212 | H55: 252 | I55: 265 | J55: 275 | K55: 239 | L55: 260 | M55: 277 | N55: 311.5 | O55: 271.9 | P55: 299.8 | Q55: 315.3 | R55: 345.3 | U55: n/a | V55: 922 | W55: 1004 | X55: 1086.8 | Y55: 1240.4 | Z55: 1394.6 | AA55: 1563.8 | AB55: 1753.3 | AD55: Estimates = consensus revenue x consensus operating-margin line
A56: Adj. operating income ($M) y/y | B56: yoy | C56: n/a | D56: n/a | E56: n/a | F56: n/a | G56: =IF(AND(ISNUMBER(G55),ISNUMBER(C55)),G55/C55-1,"n/a") -> -0.027522936 | H56: =IF(AND(ISNUMBER(H55),ISNUMBER(D55)),H55/D55-1,"n/a") -> 0.041322314 | I56: =IF(AND(ISNUMBER(I55),ISNUMBER(E55)),I55/E55-1,"n/a") -> 0.086065574 | J56: =IF(AND(ISNUMBER(J55),ISNUMBER(F55)),J55/F55-1,"n/a") -> 0.26146789 | K56: =IF(AND(ISNUMBER(K55),ISNUMBER(G55)),K55/G55-1,"n/a") -> 0.12735849 | L56: =IF(AND(ISNUMBER(L55),ISNUMBER(H55)),L55/H55-1,"n/a") -> 0.031746032 | M56: =IF(AND(ISNUMBER(M55),ISNUMBER(I55)),M55/I55-1,"n/a") -> 0.045283019 | N56: =IF(AND(ISNUMBER(N55),ISNUMBER(J55)),N55/J55-1,"n/a") -> 0.13272727 | ... R56: =IF(AND(ISNUMBER(R55),ISNUMBER(N55)),R55/N55-1,"n/a") -> 0.10850722 | U56: n/a | V56: =IF(AND(ISNUMBER(V55),ISNUMBER(U55)),V55/U55-1,"n/a") -> n/a | W56: =IF(AND(ISNUMBER(W55),ISNUMBER(V55)),W55/V55-1,"n/a") -> 0.088937093 | X56: =IF(AND(ISNUMBER(X55),ISNUMBER(W55)),X55/W55-1,"n/a") -> 0.08247012 | Y56: =IF(AND(ISNUMBER(Y55),ISNUMBER(X55)),Y55/X55-1,"n/a") -> 0.14133235 | Z56: =IF(AND(ISNUMBER(Z55),ISNUMBER(Y55)),Z55/Y55-1,"n/a") -> 0.12431474 | AA56: =IF(AND(ISNUMBER(AA55),ISNUMBER(Z55)),AA55/Z55-1,"n/a") -> 0.12132511 | AB56: =IF(AND(ISNUMBER(AB55),ISNUMBER(AA55)),AB55/AA55-1,"n/a") -> 0.12117918
A57: Adj. operating income ($M) q/q | B57: qoq | C57: n/a | D57: =IF(AND(ISNUMBER(D55),ISNUMBER(C55)),D55/C55-1,"n/a") -> 0.11009174 | E57: =IF(AND(ISNUMBER(E55),ISNUMBER(D55)),E55/D55-1,"n/a") -> 0.0082644628 | F57: =IF(AND(ISNUMBER(F55),ISNUMBER(E55)),F55/E55-1,"n/a") -> -0.10655738 | G57: =IF(AND(ISNUMBER(G55),ISNUMBER(F55)),G55/F55-1,"n/a") -> -0.027522936 | H57: =IF(AND(ISNUMBER(H55),ISNUMBER(G55)),H55/G55-1,"n/a") -> 0.18867925 | I57: =IF(AND(ISNUMBER(I55),ISNUMBER(H55)),I55/H55-1,"n/a") -> 0.051587302 | J57: =IF(AND(ISNUMBER(J55),ISNUMBER(I55)),J55/I55-1,"n/a") -> 0.037735849 | K57: =IF(AND(ISNUMBER(K55),ISNUMBER(J55)),K55/J55-1,"n/a") -> -0.13090909 | ... R57: =IF(AND(ISNUMBER(R55),ISNUMBER(Q55)),R55/Q55-1,"n/a") -> 0.095147479 | U57: n/a | V57: n/a | W57: n/a | X57: n/a | Y57: n/a | Z57: n/a | AA57: n/a | AB57: n/a
A58: Adj. operating income ($M) 2-yr stack | B58: stk | C58: n/a | D58: n/a | E58: n/a | F58: n/a | G58: =IF(AND(ISNUMBER(G56),ISNUMBER(C56)),G56+C56,"n/a") -> n/a | H58: =IF(AND(ISNUMBER(H56),ISNUMBER(D56)),H56+D56,"n/a") -> n/a | I58: =IF(AND(ISNUMBER(I56),ISNUMBER(E56)),I56+E56,"n/a") -> n/a | J58: =IF(AND(ISNUMBER(J56),ISNUMBER(F56)),J56+F56,"n/a") -> n/a | K58: =IF(AND(ISNUMBER(K56),ISNUMBER(G56)),K56+G56,"n/a") -> 0.099835555 | L58: =IF(AND(ISNUMBER(L56),ISNUMBER(H56)),L56+H56,"n/a") -> 0.073068346 | M58: =IF(AND(ISNUMBER(M56),ISNUMBER(I56)),M56+I56,"n/a") -> 0.13134859 | N58: =IF(AND(ISNUMBER(N56),ISNUMBER(J56)),N56+J56,"n/a") -> 0.39419516 | ... R58: =IF(AND(ISNUMBER(R56),ISNUMBER(N56)),R56+N56,"n/a") -> 0.2412345 | U58: n/a | V58: n/a | W58: =IF(AND(ISNUMBER(W56),ISNUMBER(V56)),W56+V56,"n/a") -> n/a | X58: =IF(AND(ISNUMBER(X56),ISNUMBER(W56)),X56+W56,"n/a") -> 0.17140721 | Y58: =IF(AND(ISNUMBER(Y56),ISNUMBER(X56)),Y56+X56,"n/a") -> 0.22380247 | Z58: =IF(AND(ISNUMBER(Z56),ISNUMBER(Y56)),Z56+Y56,"n/a") -> 0.26564709 | AA58: =IF(AND(ISNUMBER(AA56),ISNUMBER(Z56)),AA56+Z56,"n/a") -> 0.24563985 | AB58: =IF(AND(ISNUMBER(AB56),ISNUMBER(AA56)),AB56+AA56,"n/a") -> 0.24250429
A60: Depreciation ($M) | B60: value | C60: 56 | D60: 56 | E60: 56 | F60: 56 | G60: 52 | H60: 51 | I60: 50 | J60: 50 | K60: 52 | L60: 52 | M60: 53.3 | N60: 53.9 | O60: 52.9 | P60: 54.7 | Q60: 54.6 | R60: 55 | U60: n/a | V60: 224 | W60: 204 | X60: 210.5 | Y60: 219.2 | Z60: 233.1 | AA60: 248.2 | AB60: 256.7 | AD60: 2024 quarters = FY24/4 (derived); 2025+ = D&A less amortization
A61: Depreciation ($M) y/y | B61: yoy | C61: n/a | D61: n/a | E61: n/a | F61: n/a | G61: =IF(AND(ISNUMBER(G60),ISNUMBER(C60)),G60/C60-1,"n/a") -> -0.071428571 | H61: =IF(AND(ISNUMBER(H60),ISNUMBER(D60)),H60/D60-1,"n/a") -> -0.089285714 | I61: =IF(AND(ISNUMBER(I60),ISNUMBER(E60)),I60/E60-1,"n/a") -> -0.10714286 | J61: =IF(AND(ISNUMBER(J60),ISNUMBER(F60)),J60/F60-1,"n/a") -> -0.10714286 | K61: =IF(AND(ISNUMBER(K60),ISNUMBER(G60)),K60/G60-1,"n/a") -> 0 | L61: =IF(AND(ISNUMBER(L60),ISNUMBER(H60)),L60/H60-1,"n/a") -> 0.019607843 | M61: =IF(AND(ISNUMBER(M60),ISNUMBER(I60)),M60/I60-1,"n/a") -> 0.066 | N61: =IF(AND(ISNUMBER(N60),ISNUMBER(J60)),N60/J60-1,"n/a") -> 0.078 | ... R61: =IF(AND(ISNUMBER(R60),ISNUMBER(N60)),R60/N60-1,"n/a") -> 0.020408163 | U61: n/a | V61: =IF(AND(ISNUMBER(V60),ISNUMBER(U60)),V60/U60-1,"n/a") -> n/a | W61: =IF(AND(ISNUMBER(W60),ISNUMBER(V60)),W60/V60-1,"n/a") -> -0.089285714 | X61: =IF(AND(ISNUMBER(X60),ISNUMBER(W60)),X60/W60-1,"n/a") -> 0.031862745 | Y61: =IF(AND(ISNUMBER(Y60),ISNUMBER(X60)),Y60/X60-1,"n/a") -> 0.041330166 | Z61: =IF(AND(ISNUMBER(Z60),ISNUMBER(Y60)),Z60/Y60-1,"n/a") -> 0.063412409 | AA61: =IF(AND(ISNUMBER(AA60),ISNUMBER(Z60)),AA60/Z60-1,"n/a") -> 0.064779065 | AB61: =IF(AND(ISNUMBER(AB60),ISNUMBER(AA60)),AB60/AA60-1,"n/a") -> 0.034246575
A62: Depreciation ($M) q/q | B62: qoq | C62: n/a | D62: =IF(AND(ISNUMBER(D60),ISNUMBER(C60)),D60/C60-1,"n/a") -> 0 | E62: =IF(AND(ISNUMBER(E60),ISNUMBER(D60)),E60/D60-1,"n/a") -> 0 | F62: =IF(AND(ISNUMBER(F60),ISNUMBER(E60)),F60/E60-1,"n/a") -> 0 | G62: =IF(AND(ISNUMBER(G60),ISNUMBER(F60)),G60/F60-1,"n/a") -> -0.071428571 | H62: =IF(AND(ISNUMBER(H60),ISNUMBER(G60)),H60/G60-1,"n/a") -> -0.019230769 | I62: =IF(AND(ISNUMBER(I60),ISNUMBER(H60)),I60/H60-1,"n/a") -> -0.019607843 | J62: =IF(AND(ISNUMBER(J60),ISNUMBER(I60)),J60/I60-1,"n/a") -> 0 | K62: =IF(AND(ISNUMBER(K60),ISNUMBER(J60)),K60/J60-1,"n/a") -> 0.04 | ... R62: =IF(AND(ISNUMBER(R60),ISNUMBER(Q60)),R60/Q60-1,"n/a") -> 0.0073260073 | U62: n/a | V62: n/a | W62: n/a | X62: n/a | Y62: n/a | Z62: n/a | AA62: n/a | AB62: n/a
A63: Depreciation ($M) 2-yr stack | B63: stk | C63: n/a | D63: n/a | E63: n/a | F63: n/a | G63: =IF(AND(ISNUMBER(G61),ISNUMBER(C61)),G61+C61,"n/a") -> n/a | H63: =IF(AND(ISNUMBER(H61),ISNUMBER(D61)),H61+D61,"n/a") -> n/a | I63: =IF(AND(ISNUMBER(I61),ISNUMBER(E61)),I61+E61,"n/a") -> n/a | J63: =IF(AND(ISNUMBER(J61),ISNUMBER(F61)),J61+F61,"n/a") -> n/a | K63: =IF(AND(ISNUMBER(K61),ISNUMBER(G61)),K61+G61,"n/a") -> -0.071428571 | L63: =IF(AND(ISNUMBER(L61),ISNUMBER(H61)),L61+H61,"n/a") -> -0.069677871 | M63: =IF(AND(ISNUMBER(M61),ISNUMBER(I61)),M61+I61,"n/a") -> -0.041142857 | N63: =IF(AND(ISNUMBER(N61),ISNUMBER(J61)),N61+J61,"n/a") -> -0.029142857 | ... R63: =IF(AND(ISNUMBER(R61),ISNUMBER(N61)),R61+N61,"n/a") -> 0.098408163 | U63: n/a | V63: n/a | W63: =IF(AND(ISNUMBER(W61),ISNUMBER(V61)),W61+V61,"n/a") -> n/a | X63: =IF(AND(ISNUMBER(X61),ISNUMBER(W61)),X61+W61,"n/a") -> -0.057422969 | Y63: =IF(AND(ISNUMBER(Y61),ISNUMBER(X61)),Y61+X61,"n/a") -> 0.073192911 | Z63: =IF(AND(ISNUMBER(Z61),ISNUMBER(Y61)),Z61+Y61,"n/a") -> 0.10474258 | AA63: =IF(AND(ISNUMBER(AA61),ISNUMBER(Z61)),AA61+Z61,"n/a") -> 0.12819147 | AB63: =IF(AND(ISNUMBER(AB61),ISNUMBER(AA61)),AB61+AA61,"n/a") -> 0.09902564
A65: Adj. net income ($M) | B65: value | C65: 156 | D65: 174 | E65: 181 | F65: 152 | G65: 154 | H65: 187 | I65: 206 | J65: 208 | K65: 177 | L65: 200 | M65: 207.1 | N65: 235.1 | O65: 202.9 | P65: 227.8 | Q65: 239.9 | R65: 263.6 | U65: n/a | V65: 663 | W65: 756 | X65: 821 | Y65: 936.4 | Z65: 1073.2 | AA65: 1221.9 | AB65: 1441
A66: Adj. net income ($M) y/y | B66: yoy | C66: n/a | D66: n/a | E66: n/a | F66: n/a | G66: =IF(AND(ISNUMBER(G65),ISNUMBER(C65)),G65/C65-1,"n/a") -> -0.012820513 | H66: =IF(AND(ISNUMBER(H65),ISNUMBER(D65)),H65/D65-1,"n/a") -> 0.074712644 | I66: =IF(AND(ISNUMBER(I65),ISNUMBER(E65)),I65/E65-1,"n/a") -> 0.13812155 | J66: =IF(AND(ISNUMBER(J65),ISNUMBER(F65)),J65/F65-1,"n/a") -> 0.36842105 | K66: =IF(AND(ISNUMBER(K65),ISNUMBER(G65)),K65/G65-1,"n/a") -> 0.14935065 | L66: =IF(AND(ISNUMBER(L65),ISNUMBER(H65)),L65/H65-1,"n/a") -> 0.069518717 | M66: =IF(AND(ISNUMBER(M65),ISNUMBER(I65)),M65/I65-1,"n/a") -> 0.0053398058 | N66: =IF(AND(ISNUMBER(N65),ISNUMBER(J65)),N65/J65-1,"n/a") -> 0.13028846 | ... R66: =IF(AND(ISNUMBER(R65),ISNUMBER(N65)),R65/N65-1,"n/a") -> 0.12122501 | U66: n/a | V66: =IF(AND(ISNUMBER(V65),ISNUMBER(U65)),V65/U65-1,"n/a") -> n/a | W66: =IF(AND(ISNUMBER(W65),ISNUMBER(V65)),W65/V65-1,"n/a") -> 0.14027149 | X66: =IF(AND(ISNUMBER(X65),ISNUMBER(W65)),X65/W65-1,"n/a") -> 0.085978836 | Y66: =IF(AND(ISNUMBER(Y65),ISNUMBER(X65)),Y65/X65-1,"n/a") -> 0.14056029 | Z66: =IF(AND(ISNUMBER(Z65),ISNUMBER(Y65)),Z65/Y65-1,"n/a") -> 0.14609141 | AA66: =IF(AND(ISNUMBER(AA65),ISNUMBER(Z65)),AA65/Z65-1,"n/a") -> 0.13855758 | AB66: =IF(AND(ISNUMBER(AB65),ISNUMBER(AA65)),AB65/AA65-1,"n/a") -> 0.17931091
A67: Adj. net income ($M) q/q | B67: qoq | C67: n/a | D67: =IF(AND(ISNUMBER(D65),ISNUMBER(C65)),D65/C65-1,"n/a") -> 0.11538462 | E67: =IF(AND(ISNUMBER(E65),ISNUMBER(D65)),E65/D65-1,"n/a") -> 0.040229885 | F67: =IF(AND(ISNUMBER(F65),ISNUMBER(E65)),F65/E65-1,"n/a") -> -0.16022099 | G67: =IF(AND(ISNUMBER(G65),ISNUMBER(F65)),G65/F65-1,"n/a") -> 0.013157895 | H67: =IF(AND(ISNUMBER(H65),ISNUMBER(G65)),H65/G65-1,"n/a") -> 0.21428571 | I67: =IF(AND(ISNUMBER(I65),ISNUMBER(H65)),I65/H65-1,"n/a") -> 0.10160428 | J67: =IF(AND(ISNUMBER(J65),ISNUMBER(I65)),J65/I65-1,"n/a") -> 0.0097087379 | K67: =IF(AND(ISNUMBER(K65),ISNUMBER(J65)),K65/J65-1,"n/a") -> -0.14903846 | ... R67: =IF(AND(ISNUMBER(R65),ISNUMBER(Q65)),R65/Q65-1,"n/a") -> 0.098791163 | U67: n/a | V67: n/a | W67: n/a | X67: n/a | Y67: n/a | Z67: n/a | AA67: n/a | AB67: n/a
A68: Adj. net income ($M) 2-yr stack | B68: stk | C68: n/a | D68: n/a | E68: n/a | F68: n/a | G68: =IF(AND(ISNUMBER(G66),ISNUMBER(C66)),G66+C66,"n/a") -> n/a | H68: =IF(AND(ISNUMBER(H66),ISNUMBER(D66)),H66+D66,"n/a") -> n/a | I68: =IF(AND(ISNUMBER(I66),ISNUMBER(E66)),I66+E66,"n/a") -> n/a | J68: =IF(AND(ISNUMBER(J66),ISNUMBER(F66)),J66+F66,"n/a") -> n/a | K68: =IF(AND(ISNUMBER(K66),ISNUMBER(G66)),K66+G66,"n/a") -> 0.13653014 | L68: =IF(AND(ISNUMBER(L66),ISNUMBER(H66)),L66+H66,"n/a") -> 0.14423136 | M68: =IF(AND(ISNUMBER(M66),ISNUMBER(I66)),M66+I66,"n/a") -> 0.14346135 | N68: =IF(AND(ISNUMBER(N66),ISNUMBER(J66)),N66+J66,"n/a") -> 0.49870951 | ... R68: =IF(AND(ISNUMBER(R66),ISNUMBER(N66)),R66+N66,"n/a") -> 0.25151347 | U68: n/a | V68: n/a | W68: =IF(AND(ISNUMBER(W66),ISNUMBER(V66)),W66+V66,"n/a") -> n/a | X68: =IF(AND(ISNUMBER(X66),ISNUMBER(W66)),X66+W66,"n/a") -> 0.22625033 | Y68: =IF(AND(ISNUMBER(Y66),ISNUMBER(X66)),Y66+X66,"n/a") -> 0.22653913 | Z68: =IF(AND(ISNUMBER(Z66),ISNUMBER(Y66)),Z66+Y66,"n/a") -> 0.28665171 | AA68: =IF(AND(ISNUMBER(AA66),ISNUMBER(Z66)),AA66+Z66,"n/a") -> 0.284649 | AB68: =IF(AND(ISNUMBER(AB66),ISNUMBER(AA66)),AB66+AA66,"n/a") -> 0.31786849
A70: Adj. R&D ($M) | B70: value | C70: 236 | D70: 241 | E70: 249 | F70: 255 | G70: 241 | H70: 243 | I70: 228 | J70: 238 | K70: 239 | L70: 252 | M70: 246.5 | N70: 249.2 | O70: 246.1 | P70: 258.7 | Q70: 254.8 | R70: 258.2 | U70: n/a | V70: 982 | W70: 950 | X70: 984.2 | Y70: 1020 | Z70: 1059.2 | AA70: 1098.7 | AB70: 1095.8
A71: Adj. R&D ($M) y/y | B71: yoy | C71: n/a | D71: n/a | E71: n/a | F71: n/a | G71: =IF(AND(ISNUMBER(G70),ISNUMBER(C70)),G70/C70-1,"n/a") -> 0.021186441 | H71: =IF(AND(ISNUMBER(H70),ISNUMBER(D70)),H70/D70-1,"n/a") -> 0.0082987552 | I71: =IF(AND(ISNUMBER(I70),ISNUMBER(E70)),I70/E70-1,"n/a") -> -0.084337349 | J71: =IF(AND(ISNUMBER(J70),ISNUMBER(F70)),J70/F70-1,"n/a") -> -0.066666667 | K71: =IF(AND(ISNUMBER(K70),ISNUMBER(G70)),K70/G70-1,"n/a") -> -0.0082987552 | L71: =IF(AND(ISNUMBER(L70),ISNUMBER(H70)),L70/H70-1,"n/a") -> 0.037037037 | M71: =IF(AND(ISNUMBER(M70),ISNUMBER(I70)),M70/I70-1,"n/a") -> 0.081140351 | N71: =IF(AND(ISNUMBER(N70),ISNUMBER(J70)),N70/J70-1,"n/a") -> 0.047058824 | ... R71: =IF(AND(ISNUMBER(R70),ISNUMBER(N70)),R70/N70-1,"n/a") -> 0.03611557 | U71: n/a | V71: =IF(AND(ISNUMBER(V70),ISNUMBER(U70)),V70/U70-1,"n/a") -> n/a | W71: =IF(AND(ISNUMBER(W70),ISNUMBER(V70)),W70/V70-1,"n/a") -> -0.032586558 | X71: =IF(AND(ISNUMBER(X70),ISNUMBER(W70)),X70/W70-1,"n/a") -> 0.036 | Y71: =IF(AND(ISNUMBER(Y70),ISNUMBER(X70)),Y70/X70-1,"n/a") -> 0.036374721 | Z71: =IF(AND(ISNUMBER(Z70),ISNUMBER(Y70)),Z70/Y70-1,"n/a") -> 0.038431373 | AA71: =IF(AND(ISNUMBER(AA70),ISNUMBER(Z70)),AA70/Z70-1,"n/a") -> 0.037292296 | AB71: =IF(AND(ISNUMBER(AB70),ISNUMBER(AA70)),AB70/AA70-1,"n/a") -> -0.002639483
A72: Adj. R&D ($M) q/q | B72: qoq | C72: n/a | D72: =IF(AND(ISNUMBER(D70),ISNUMBER(C70)),D70/C70-1,"n/a") -> 0.021186441 | E72: =IF(AND(ISNUMBER(E70),ISNUMBER(D70)),E70/D70-1,"n/a") -> 0.033195021 | F72: =IF(AND(ISNUMBER(F70),ISNUMBER(E70)),F70/E70-1,"n/a") -> 0.024096386 | G72: =IF(AND(ISNUMBER(G70),ISNUMBER(F70)),G70/F70-1,"n/a") -> -0.054901961 | H72: =IF(AND(ISNUMBER(H70),ISNUMBER(G70)),H70/G70-1,"n/a") -> 0.0082987552 | I72: =IF(AND(ISNUMBER(I70),ISNUMBER(H70)),I70/H70-1,"n/a") -> -0.061728395 | J72: =IF(AND(ISNUMBER(J70),ISNUMBER(I70)),J70/I70-1,"n/a") -> 0.043859649 | K72: =IF(AND(ISNUMBER(K70),ISNUMBER(J70)),K70/J70-1,"n/a") -> 0.0042016807 | ... R72: =IF(AND(ISNUMBER(R70),ISNUMBER(Q70)),R70/Q70-1,"n/a") -> 0.013343799 | U72: n/a | V72: n/a | W72: n/a | X72: n/a | Y72: n/a | Z72: n/a | AA72: n/a | AB72: n/a
A73: Adj. R&D ($M) 2-yr stack | B73: stk | C73: n/a | D73: n/a | E73: n/a | F73: n/a | G73: =IF(AND(ISNUMBER(G71),ISNUMBER(C71)),G71+C71,"n/a") -> n/a | H73: =IF(AND(ISNUMBER(H71),ISNUMBER(D71)),H71+D71,"n/a") -> n/a | I73: =IF(AND(ISNUMBER(I71),ISNUMBER(E71)),I71+E71,"n/a") -> n/a | J73: =IF(AND(ISNUMBER(J71),ISNUMBER(F71)),J71+F71,"n/a") -> n/a | K73: =IF(AND(ISNUMBER(K71),ISNUMBER(G71)),K71+G71,"n/a") -> 0.012887685 | L73: =IF(AND(ISNUMBER(L71),ISNUMBER(H71)),L71+H71,"n/a") -> 0.045335792 | M73: =IF(AND(ISNUMBER(M71),ISNUMBER(I71)),M71+I71,"n/a") -> -0.0031969985 | N73: =IF(AND(ISNUMBER(N71),ISNUMBER(J71)),N71+J71,"n/a") -> -0.019607843 | ... R73: =IF(AND(ISNUMBER(R71),ISNUMBER(N71)),R71+N71,"n/a") -> 0.083174393 | U73: n/a | V73: n/a | W73: =IF(AND(ISNUMBER(W71),ISNUMBER(V71)),W71+V71,"n/a") -> n/a | X73: =IF(AND(ISNUMBER(X71),ISNUMBER(W71)),X71+W71,"n/a") -> 0.003413442 | Y73: =IF(AND(ISNUMBER(Y71),ISNUMBER(X71)),Y71+X71,"n/a") -> 0.072374721 | Z73: =IF(AND(ISNUMBER(Z71),ISNUMBER(Y71)),Z71+Y71,"n/a") -> 0.074806093 | AA73: =IF(AND(ISNUMBER(AA71),ISNUMBER(Z71)),AA71+Z71,"n/a") -> 0.075723669 | AB73: =IF(AND(ISNUMBER(AB71),ISNUMBER(AA71)),AB71+AA71,"n/a") -> 0.034652813
A75: Adj. SG&A ($M) | B75: value | C75: 254 | D75: 275 | E75: 268 | F75: 271 | G75: 248 | H75: 241 | I75: 256 | J75: 264 | K75: 267 | L75: 278 | M75: 271 | N75: 273 | O75: 277.9 | P75: 284 | Q75: 280.3 | R75: 284.8 | U75: n/a | V75: 1069 | W75: 1009 | X75: 1089.7 | Y75: 1121.5 | Z75: 1164.5 | AA75: 1234.4 | AB75: 1369
A76: Adj. SG&A ($M) y/y | B76: yoy | C76: n/a | D76: n/a | E76: n/a | F76: n/a | G76: =IF(AND(ISNUMBER(G75),ISNUMBER(C75)),G75/C75-1,"n/a") -> -0.023622047 | H76: =IF(AND(ISNUMBER(H75),ISNUMBER(D75)),H75/D75-1,"n/a") -> -0.12363636 | I76: =IF(AND(ISNUMBER(I75),ISNUMBER(E75)),I75/E75-1,"n/a") -> -0.044776119 | J76: =IF(AND(ISNUMBER(J75),ISNUMBER(F75)),J75/F75-1,"n/a") -> -0.025830258 | K76: =IF(AND(ISNUMBER(K75),ISNUMBER(G75)),K75/G75-1,"n/a") -> 0.076612903 | L76: =IF(AND(ISNUMBER(L75),ISNUMBER(H75)),L75/H75-1,"n/a") -> 0.15352697 | M76: =IF(AND(ISNUMBER(M75),ISNUMBER(I75)),M75/I75-1,"n/a") -> 0.05859375 | N76: =IF(AND(ISNUMBER(N75),ISNUMBER(J75)),N75/J75-1,"n/a") -> 0.034090909 | ... R76: =IF(AND(ISNUMBER(R75),ISNUMBER(N75)),R75/N75-1,"n/a") -> 0.043223443 | U76: n/a | V76: =IF(AND(ISNUMBER(V75),ISNUMBER(U75)),V75/U75-1,"n/a") -> n/a | W76: =IF(AND(ISNUMBER(W75),ISNUMBER(V75)),W75/V75-1,"n/a") -> -0.056127222 | X76: =IF(AND(ISNUMBER(X75),ISNUMBER(W75)),X75/W75-1,"n/a") -> 0.079980178 | Y76: =IF(AND(ISNUMBER(Y75),ISNUMBER(X75)),Y75/X75-1,"n/a") -> 0.029182344 | Z76: =IF(AND(ISNUMBER(Z75),ISNUMBER(Y75)),Z75/Y75-1,"n/a") -> 0.038341507 | AA76: =IF(AND(ISNUMBER(AA75),ISNUMBER(Z75)),AA75/Z75-1,"n/a") -> 0.060025762 | AB76: =IF(AND(ISNUMBER(AB75),ISNUMBER(AA75)),AB75/AA75-1,"n/a") -> 0.10904083
A77: Adj. SG&A ($M) q/q | B77: qoq | C77: n/a | D77: =IF(AND(ISNUMBER(D75),ISNUMBER(C75)),D75/C75-1,"n/a") -> 0.082677165 | E77: =IF(AND(ISNUMBER(E75),ISNUMBER(D75)),E75/D75-1,"n/a") -> -0.025454545 | F77: =IF(AND(ISNUMBER(F75),ISNUMBER(E75)),F75/E75-1,"n/a") -> 0.01119403 | G77: =IF(AND(ISNUMBER(G75),ISNUMBER(F75)),G75/F75-1,"n/a") -> -0.084870849 | H77: =IF(AND(ISNUMBER(H75),ISNUMBER(G75)),H75/G75-1,"n/a") -> -0.028225806 | I77: =IF(AND(ISNUMBER(I75),ISNUMBER(H75)),I75/H75-1,"n/a") -> 0.062240664 | J77: =IF(AND(ISNUMBER(J75),ISNUMBER(I75)),J75/I75-1,"n/a") -> 0.03125 | K77: =IF(AND(ISNUMBER(K75),ISNUMBER(J75)),K75/J75-1,"n/a") -> 0.011363636 | ... R77: =IF(AND(ISNUMBER(R75),ISNUMBER(Q75)),R75/Q75-1,"n/a") -> 0.016054228 | U77: n/a | V77: n/a | W77: n/a | X77: n/a | Y77: n/a | Z77: n/a | AA77: n/a | AB77: n/a
A78: Adj. SG&A ($M) 2-yr stack | B78: stk | C78: n/a | D78: n/a | E78: n/a | F78: n/a | G78: =IF(AND(ISNUMBER(G76),ISNUMBER(C76)),G76+C76,"n/a") -> n/a | H78: =IF(AND(ISNUMBER(H76),ISNUMBER(D76)),H76+D76,"n/a") -> n/a | I78: =IF(AND(ISNUMBER(I76),ISNUMBER(E76)),I76+E76,"n/a") -> n/a | J78: =IF(AND(ISNUMBER(J76),ISNUMBER(F76)),J76+F76,"n/a") -> n/a | K78: =IF(AND(ISNUMBER(K76),ISNUMBER(G76)),K76+G76,"n/a") -> 0.052990856 | L78: =IF(AND(ISNUMBER(L76),ISNUMBER(H76)),L76+H76,"n/a") -> 0.029890607 | M78: =IF(AND(ISNUMBER(M76),ISNUMBER(I76)),M76+I76,"n/a") -> 0.013817631 | N78: =IF(AND(ISNUMBER(N76),ISNUMBER(J76)),N76+J76,"n/a") -> 0.0082606508 | ... R78: =IF(AND(ISNUMBER(R76),ISNUMBER(N76)),R76+N76,"n/a") -> 0.077314352 | U78: n/a | V78: n/a | W78: =IF(AND(ISNUMBER(W76),ISNUMBER(V76)),W76+V76,"n/a") -> n/a | X78: =IF(AND(ISNUMBER(X76),ISNUMBER(W76)),X76+W76,"n/a") -> 0.023852957 | Y78: =IF(AND(ISNUMBER(Y76),ISNUMBER(X76)),Y76+X76,"n/a") -> 0.10916252 | Z78: =IF(AND(ISNUMBER(Z76),ISNUMBER(Y76)),Z76+Y76,"n/a") -> 0.067523851 | AA78: =IF(AND(ISNUMBER(AA76),ISNUMBER(Z76)),AA76+Z76,"n/a") -> 0.098367269 | AB78: =IF(AND(ISNUMBER(AB76),ISNUMBER(AA76)),AB76+AA76,"n/a") -> 0.16906659
A80: Stock-based compensation ($M) | B80: value | C80: n/a | D80: n/a | E80: n/a | F80: n/a | G80: 73 | H80: 69 | I80: 70 | J80: 63 | K80: 60 | L80: 73 | M80: 74.6 | N80: 73.9 | O80: 78.9 | P80: 73.6 | Q80: 74 | R80: 73.3 | U80: n/a | V80: n/a | W80: 275 | X80: 282 | Y80: 295.8 | Z80: 311.6 | AA80: 324.4 | AB80: 353.5 | AD80: Kept inside non-GAAP costs (not added back)
A81: Stock-based compensation ($M) y/y | B81: yoy | C81: n/a | D81: n/a | E81: n/a | F81: n/a | G81: =IF(AND(ISNUMBER(G80),ISNUMBER(C80)),G80/C80-1,"n/a") -> n/a | H81: =IF(AND(ISNUMBER(H80),ISNUMBER(D80)),H80/D80-1,"n/a") -> n/a | I81: =IF(AND(ISNUMBER(I80),ISNUMBER(E80)),I80/E80-1,"n/a") -> n/a | J81: =IF(AND(ISNUMBER(J80),ISNUMBER(F80)),J80/F80-1,"n/a") -> n/a | K81: =IF(AND(ISNUMBER(K80),ISNUMBER(G80)),K80/G80-1,"n/a") -> -0.17808219 | L81: =IF(AND(ISNUMBER(L80),ISNUMBER(H80)),L80/H80-1,"n/a") -> 0.057971014 | M81: =IF(AND(ISNUMBER(M80),ISNUMBER(I80)),M80/I80-1,"n/a") -> 0.065714286 | N81: =IF(AND(ISNUMBER(N80),ISNUMBER(J80)),N80/J80-1,"n/a") -> 0.17301587 | ... R81: =IF(AND(ISNUMBER(R80),ISNUMBER(N80)),R80/N80-1,"n/a") -> -0.0081190798 | U81: n/a | V81: =IF(AND(ISNUMBER(V80),ISNUMBER(U80)),V80/U80-1,"n/a") -> n/a | W81: =IF(AND(ISNUMBER(W80),ISNUMBER(V80)),W80/V80-1,"n/a") -> n/a | X81: =IF(AND(ISNUMBER(X80),ISNUMBER(W80)),X80/W80-1,"n/a") -> 0.025454545 | Y81: =IF(AND(ISNUMBER(Y80),ISNUMBER(X80)),Y80/X80-1,"n/a") -> 0.04893617 | Z81: =IF(AND(ISNUMBER(Z80),ISNUMBER(Y80)),Z80/Y80-1,"n/a") -> 0.053414469 | AA81: =IF(AND(ISNUMBER(AA80),ISNUMBER(Z80)),AA80/Z80-1,"n/a") -> 0.041078306 | AB81: =IF(AND(ISNUMBER(AB80),ISNUMBER(AA80)),AB80/AA80-1,"n/a") -> 0.089704069
A82: Stock-based compensation ($M) q/q | B82: qoq | C82: n/a | D82: =IF(AND(ISNUMBER(D80),ISNUMBER(C80)),D80/C80-1,"n/a") -> n/a | E82: =IF(AND(ISNUMBER(E80),ISNUMBER(D80)),E80/D80-1,"n/a") -> n/a | F82: =IF(AND(ISNUMBER(F80),ISNUMBER(E80)),F80/E80-1,"n/a") -> n/a | G82: =IF(AND(ISNUMBER(G80),ISNUMBER(F80)),G80/F80-1,"n/a") -> n/a | H82: =IF(AND(ISNUMBER(H80),ISNUMBER(G80)),H80/G80-1,"n/a") -> -0.054794521 | I82: =IF(AND(ISNUMBER(I80),ISNUMBER(H80)),I80/H80-1,"n/a") -> 0.014492754 | J82: =IF(AND(ISNUMBER(J80),ISNUMBER(I80)),J80/I80-1,"n/a") -> -0.1 | K82: =IF(AND(ISNUMBER(K80),ISNUMBER(J80)),K80/J80-1,"n/a") -> -0.047619048 | ... R82: =IF(AND(ISNUMBER(R80),ISNUMBER(Q80)),R80/Q80-1,"n/a") -> -0.0094594595 | U82: n/a | V82: n/a | W82: n/a | X82: n/a | Y82: n/a | Z82: n/a | AA82: n/a | AB82: n/a
A83: Stock-based compensation ($M) 2-yr stack | B83: stk | C83: n/a | D83: n/a | E83: n/a | F83: n/a | G83: =IF(AND(ISNUMBER(G81),ISNUMBER(C81)),G81+C81,"n/a") -> n/a | H83: =IF(AND(ISNUMBER(H81),ISNUMBER(D81)),H81+D81,"n/a") -> n/a | I83: =IF(AND(ISNUMBER(I81),ISNUMBER(E81)),I81+E81,"n/a") -> n/a | J83: =IF(AND(ISNUMBER(J81),ISNUMBER(F81)),J81+F81,"n/a") -> n/a | K83: =IF(AND(ISNUMBER(K81),ISNUMBER(G81)),K81+G81,"n/a") -> n/a | L83: =IF(AND(ISNUMBER(L81),ISNUMBER(H81)),L81+H81,"n/a") -> n/a | M83: =IF(AND(ISNUMBER(M81),ISNUMBER(I81)),M81+I81,"n/a") -> n/a | N83: =IF(AND(ISNUMBER(N81),ISNUMBER(J81)),N81+J81,"n/a") -> n/a | ... R83: =IF(AND(ISNUMBER(R81),ISNUMBER(N81)),R81+N81,"n/a") -> 0.16489679 | U83: n/a | V83: n/a | W83: =IF(AND(ISNUMBER(W81),ISNUMBER(V81)),W81+V81,"n/a") -> n/a | X83: =IF(AND(ISNUMBER(X81),ISNUMBER(W81)),X81+W81,"n/a") -> n/a | Y83: =IF(AND(ISNUMBER(Y81),ISNUMBER(X81)),Y81+X81,"n/a") -> 0.074390716 | Z83: =IF(AND(ISNUMBER(Z81),ISNUMBER(Y81)),Z81+Y81,"n/a") -> 0.10235064 | AA83: =IF(AND(ISNUMBER(AA81),ISNUMBER(Z81)),AA81+Z81,"n/a") -> 0.094492775 | AB83: =IF(AND(ISNUMBER(AB81),ISNUMBER(AA81)),AB81+AA81,"n/a") -> 0.13078237
A85: GAAP gross margin | B85: value | C85: 0.657 | D85: 0.68 | E85: 0.689 | F85: 0.659 | G85: 0.656 | H85: 0.656 | I85: 0.676 | J85: 0.655 | K85: 0.661 | L85: 0.664 | M85: 0.6798 | N85: 0.6744 | O85: 0.6799 | P85: 0.6848 | Q85: 0.6846 | R85: 0.6804 | U85: n/a | V85: 0.671 | W85: 0.661 | X85: 0.6749 | Y85: 0.6823 | Z85: 0.6864 | AA85: 0.6897 | AB85: 0.69
A87: GAAP operating margin | B87: value | C87: 0.11 | D87: 0.405 | E87: 0.686 | F87: 0.158 | G87: 0.158 | H87: 0.202 | I87: 0.21 | J87: 0.174 | K87: 0.192 | L87: 0.211 | M87: 0.2177 | N87: 0.2278 | O87: 0.218 | P87: 0.2302 | Q87: 0.2345 | R87: 0.2432 | U87: n/a | V87: 0.34 | W87: 0.1858 | X87: 0.2126 | Y87: 0.2319 | Z87: 0.25 | AA87: 0.2644 | AB87: 0.2789 | AD87: 2024 Core GAAP inflated by EU fine reversal (Q3'24) and CVR gains
A89: Adj. tax rate | B89: value | C89: 0.25 | D89: 0.242 | E89: 0.21 | F89: 0.237 | G89: 0.22 | H89: 0.222 | I89: 0.186 | J89: 0.195 | K89: 0.205 | L89: 0.205 | M89: 0.204 | N89: 0.204 | O89: 0.2045 | P89: 0.204 | Q89: 0.2041 | R89: 0.2041 | U89: n/a | V89: 0.236 | W89: 0.205 | X89: 0.2049 | Y89: 0.2046 | Z89: 0.2043 | AA89: 0.2065 | AB89: 0.2112
A91: Non-GAAP EPS ($) | B91: value | C91: 0.98 | D91: 1.09 | E91: 1.14 | F91: 0.95 | G91: 0.97 | H91: 1.19 | I91: 1.34 | J91: 1.35 | K91: 1.15 | L91: 1.31 | M91: 1.36 | N91: 1.54 | O91: 1.35 | P91: 1.47 | Q91: 1.55 | R91: 1.71 | U91: n/a | V91: 4.16 | W91: 4.84 | X91: 5.36 | Y91: 6.11 | Z91: 7.01 | AA91: 7.99 | AB91: 9.5 | AD91: 2024 = Core; 2023 comparisons distorted by GRAIL
A92: Non-GAAP EPS ($) y/y | B92: yoy | C92: n/a | D92: n/a | E92: n/m | F92: n/m | G92: =IF(AND(ISNUMBER(G91),ISNUMBER(C91)),G91/C91-1,"n/a") -> -0.010204082 | H92: =IF(AND(ISNUMBER(H91),ISNUMBER(D91)),H91/D91-1,"n/a") -> 0.091743119 | I92: =IF(AND(ISNUMBER(I91),ISNUMBER(E91)),I91/E91-1,"n/a") -> 0.1754386 | J92: =IF(AND(ISNUMBER(J91),ISNUMBER(F91)),J91/F91-1,"n/a") -> 0.42105263 | K92: =IF(AND(ISNUMBER(K91),ISNUMBER(G91)),K91/G91-1,"n/a") -> 0.18556701 | L92: =IF(AND(ISNUMBER(L91),ISNUMBER(H91)),L91/H91-1,"n/a") -> 0.10084034 | M92: =IF(AND(ISNUMBER(M91),ISNUMBER(I91)),M91/I91-1,"n/a") -> 0.014925373 | N92: =IF(AND(ISNUMBER(N91),ISNUMBER(J91)),N91/J91-1,"n/a") -> 0.14074074 | ... R92: =IF(AND(ISNUMBER(R91),ISNUMBER(N91)),R91/N91-1,"n/a") -> 0.11038961 | U92: n/a | V92: n/m | W92: =IF(AND(ISNUMBER(W91),ISNUMBER(V91)),W91/V91-1,"n/a") -> 0.16346154 | X92: =IF(AND(ISNUMBER(X91),ISNUMBER(W91)),X91/W91-1,"n/a") -> 0.10743802 | Y92: =IF(AND(ISNUMBER(Y91),ISNUMBER(X91)),Y91/X91-1,"n/a") -> 0.13992537 | Z92: =IF(AND(ISNUMBER(Z91),ISNUMBER(Y91)),Z91/Y91-1,"n/a") -> 0.14729951 | AA92: =IF(AND(ISNUMBER(AA91),ISNUMBER(Z91)),AA91/Z91-1,"n/a") -> 0.13980029 | AB92: =IF(AND(ISNUMBER(AB91),ISNUMBER(AA91)),AB91/AA91-1,"n/a") -> 0.18898623
A93: Non-GAAP EPS ($) q/q | B93: qoq | C93: n/a | D93: =IF(AND(ISNUMBER(D91),ISNUMBER(C91)),D91/C91-1,"n/a") -> 0.1122449 | E93: =IF(AND(ISNUMBER(E91),ISNUMBER(D91)),E91/D91-1,"n/a") -> 0.04587156 | F93: =IF(AND(ISNUMBER(F91),ISNUMBER(E91)),F91/E91-1,"n/a") -> -0.16666667 | G93: =IF(AND(ISNUMBER(G91),ISNUMBER(F91)),G91/F91-1,"n/a") -> 0.021052632 | H93: =IF(AND(ISNUMBER(H91),ISNUMBER(G91)),H91/G91-1,"n/a") -> 0.22680412 | I93: =IF(AND(ISNUMBER(I91),ISNUMBER(H91)),I91/H91-1,"n/a") -> 0.12605042 | J93: =IF(AND(ISNUMBER(J91),ISNUMBER(I91)),J91/I91-1,"n/a") -> 0.0074626866 | K93: =IF(AND(ISNUMBER(K91),ISNUMBER(J91)),K91/J91-1,"n/a") -> -0.14814815 | ... R93: =IF(AND(ISNUMBER(R91),ISNUMBER(Q91)),R91/Q91-1,"n/a") -> 0.10322581 | U93: n/a | V93: n/a | W93: n/a | X93: n/a | Y93: n/a | Z93: n/a | AA93: n/a | AB93: n/a
A94: Non-GAAP EPS ($) 2-yr stack | B94: stk | C94: n/a | D94: n/a | E94: n/a | F94: n/a | G94: =IF(AND(ISNUMBER(G92),ISNUMBER(C92)),G92+C92,"n/a") -> n/a | H94: =IF(AND(ISNUMBER(H92),ISNUMBER(D92)),H92+D92,"n/a") -> n/a | I94: =IF(AND(ISNUMBER(I92),ISNUMBER(E92)),I92+E92,"n/a") -> n/a | J94: =IF(AND(ISNUMBER(J92),ISNUMBER(F92)),J92+F92,"n/a") -> n/a | K94: =IF(AND(ISNUMBER(K92),ISNUMBER(G92)),K92+G92,"n/a") -> 0.17536293 | L94: =IF(AND(ISNUMBER(L92),ISNUMBER(H92)),L92+H92,"n/a") -> 0.19258346 | M94: =IF(AND(ISNUMBER(M92),ISNUMBER(I92)),M92+I92,"n/a") -> 0.19036397 | N94: =IF(AND(ISNUMBER(N92),ISNUMBER(J92)),N92+J92,"n/a") -> 0.56179337 | ... R94: =IF(AND(ISNUMBER(R92),ISNUMBER(N92)),R92+N92,"n/a") -> 0.25113035 | U94: n/a | V94: n/a | W94: =IF(AND(ISNUMBER(W92),ISNUMBER(V92)),W92+V92,"n/a") -> n/a | X94: =IF(AND(ISNUMBER(X92),ISNUMBER(W92)),X92+W92,"n/a") -> 0.27089955 | Y94: =IF(AND(ISNUMBER(Y92),ISNUMBER(X92)),Y92+X92,"n/a") -> 0.24736339 | Z94: =IF(AND(ISNUMBER(Z92),ISNUMBER(Y92)),Z92+Y92,"n/a") -> 0.28722488 | AA94: =IF(AND(ISNUMBER(AA92),ISNUMBER(Z92)),AA92+Z92,"n/a") -> 0.28709979 | AB94: =IF(AND(ISNUMBER(AB92),ISNUMBER(AA92)),AB92+AA92,"n/a") -> 0.32878652
A96: X share of high-throughput Gb | B96: value | C96: n/a | D96: 0.45 | E96: 0.55 | F96: 0.66 | G96: 0.68 | H96: 0.69 | I96: 0.78 | J96: 0.8 | K96: 0.82 | L96: 0.83 | M96: n/a | N96: n/a | O96: n/a | P96: n/a | Q96: n/a | R96: n/a | U96: n/a | V96: n/a | W96: n/a | X96: n/a | Y96: n/a | Z96: n/a | AA96: n/a | AB96: n/a
A98: X share of high-throughput consumables revenue | B98: value | C98: n/a | D98: 0.27 | E98: 0.36 | F98: 0.4 | G98: 0.43 | H98: 0.44 | I98: 0.51 | J98: 0.55 | K98: 0.55 | L98: 0.59 | M98: n/a | N98: n/a | O98: n/a | P98: n/a | Q98: n/a | R98: n/a | U98: n/a | V98: n/a | W98: n/a | X98: n/a | Y98: n/a | Z98: n/a | AA98: n/a | AB98: n/a
A100: Adj. gross margin | B100: value | C100: =IF(AND(ISNUMBER(C50),ISNUMBER(C4)),C50/C4,"n/a") -> 0.67045455 | D100: =IF(AND(ISNUMBER(D50),ISNUMBER(D4)),D50/D4,"n/a") -> 0.69413919 | E100: =IF(AND(ISNUMBER(E50),ISNUMBER(E4)),E50/E4,"n/a") -> 0.70462963 | F100: =IF(AND(ISNUMBER(F50),ISNUMBER(F4)),F50/F4,"n/a") -> 0.67481884 | G100: =IF(AND(ISNUMBER(G50),ISNUMBER(G4)),G50/G4,"n/a") -> 0.67435159 | H100: =IF(AND(ISNUMBER(H50),ISNUMBER(H4)),H50/H4,"n/a") -> 0.69405099 | I100: =IF(AND(ISNUMBER(I50),ISNUMBER(I4)),I50/I4,"n/a") -> 0.69188192 | J100: =IF(AND(ISNUMBER(J50),ISNUMBER(J4)),J50/J4,"n/a") -> 0.67040552 | ... R100: =IF(AND(ISNUMBER(R50),ISNUMBER(R4)),R50/R4,"n/a") -> 0.68993268 | U100: =IF(AND(ISNUMBER(U50),ISNUMBER(U4)),U50/U4,"n/a") -> n/a | V100: =IF(AND(ISNUMBER(V50),ISNUMBER(V4)),V50/V4,"n/a") -> 0.68628809 | W100: =IF(AND(ISNUMBER(W50),ISNUMBER(W4)),W50/W4,"n/a") -> 0.68247755 | X100: =IF(AND(ISNUMBER(X50),ISNUMBER(X4)),X50/X4,"n/a") -> 0.68469988 | Y100: =IF(AND(ISNUMBER(Y50),ISNUMBER(Y4)),Y50/Y4,"n/a") -> 0.69050282 | Z100: =IF(AND(ISNUMBER(Z50),ISNUMBER(Z4)),Z50/Z4,"n/a") -> 0.69529528 | AA100: =IF(AND(ISNUMBER(AA50),ISNUMBER(AA4)),AA50/AA4,"n/a") -> 0.70030267 | AB100: =IF(AND(ISNUMBER(AB50),ISNUMBER(AB4)),AB50/AB4,"n/a") -> 0.70260681
A102: Adj. operating margin | B102: value | C102: =IF(AND(ISNUMBER(C55),ISNUMBER(C4)),C55/C4,"n/a") -> 0.20643939 | D102: =IF(AND(ISNUMBER(D55),ISNUMBER(D4)),D55/D4,"n/a") -> 0.22161172 | E102: =IF(AND(ISNUMBER(E55),ISNUMBER(E4)),E55/E4,"n/a") -> 0.22592593 | F102: =IF(AND(ISNUMBER(F55),ISNUMBER(F4)),F55/F4,"n/a") -> 0.19746377 | G102: =IF(AND(ISNUMBER(G55),ISNUMBER(G4)),G55/G4,"n/a") -> 0.20365034 | H102: =IF(AND(ISNUMBER(H55),ISNUMBER(H4)),H55/H4,"n/a") -> 0.23796034 | I102: =IF(AND(ISNUMBER(I55),ISNUMBER(I4)),I55/I4,"n/a") -> 0.24446494 | J102: =IF(AND(ISNUMBER(J55),ISNUMBER(J4)),J55/J4,"n/a") -> 0.23727351 | ... R102: =IF(AND(ISNUMBER(R55),ISNUMBER(R4)),R55/R4,"n/a") -> 0.26719802 | U102: =IF(AND(ISNUMBER(U55),ISNUMBER(U4)),U55/U4,"n/a") -> n/a | V102: =IF(AND(ISNUMBER(V55),ISNUMBER(V4)),V55/V4,"n/a") -> 0.21283472 | W102: =IF(AND(ISNUMBER(W55),ISNUMBER(W4)),W55/W4,"n/a") -> 0.23117661 | X102: =IF(AND(ISNUMBER(X55),ISNUMBER(X4)),X55/X4,"n/a") -> 0.23499395 | Y102: =IF(AND(ISNUMBER(Y55),ISNUMBER(Y4)),Y55/Y4,"n/a") -> 0.25220096 | Z102: =IF(AND(ISNUMBER(Z55),ISNUMBER(Z4)),Z55/Z4,"n/a") -> 0.26499202 | AA102: =IF(AND(ISNUMBER(AA55),ISNUMBER(AA4)),AA55/AA4,"n/a") -> 0.27679346 | AB102: =IF(AND(ISNUMBER(AB55),ISNUMBER(AB4)),AB55/AB4,"n/a") -> 0.2879975
A104: Adj. EBITDA margin (op. income + depreciation) | B104: value | C104: =IF(AND(ISNUMBER(C55),ISNUMBER(C60),ISNUMBER(C4)),(C55+C60)/C4,"n/a") -> 0.2594697 | D104: =IF(AND(ISNUMBER(D55),ISNUMBER(D60),ISNUMBER(D4)),(D55+D60)/D4,"n/a") -> 0.27289377 | E104: =IF(AND(ISNUMBER(E55),ISNUMBER(E60),ISNUMBER(E4)),(E55+E60)/E4,"n/a") -> 0.27777778 | F104: =IF(AND(ISNUMBER(F55),ISNUMBER(F60),ISNUMBER(F4)),(F55+F60)/F4,"n/a") -> 0.24818841 | G104: =IF(AND(ISNUMBER(G55),ISNUMBER(G60),ISNUMBER(G4)),(G55+G60)/G4,"n/a") -> 0.25360231 | H104: =IF(AND(ISNUMBER(H55),ISNUMBER(H60),ISNUMBER(H4)),(H55+H60)/H4,"n/a") -> 0.28611898 | I104: =IF(AND(ISNUMBER(I55),ISNUMBER(I60),ISNUMBER(I4)),(I55+I60)/I4,"n/a") -> 0.29059041 | J104: =IF(AND(ISNUMBER(J55),ISNUMBER(J60),ISNUMBER(J4)),(J55+J60)/J4,"n/a") -> 0.28041415 | ... R104: =IF(AND(ISNUMBER(R55),ISNUMBER(R60),ISNUMBER(R4)),(R55+R60)/R4,"n/a") -> 0.3097578 | U104: =IF(AND(ISNUMBER(U55),ISNUMBER(U60),ISNUMBER(U4)),(U55+U60)/U4,"n/a") -> n/a | V104: =IF(AND(ISNUMBER(V55),ISNUMBER(V60),ISNUMBER(V4)),(V55+V60)/V4,"n/a") -> 0.26454294 | W104: =IF(AND(ISNUMBER(W55),ISNUMBER(W60),ISNUMBER(W4)),(W55+W60)/W4,"n/a") -> 0.27814875 | X104: =IF(AND(ISNUMBER(X55),ISNUMBER(X60),ISNUMBER(X4)),(X55+X60)/X4,"n/a") -> 0.28050943 | Y104: =IF(AND(ISNUMBER(Y55),ISNUMBER(Y60),ISNUMBER(Y4)),(Y55+Y60)/Y4,"n/a") -> 0.29676921 | Z104: =IF(AND(ISNUMBER(Z55),ISNUMBER(Z60),ISNUMBER(Z4)),(Z55+Z60)/Z4,"n/a") -> 0.30928403 | AA104: =IF(AND(ISNUMBER(AA55),ISNUMBER(AA60),ISNUMBER(AA4)),(AA55+AA60)/AA4,"n/a") -> 0.32072499 | AB104: =IF(AND(ISNUMBER(AB55),ISNUMBER(AB60),ISNUMBER(AB4)),(AB55+AB60)/AB4,"n/a") -> 0.33016311
A106: Adj. net margin | B106: value | C106: =IF(AND(ISNUMBER(C65),ISNUMBER(C4)),C65/C4,"n/a") -> 0.14772727 | D106: =IF(AND(ISNUMBER(D65),ISNUMBER(D4)),D65/D4,"n/a") -> 0.15934066 | E106: =IF(AND(ISNUMBER(E65),ISNUMBER(E4)),E65/E4,"n/a") -> 0.16759259 | F106: =IF(AND(ISNUMBER(F65),ISNUMBER(F4)),F65/F4,"n/a") -> 0.13768116 | G106: =IF(AND(ISNUMBER(G65),ISNUMBER(G4)),G65/G4,"n/a") -> 0.14793468 | H106: =IF(AND(ISNUMBER(H65),ISNUMBER(H4)),H65/H4,"n/a") -> 0.17658168 | I106: =IF(AND(ISNUMBER(I65),ISNUMBER(I4)),I65/I4,"n/a") -> 0.1900369 | J106: =IF(AND(ISNUMBER(J65),ISNUMBER(J4)),J65/J4,"n/a") -> 0.17946506 | ... R106: =IF(AND(ISNUMBER(R65),ISNUMBER(R4)),R65/R4,"n/a") -> 0.2039774 | U106: =IF(AND(ISNUMBER(U65),ISNUMBER(U4)),U65/U4,"n/a") -> n/a | V106: =IF(AND(ISNUMBER(V65),ISNUMBER(V4)),V65/V4,"n/a") -> 0.15304709 | W106: =IF(AND(ISNUMBER(W65),ISNUMBER(W4)),W65/W4,"n/a") -> 0.17407322 | X106: =IF(AND(ISNUMBER(X65),ISNUMBER(X4)),X65/X4,"n/a") -> 0.17752119 | Y106: =IF(AND(ISNUMBER(Y65),ISNUMBER(Y4)),Y65/Y4,"n/a") -> 0.19039099 | Z106: =IF(AND(ISNUMBER(Z65),ISNUMBER(Z4)),Z65/Z4,"n/a") -> 0.20392187 | AA106: =IF(AND(ISNUMBER(AA65),ISNUMBER(AA4)),AA65/AA4,"n/a") -> 0.21627697 | AB106: =IF(AND(ISNUMBER(AB65),ISNUMBER(AB4)),AB65/AB4,"n/a") -> 0.23669903
A108: COGS % of revenue (non-GAAP) | B108: value | C108: =IF(AND(ISNUMBER(C50),ISNUMBER(C4)),1-C50/C4,"n/a") -> 0.32954545 | D108: =IF(AND(ISNUMBER(D50),ISNUMBER(D4)),1-D50/D4,"n/a") -> 0.30586081 | E108: =IF(AND(ISNUMBER(E50),ISNUMBER(E4)),1-E50/E4,"n/a") -> 0.29537037 | F108: =IF(AND(ISNUMBER(F50),ISNUMBER(F4)),1-F50/F4,"n/a") -> 0.32518116 | G108: =IF(AND(ISNUMBER(G50),ISNUMBER(G4)),1-G50/G4,"n/a") -> 0.32564841 | H108: =IF(AND(ISNUMBER(H50),ISNUMBER(H4)),1-H50/H4,"n/a") -> 0.30594901 | I108: =IF(AND(ISNUMBER(I50),ISNUMBER(I4)),1-I50/I4,"n/a") -> 0.30811808 | J108: =IF(AND(ISNUMBER(J50),ISNUMBER(J4)),1-J50/J4,"n/a") -> 0.32959448 | ... R108: =IF(AND(ISNUMBER(R50),ISNUMBER(R4)),1-R50/R4,"n/a") -> 0.31006732 | U108: =IF(AND(ISNUMBER(U50),ISNUMBER(U4)),1-U50/U4,"n/a") -> n/a | V108: =IF(AND(ISNUMBER(V50),ISNUMBER(V4)),1-V50/V4,"n/a") -> 0.31371191 | W108: =IF(AND(ISNUMBER(W50),ISNUMBER(W4)),1-W50/W4,"n/a") -> 0.31752245 | X108: =IF(AND(ISNUMBER(X50),ISNUMBER(X4)),1-X50/X4,"n/a") -> 0.31530012 | Y108: =IF(AND(ISNUMBER(Y50),ISNUMBER(Y4)),1-Y50/Y4,"n/a") -> 0.30949718 | Z108: =IF(AND(ISNUMBER(Z50),ISNUMBER(Z4)),1-Z50/Z4,"n/a") -> 0.30470472 | AA108: =IF(AND(ISNUMBER(AA50),ISNUMBER(AA4)),1-AA50/AA4,"n/a") -> 0.29969733 | AB108: =IF(AND(ISNUMBER(AB50),ISNUMBER(AB4)),1-AB50/AB4,"n/a") -> 0.29739319
A110: R&D % of revenue | B110: value | C110: =IF(AND(ISNUMBER(C70),ISNUMBER(C4)),C70/C4,"n/a") -> 0.22348485 | D110: =IF(AND(ISNUMBER(D70),ISNUMBER(D4)),D70/D4,"n/a") -> 0.22069597 | E110: =IF(AND(ISNUMBER(E70),ISNUMBER(E4)),E70/E4,"n/a") -> 0.23055556 | F110: =IF(AND(ISNUMBER(F70),ISNUMBER(F4)),F70/F4,"n/a") -> 0.23097826 | G110: =IF(AND(ISNUMBER(G70),ISNUMBER(G4)),G70/G4,"n/a") -> 0.23150817 | H110: =IF(AND(ISNUMBER(H70),ISNUMBER(H4)),H70/H4,"n/a") -> 0.22946176 | I110: =IF(AND(ISNUMBER(I70),ISNUMBER(I4)),I70/I4,"n/a") -> 0.2103321 | J110: =IF(AND(ISNUMBER(J70),ISNUMBER(J4)),J70/J4,"n/a") -> 0.20534944 | ... R110: =IF(AND(ISNUMBER(R70),ISNUMBER(R4)),R70/R4,"n/a") -> 0.19979881 | U110: =IF(AND(ISNUMBER(U70),ISNUMBER(U4)),U70/U4,"n/a") -> n/a | V110: =IF(AND(ISNUMBER(V70),ISNUMBER(V4)),V70/V4,"n/a") -> 0.22668513 | W110: =IF(AND(ISNUMBER(W70),ISNUMBER(W4)),W70/W4,"n/a") -> 0.2187428 | X110: =IF(AND(ISNUMBER(X70),ISNUMBER(X4)),X70/X4,"n/a") -> 0.2128092 | Y110: =IF(AND(ISNUMBER(Y70),ISNUMBER(Y4)),Y70/Y4,"n/a") -> 0.20738873 | Z110: =IF(AND(ISNUMBER(Z70),ISNUMBER(Z4)),Z70/Z4,"n/a") -> 0.20126169 | AA110: =IF(AND(ISNUMBER(AA70),ISNUMBER(AA4)),AA70/AA4,"n/a") -> 0.1944705 | AB110: =IF(AND(ISNUMBER(AB70),ISNUMBER(AB4)),AB70/AB4,"n/a") -> 0.17999639
A112: SG&A % of revenue | B112: value | C112: =IF(AND(ISNUMBER(C75),ISNUMBER(C4)),C75/C4,"n/a") -> 0.2405303 | D112: =IF(AND(ISNUMBER(D75),ISNUMBER(D4)),D75/D4,"n/a") -> 0.2518315 | E112: =IF(AND(ISNUMBER(E75),ISNUMBER(E4)),E75/E4,"n/a") -> 0.24814815 | F112: =IF(AND(ISNUMBER(F75),ISNUMBER(F4)),F75/F4,"n/a") -> 0.24547101 | G112: =IF(AND(ISNUMBER(G75),ISNUMBER(G4)),G75/G4,"n/a") -> 0.23823247 | H112: =IF(AND(ISNUMBER(H75),ISNUMBER(H4)),H75/H4,"n/a") -> 0.22757318 | I112: =IF(AND(ISNUMBER(I75),ISNUMBER(I4)),I75/I4,"n/a") -> 0.23616236 | J112: =IF(AND(ISNUMBER(J75),ISNUMBER(J4)),J75/J4,"n/a") -> 0.22778257 | ... R112: =IF(AND(ISNUMBER(R75),ISNUMBER(R4)),R75/R4,"n/a") -> 0.22038226 | U112: =IF(AND(ISNUMBER(U75),ISNUMBER(U4)),U75/U4,"n/a") -> n/a | V112: =IF(AND(ISNUMBER(V75),ISNUMBER(V4)),V75/V4,"n/a") -> 0.24676824 | W112: =IF(AND(ISNUMBER(W75),ISNUMBER(W4)),W75/W4,"n/a") -> 0.23232788 | X112: =IF(AND(ISNUMBER(X75),ISNUMBER(X4)),X75/X4,"n/a") -> 0.235621 | Y112: =IF(AND(ISNUMBER(Y75),ISNUMBER(Y4)),Y75/Y4,"n/a") -> 0.22802594 | Z112: =IF(AND(ISNUMBER(Z75),ISNUMBER(Z4)),Z75/Z4,"n/a") -> 0.22127005 | AA112: =IF(AND(ISNUMBER(AA75),ISNUMBER(AA4)),AA75/AA4,"n/a") -> 0.21848948 | AB112: =IF(AND(ISNUMBER(AB75),ISNUMBER(AB4)),AB75/AB4,"n/a") -> 0.22487229
A114: Total opex % of revenue (R&D + SG&A) | B114: value | C114: =IF(AND(ISNUMBER(C70),ISNUMBER(C75),ISNUMBER(C4)),(C70+C75)/C4,"n/a") -> 0.46401515 | D114: =IF(AND(ISNUMBER(D70),ISNUMBER(D75),ISNUMBER(D4)),(D70+D75)/D4,"n/a") -> 0.47252747 | E114: =IF(AND(ISNUMBER(E70),ISNUMBER(E75),ISNUMBER(E4)),(E70+E75)/E4,"n/a") -> 0.4787037 | F114: =IF(AND(ISNUMBER(F70),ISNUMBER(F75),ISNUMBER(F4)),(F70+F75)/F4,"n/a") -> 0.47644928 | G114: =IF(AND(ISNUMBER(G70),ISNUMBER(G75),ISNUMBER(G4)),(G70+G75)/G4,"n/a") -> 0.46974063 | H114: =IF(AND(ISNUMBER(H70),ISNUMBER(H75),ISNUMBER(H4)),(H70+H75)/H4,"n/a") -> 0.45703494 | I114: =IF(AND(ISNUMBER(I70),ISNUMBER(I75),ISNUMBER(I4)),(I70+I75)/I4,"n/a") -> 0.44649446 | J114: =IF(AND(ISNUMBER(J70),ISNUMBER(J75),ISNUMBER(J4)),(J70+J75)/J4,"n/a") -> 0.43313201 | ... R114: =IF(AND(ISNUMBER(R70),ISNUMBER(R75),ISNUMBER(R4)),(R70+R75)/R4,"n/a") -> 0.42018107 | U114: =IF(AND(ISNUMBER(U70),ISNUMBER(U75),ISNUMBER(U4)),(U70+U75)/U4,"n/a") -> n/a | V114: =IF(AND(ISNUMBER(V70),ISNUMBER(V75),ISNUMBER(V4)),(V70+V75)/V4,"n/a") -> 0.47345337 | W114: =IF(AND(ISNUMBER(W70),ISNUMBER(W75),ISNUMBER(W4)),(W70+W75)/W4,"n/a") -> 0.45107069 | X114: =IF(AND(ISNUMBER(X70),ISNUMBER(X75),ISNUMBER(X4)),(X70+X75)/X4,"n/a") -> 0.4484302 | Y114: =IF(AND(ISNUMBER(Y70),ISNUMBER(Y75),ISNUMBER(Y4)),(Y70+Y75)/Y4,"n/a") -> 0.43541468 | Z114: =IF(AND(ISNUMBER(Z70),ISNUMBER(Z75),ISNUMBER(Z4)),(Z70+Z75)/Z4,"n/a") -> 0.42253173 | AA114: =IF(AND(ISNUMBER(AA70),ISNUMBER(AA75),ISNUMBER(AA4)),(AA70+AA75)/AA4,"n/a") -> 0.41295998 | AB114: =IF(AND(ISNUMBER(AB70),ISNUMBER(AB75),ISNUMBER(AB4)),(AB70+AB75)/AB4,"n/a") -> 0.40486867
A116: SBC % of revenue | B116: value | C116: =IF(AND(ISNUMBER(C80),ISNUMBER(C4)),C80/C4,"n/a") -> n/a | D116: =IF(AND(ISNUMBER(D80),ISNUMBER(D4)),D80/D4,"n/a") -> n/a | E116: =IF(AND(ISNUMBER(E80),ISNUMBER(E4)),E80/E4,"n/a") -> n/a | F116: =IF(AND(ISNUMBER(F80),ISNUMBER(F4)),F80/F4,"n/a") -> n/a | G116: =IF(AND(ISNUMBER(G80),ISNUMBER(G4)),G80/G4,"n/a") -> 0.07012488 | H116: =IF(AND(ISNUMBER(H80),ISNUMBER(H4)),H80/H4,"n/a") -> 0.065155807 | I116: =IF(AND(ISNUMBER(I80),ISNUMBER(I4)),I80/I4,"n/a") -> 0.064575646 | J116: =IF(AND(ISNUMBER(J80),ISNUMBER(J4)),J80/J4,"n/a") -> 0.054357204 | ... R116: =IF(AND(ISNUMBER(R80),ISNUMBER(R4)),R80/R4,"n/a") -> 0.056720576 | U116: =IF(AND(ISNUMBER(U80),ISNUMBER(U4)),U80/U4,"n/a") -> n/a | V116: =IF(AND(ISNUMBER(V80),ISNUMBER(V4)),V80/V4,"n/a") -> n/a | W116: =IF(AND(ISNUMBER(W80),ISNUMBER(W4)),W80/W4,"n/a") -> 0.063320286 | X116: =IF(AND(ISNUMBER(X80),ISNUMBER(X4)),X80/X4,"n/a") -> 0.06097561 | Y116: =IF(AND(ISNUMBER(Y80),ISNUMBER(Y4)),Y80/Y4,"n/a") -> 0.060142732 | Z116: =IF(AND(ISNUMBER(Z80),ISNUMBER(Z4)),Z80/Z4,"n/a") -> 0.059208026 | AA116: =IF(AND(ISNUMBER(AA80),ISNUMBER(AA4)),AA80/AA4,"n/a") -> 0.057418978 | AB116: =IF(AND(ISNUMBER(AB80),ISNUMBER(AB4)),AB80/AB4,"n/a") -> 0.058066
A118: Adj. gross margin y/y change (bps) | B118: ybps | C118: n/a | D118: n/a | E118: n/a | F118: n/a | G118: =IF(AND(ISNUMBER(G100),ISNUMBER(C100)),(G100-C100)*10000,"n/a") -> 38.970396 | H118: =IF(AND(ISNUMBER(H100),ISNUMBER(D100)),(H100-D100)*10000,"n/a") -> -0.88202638 | I118: =IF(AND(ISNUMBER(I100),ISNUMBER(E100)),(I100-E100)*10000,"n/a") -> -127.47711 | J118: =IF(AND(ISNUMBER(J100),ISNUMBER(F100)),(J100-F100)*10000,"n/a") -> -44.133186 | K118: =IF(AND(ISNUMBER(K100),ISNUMBER(G100)),(K100-G100)*10000,"n/a") -> 75.915864 | L118: =IF(AND(ISNUMBER(L100),ISNUMBER(H100)),(L100-H100)*10000,"n/a") -> -124.28903 | M118: =IF(AND(ISNUMBER(M100),ISNUMBER(I100)),(M100-I100)*10000,"n/a") -> -34.397078 | N118: =IF(AND(ISNUMBER(N100),ISNUMBER(J100)),(N100-J100)*10000,"n/a") -> 164.28385 | ... R118: =IF(AND(ISNUMBER(R100),ISNUMBER(N100)),(R100-N100)*10000,"n/a") -> 30.98771 | U118: n/a | V118: =IF(AND(ISNUMBER(V100),ISNUMBER(U100)),(V100-U100)*10000,"n/a") -> n/a | W118: =IF(AND(ISNUMBER(W100),ISNUMBER(V100)),(W100-V100)*10000,"n/a") -> -38.105386 | X118: =IF(AND(ISNUMBER(X100),ISNUMBER(W100)),(X100-W100)*10000,"n/a") -> 22.223288 | Y118: =IF(AND(ISNUMBER(Y100),ISNUMBER(X100)),(Y100-X100)*10000,"n/a") -> 58.029371 | Z118: =IF(AND(ISNUMBER(Z100),ISNUMBER(Y100)),(Z100-Y100)*10000,"n/a") -> 47.924641 | AA118: =IF(AND(ISNUMBER(AA100),ISNUMBER(Z100)),(AA100-Z100)*10000,"n/a") -> 50.073909 | AB118: =IF(AND(ISNUMBER(AB100),ISNUMBER(AA100)),(AB100-AA100)*10000,"n/a") -> 23.041393
A119: Adj. gross margin q/q change (bps) | B119: qbps | C119: n/a | D119: =IF(AND(ISNUMBER(D100),ISNUMBER(C100)),(D100-C100)*10000,"n/a") -> 236.84649 | E119: =IF(AND(ISNUMBER(E100),ISNUMBER(D100)),(E100-D100)*10000,"n/a") -> 104.90435 | F119: =IF(AND(ISNUMBER(F100),ISNUMBER(E100)),(F100-E100)*10000,"n/a") -> -298.10789 | G119: =IF(AND(ISNUMBER(G100),ISNUMBER(F100)),(G100-F100)*10000,"n/a") -> -4.6725557 | H119: =IF(AND(ISNUMBER(H100),ISNUMBER(G100)),(H100-G100)*10000,"n/a") -> 196.99406 | I119: =IF(AND(ISNUMBER(I100),ISNUMBER(H100)),(I100-H100)*10000,"n/a") -> -21.690727 | J119: =IF(AND(ISNUMBER(J100),ISNUMBER(I100)),(J100-I100)*10000,"n/a") -> -214.76397 | K119: =IF(AND(ISNUMBER(K100),ISNUMBER(J100)),(K100-J100)*10000,"n/a") -> 115.37649 | ... R119: =IF(AND(ISNUMBER(R100),ISNUMBER(Q100)),(R100-Q100)*10000,"n/a") -> -33.637748 | U119: n/a | V119: n/a | W119: n/a | X119: n/a | Y119: n/a | Z119: n/a | AA119: n/a | AB119: n/a
A121: Adj. operating margin y/y change (bps) | B121: ybps | C121: n/a | D121: n/a | E121: n/a | F121: n/a | G121: =IF(AND(ISNUMBER(G102),ISNUMBER(C102)),(G102-C102)*10000,"n/a") -> -27.890577 | H121: =IF(AND(ISNUMBER(H102),ISNUMBER(D102)),(H102-D102)*10000,"n/a") -> 163.48618 | I121: =IF(AND(ISNUMBER(I102),ISNUMBER(E102)),(I102-E102)*10000,"n/a") -> 185.39019 | J121: =IF(AND(ISNUMBER(J102),ISNUMBER(F102)),(J102-F102)*10000,"n/a") -> 398.09744 | K121: =IF(AND(ISNUMBER(K102),ISNUMBER(G102)),(K102-G102)*10000,"n/a") -> 154.14742 | L121: =IF(AND(ISNUMBER(L102),ISNUMBER(H102)),(L102-H102)*10000,"n/a") -> -136.2902 | M121: =IF(AND(ISNUMBER(M102),ISNUMBER(I102)),(M102-I102)*10000,"n/a") -> -44.718759 | N121: =IF(AND(ISNUMBER(N102),ISNUMBER(J102)),(N102-J102)*10000,"n/a") -> 180.96221 | ... R121: =IF(AND(ISNUMBER(R102),ISNUMBER(N102)),(R102-N102)*10000,"n/a") -> 118.28286 | U121: n/a | V121: =IF(AND(ISNUMBER(V102),ISNUMBER(U102)),(V102-U102)*10000,"n/a") -> n/a | W121: =IF(AND(ISNUMBER(W102),ISNUMBER(V102)),(W102-V102)*10000,"n/a") -> 183.41888 | X121: =IF(AND(ISNUMBER(X102),ISNUMBER(W102)),(X102-W102)*10000,"n/a") -> 38.173397 | Y121: =IF(AND(ISNUMBER(Y102),ISNUMBER(X102)),(Y102-X102)*10000,"n/a") -> 172.07018 | Z121: =IF(AND(ISNUMBER(Z102),ISNUMBER(Y102)),(Z102-Y102)*10000,"n/a") -> 127.91056 | AA121: =IF(AND(ISNUMBER(AA102),ISNUMBER(Z102)),(AA102-Z102)*10000,"n/a") -> 118.01439 | AB121: =IF(AND(ISNUMBER(AB102),ISNUMBER(AA102)),(AB102-AA102)*10000,"n/a") -> 112.04045
A122: Adj. operating margin q/q change (bps) | B122: qbps | C122: n/a | D122: =IF(AND(ISNUMBER(D102),ISNUMBER(C102)),(D102-C102)*10000,"n/a") -> 151.72328 | E122: =IF(AND(ISNUMBER(E102),ISNUMBER(D102)),(E102-D102)*10000,"n/a") -> 43.142043 | F122: =IF(AND(ISNUMBER(F102),ISNUMBER(E102)),(F102-E102)*10000,"n/a") -> -284.62158 | G122: =IF(AND(ISNUMBER(G102),ISNUMBER(F102)),(G102-F102)*10000,"n/a") -> 61.865681 | H122: =IF(AND(ISNUMBER(H102),ISNUMBER(G102)),(H102-G102)*10000,"n/a") -> 343.10004 | I122: =IF(AND(ISNUMBER(I102),ISNUMBER(H102)),(I102-H102)*10000,"n/a") -> 65.046047 | J122: =IF(AND(ISNUMBER(J102),ISNUMBER(I102)),(J102-I102)*10000,"n/a") -> -71.91433 | K122: =IF(AND(ISNUMBER(K102),ISNUMBER(J102)),(K102-J102)*10000,"n/a") -> -182.08434 | ... R122: =IF(AND(ISNUMBER(R102),ISNUMBER(Q102)),(R102-Q102)*10000,"n/a") -> 106.89721 | U122: n/a | V122: n/a | W122: n/a | X122: n/a | Y122: n/a | Z122: n/a | AA122: n/a | AB122: n/a
A124: Adj. EBITDA margin (op. income + depreciation) y/y change (bps) | B124: ybps | C124: n/a | D124: n/a | E124: n/a | F124: n/a | G124: =IF(AND(ISNUMBER(G104),ISNUMBER(C104)),(G104-C104)*10000,"n/a") -> -58.673915 | H124: =IF(AND(ISNUMBER(H104),ISNUMBER(D104)),(H104-D104)*10000,"n/a") -> 132.25207 | I124: =IF(AND(ISNUMBER(I104),ISNUMBER(E104)),(I104-E104)*10000,"n/a") -> 128.12628 | J124: =IF(AND(ISNUMBER(J104),ISNUMBER(F104)),(J104-F104)*10000,"n/a") -> 322.25744 | K124: =IF(AND(ISNUMBER(K104),ISNUMBER(G104)),(K104-G104)*10000,"n/a") -> 131.25467 | L124: =IF(AND(ISNUMBER(L104),ISNUMBER(H104)),(L104-H104)*10000,"n/a") -> -169.21396 | M124: =IF(AND(ISNUMBER(M104),ISNUMBER(I104)),(M104-I104)*10000,"n/a") -> -44.181654 | N124: =IF(AND(ISNUMBER(N104),ISNUMBER(J104)),(N104-J104)*10000,"n/a") -> 191.43154 | ... R124: =IF(AND(ISNUMBER(R104),ISNUMBER(N104)),(R104-N104)*10000,"n/a") -> 102.00492 | U124: n/a | V124: =IF(AND(ISNUMBER(V104),ISNUMBER(U104)),(V104-U104)*10000,"n/a") -> n/a | W124: =IF(AND(ISNUMBER(W104),ISNUMBER(V104)),(W104-V104)*10000,"n/a") -> 136.05809 | X124: =IF(AND(ISNUMBER(X104),ISNUMBER(W104)),(X104-W104)*10000,"n/a") -> 23.606823 | Y124: =IF(AND(ISNUMBER(Y104),ISNUMBER(X104)),(Y104-X104)*10000,"n/a") -> 162.59781 | Z124: =IF(AND(ISNUMBER(Z104),ISNUMBER(Y104)),(Z104-Y104)*10000,"n/a") -> 125.14822 | AA124: =IF(AND(ISNUMBER(AA104),ISNUMBER(Z104)),(AA104-Z104)*10000,"n/a") -> 114.40963 | AB124: =IF(AND(ISNUMBER(AB104),ISNUMBER(AA104)),(AB104-AA104)*10000,"n/a") -> 94.381162
A125: Adj. EBITDA margin (op. income + depreciation) q/q change (bps) | B125: qbps | C125: n/a | D125: =IF(AND(ISNUMBER(D104),ISNUMBER(C104)),(D104-C104)*10000,"n/a") -> 134.24076 | E125: =IF(AND(ISNUMBER(E104),ISNUMBER(D104)),(E104-D104)*10000,"n/a") -> 48.840049 | F125: =IF(AND(ISNUMBER(F104),ISNUMBER(E104)),(F104-E104)*10000,"n/a") -> -295.89372 | G125: =IF(AND(ISNUMBER(G104),ISNUMBER(F104)),(G104-F104)*10000,"n/a") -> 54.138997 | H125: =IF(AND(ISNUMBER(H104),ISNUMBER(G104)),(H104-G104)*10000,"n/a") -> 325.16675 | I125: =IF(AND(ISNUMBER(I104),ISNUMBER(H104)),(I104-H104)*10000,"n/a") -> 44.714257 | J125: =IF(AND(ISNUMBER(J104),ISNUMBER(I104)),(J104-I104)*10000,"n/a") -> -101.76256 | K125: =IF(AND(ISNUMBER(K104),ISNUMBER(J104)),(K104-J104)*10000,"n/a") -> -136.86377 | ... R125: =IF(AND(ISNUMBER(R104),ISNUMBER(Q104)),(R104-Q104)*10000,"n/a") -> 88.303637 | U125: n/a | V125: n/a | W125: n/a | X125: n/a | Y125: n/a | Z125: n/a | AA125: n/a | AB125: n/a
A127: Adj. net margin y/y change (bps) | B127: ybps | C127: n/a | D127: n/a | E127: n/a | F127: n/a | G127: =IF(AND(ISNUMBER(G106),ISNUMBER(C106)),(G106-C106)*10000,"n/a") -> 2.0740547 | H127: =IF(AND(ISNUMBER(H106),ISNUMBER(D106)),(H106-D106)*10000,"n/a") -> 172.41021 | I127: =IF(AND(ISNUMBER(I106),ISNUMBER(E106)),(I106-E106)*10000,"n/a") -> 224.44308 | J127: =IF(AND(ISNUMBER(J106),ISNUMBER(F106)),(J106-F106)*10000,"n/a") -> 417.83897 | K127: =IF(AND(ISNUMBER(K106),ISNUMBER(G106)),(K106-G106)*10000,"n/a") -> 143.01802 | L127: =IF(AND(ISNUMBER(L106),ISNUMBER(H106)),(L106-H106)*10000,"n/a") -> -40.191269 | M127: =IF(AND(ISNUMBER(M106),ISNUMBER(I106)),(M106-I106)*10000,"n/a") -> -106.05259 | N127: =IF(AND(ISNUMBER(N106),ISNUMBER(J106)),(N106-J106)*10000,"n/a") -> 132.71458 | ... R127: =IF(AND(ISNUMBER(R106),ISNUMBER(N106)),(R106-N106)*10000,"n/a") -> 112.4089 | U127: n/a | V127: =IF(AND(ISNUMBER(V106),ISNUMBER(U106)),(V106-U106)*10000,"n/a") -> n/a | W127: =IF(AND(ISNUMBER(W106),ISNUMBER(V106)),(W106-V106)*10000,"n/a") -> 210.2613 | X127: =IF(AND(ISNUMBER(X106),ISNUMBER(W106)),(X106-W106)*10000,"n/a") -> 34.479688 | Y127: =IF(AND(ISNUMBER(Y106),ISNUMBER(X106)),(Y106-X106)*10000,"n/a") -> 128.69799 | Z127: =IF(AND(ISNUMBER(Z106),ISNUMBER(Y106)),(Z106-Y106)*10000,"n/a") -> 135.30878 | AA127: =IF(AND(ISNUMBER(AA106),ISNUMBER(Z106)),(AA106-Z106)*10000,"n/a") -> 123.55104 | AB127: =IF(AND(ISNUMBER(AB106),ISNUMBER(AA106)),(AB106-AA106)*10000,"n/a") -> 204.22055
A128: Adj. net margin q/q change (bps) | B128: qbps | C128: n/a | D128: =IF(AND(ISNUMBER(D106),ISNUMBER(C106)),(D106-C106)*10000,"n/a") -> 116.13387 | E128: =IF(AND(ISNUMBER(E106),ISNUMBER(D106)),(E106-D106)*10000,"n/a") -> 82.519333 | F128: =IF(AND(ISNUMBER(F106),ISNUMBER(E106)),(F106-E106)*10000,"n/a") -> -299.11433 | G128: =IF(AND(ISNUMBER(G106),ISNUMBER(F106)),(G106-F106)*10000,"n/a") -> 102.53519 | H128: =IF(AND(ISNUMBER(H106),ISNUMBER(G106)),(H106-G106)*10000,"n/a") -> 286.47003 | I128: =IF(AND(ISNUMBER(I106),ISNUMBER(H106)),(I106-H106)*10000,"n/a") -> 134.5522 | J128: =IF(AND(ISNUMBER(J106),ISNUMBER(I106)),(J106-I106)*10000,"n/a") -> -105.71844 | K128: =IF(AND(ISNUMBER(K106),ISNUMBER(J106)),(K106-J106)*10000,"n/a") -> -172.28576 | ... R128: =IF(AND(ISNUMBER(R106),ISNUMBER(Q106)),(R106-Q106)*10000,"n/a") -> 88.09816 | U128: n/a | V128: n/a | W128: n/a | X128: n/a | Y128: n/a | Z128: n/a | AA128: n/a | AB128: n/a
A130: GAAP gross margin y/y change (bps) | B130: ybps | C130: n/a | D130: n/a | E130: n/a | F130: n/a | G130: =IF(AND(ISNUMBER(G85),ISNUMBER(C85)),(G85-C85)*10000,"n/a") -> -10 | H130: =IF(AND(ISNUMBER(H85),ISNUMBER(D85)),(H85-D85)*10000,"n/a") -> -240 | I130: =IF(AND(ISNUMBER(I85),ISNUMBER(E85)),(I85-E85)*10000,"n/a") -> -130 | J130: =IF(AND(ISNUMBER(J85),ISNUMBER(F85)),(J85-F85)*10000,"n/a") -> -40 | K130: =IF(AND(ISNUMBER(K85),ISNUMBER(G85)),(K85-G85)*10000,"n/a") -> 50 | L130: =IF(AND(ISNUMBER(L85),ISNUMBER(H85)),(L85-H85)*10000,"n/a") -> 80 | M130: =IF(AND(ISNUMBER(M85),ISNUMBER(I85)),(M85-I85)*10000,"n/a") -> 38 | N130: =IF(AND(ISNUMBER(N85),ISNUMBER(J85)),(N85-J85)*10000,"n/a") -> 194 | ... R130: =IF(AND(ISNUMBER(R85),ISNUMBER(N85)),(R85-N85)*10000,"n/a") -> 60 | U130: n/a | V130: =IF(AND(ISNUMBER(V85),ISNUMBER(U85)),(V85-U85)*10000,"n/a") -> n/a | W130: =IF(AND(ISNUMBER(W85),ISNUMBER(V85)),(W85-V85)*10000,"n/a") -> -100 | X130: =IF(AND(ISNUMBER(X85),ISNUMBER(W85)),(X85-W85)*10000,"n/a") -> 139 | Y130: =IF(AND(ISNUMBER(Y85),ISNUMBER(X85)),(Y85-X85)*10000,"n/a") -> 74 | Z130: =IF(AND(ISNUMBER(Z85),ISNUMBER(Y85)),(Z85-Y85)*10000,"n/a") -> 41 | AA130: =IF(AND(ISNUMBER(AA85),ISNUMBER(Z85)),(AA85-Z85)*10000,"n/a") -> 33 | AB130: =IF(AND(ISNUMBER(AB85),ISNUMBER(AA85)),(AB85-AA85)*10000,"n/a") -> 3
A131: GAAP gross margin q/q change (bps) | B131: qbps | C131: n/a | D131: =IF(AND(ISNUMBER(D85),ISNUMBER(C85)),(D85-C85)*10000,"n/a") -> 230 | E131: =IF(AND(ISNUMBER(E85),ISNUMBER(D85)),(E85-D85)*10000,"n/a") -> 90 | F131: =IF(AND(ISNUMBER(F85),ISNUMBER(E85)),(F85-E85)*10000,"n/a") -> -300 | G131: =IF(AND(ISNUMBER(G85),ISNUMBER(F85)),(G85-F85)*10000,"n/a") -> -30 | H131: =IF(AND(ISNUMBER(H85),ISNUMBER(G85)),(H85-G85)*10000,"n/a") -> 0 | I131: =IF(AND(ISNUMBER(I85),ISNUMBER(H85)),(I85-H85)*10000,"n/a") -> 200 | J131: =IF(AND(ISNUMBER(J85),ISNUMBER(I85)),(J85-I85)*10000,"n/a") -> -210 | K131: =IF(AND(ISNUMBER(K85),ISNUMBER(J85)),(K85-J85)*10000,"n/a") -> 60 | ... R131: =IF(AND(ISNUMBER(R85),ISNUMBER(Q85)),(R85-Q85)*10000,"n/a") -> -42 | U131: n/a | V131: n/a | W131: n/a | X131: n/a | Y131: n/a | Z131: n/a | AA131: n/a | AB131: n/a
A133: GAAP operating margin y/y change (bps) | B133: ybps | C133: n/a | D133: n/a | E133: n/a | F133: n/a | G133: =IF(AND(ISNUMBER(G87),ISNUMBER(C87)),(G87-C87)*10000,"n/a") -> 480 | H133: =IF(AND(ISNUMBER(H87),ISNUMBER(D87)),(H87-D87)*10000,"n/a") -> -2030 | I133: =IF(AND(ISNUMBER(I87),ISNUMBER(E87)),(I87-E87)*10000,"n/a") -> -4760 | J133: =IF(AND(ISNUMBER(J87),ISNUMBER(F87)),(J87-F87)*10000,"n/a") -> 160 | K133: =IF(AND(ISNUMBER(K87),ISNUMBER(G87)),(K87-G87)*10000,"n/a") -> 340 | L133: =IF(AND(ISNUMBER(L87),ISNUMBER(H87)),(L87-H87)*10000,"n/a") -> 90 | M133: =IF(AND(ISNUMBER(M87),ISNUMBER(I87)),(M87-I87)*10000,"n/a") -> 77 | N133: =IF(AND(ISNUMBER(N87),ISNUMBER(J87)),(N87-J87)*10000,"n/a") -> 538 | ... R133: =IF(AND(ISNUMBER(R87),ISNUMBER(N87)),(R87-N87)*10000,"n/a") -> 154 | U133: n/a | V133: =IF(AND(ISNUMBER(V87),ISNUMBER(U87)),(V87-U87)*10000,"n/a") -> n/a | W133: =IF(AND(ISNUMBER(W87),ISNUMBER(V87)),(W87-V87)*10000,"n/a") -> -1542 | X133: =IF(AND(ISNUMBER(X87),ISNUMBER(W87)),(X87-W87)*10000,"n/a") -> 268 | Y133: =IF(AND(ISNUMBER(Y87),ISNUMBER(X87)),(Y87-X87)*10000,"n/a") -> 193 | Z133: =IF(AND(ISNUMBER(Z87),ISNUMBER(Y87)),(Z87-Y87)*10000,"n/a") -> 181 | AA133: =IF(AND(ISNUMBER(AA87),ISNUMBER(Z87)),(AA87-Z87)*10000,"n/a") -> 144 | AB133: =IF(AND(ISNUMBER(AB87),ISNUMBER(AA87)),(AB87-AA87)*10000,"n/a") -> 145
A134: GAAP operating margin q/q change (bps) | B134: qbps | C134: n/a | D134: =IF(AND(ISNUMBER(D87),ISNUMBER(C87)),(D87-C87)*10000,"n/a") -> 2950 | E134: =IF(AND(ISNUMBER(E87),ISNUMBER(D87)),(E87-D87)*10000,"n/a") -> 2810 | F134: =IF(AND(ISNUMBER(F87),ISNUMBER(E87)),(F87-E87)*10000,"n/a") -> -5280 | G134: =IF(AND(ISNUMBER(G87),ISNUMBER(F87)),(G87-F87)*10000,"n/a") -> 0 | H134: =IF(AND(ISNUMBER(H87),ISNUMBER(G87)),(H87-G87)*10000,"n/a") -> 440 | I134: =IF(AND(ISNUMBER(I87),ISNUMBER(H87)),(I87-H87)*10000,"n/a") -> 80 | J134: =IF(AND(ISNUMBER(J87),ISNUMBER(I87)),(J87-I87)*10000,"n/a") -> -360 | K134: =IF(AND(ISNUMBER(K87),ISNUMBER(J87)),(K87-J87)*10000,"n/a") -> 180 | ... R134: =IF(AND(ISNUMBER(R87),ISNUMBER(Q87)),(R87-Q87)*10000,"n/a") -> 87 | U134: n/a | V134: n/a | W134: n/a | X134: n/a | Y134: n/a | Z134: n/a | AA134: n/a | AB134: n/a
A136: COGS % of revenue (non-GAAP) y/y change (bps) | B136: ybps | C136: n/a | D136: n/a | E136: n/a | F136: n/a | G136: =IF(AND(ISNUMBER(G108),ISNUMBER(C108)),(G108-C108)*10000,"n/a") -> -38.970396 | H136: =IF(AND(ISNUMBER(H108),ISNUMBER(D108)),(H108-D108)*10000,"n/a") -> 0.88202638 | I136: =IF(AND(ISNUMBER(I108),ISNUMBER(E108)),(I108-E108)*10000,"n/a") -> 127.47711 | J136: =IF(AND(ISNUMBER(J108),ISNUMBER(F108)),(J108-F108)*10000,"n/a") -> 44.133186 | K136: =IF(AND(ISNUMBER(K108),ISNUMBER(G108)),(K108-G108)*10000,"n/a") -> -75.915864 | L136: =IF(AND(ISNUMBER(L108),ISNUMBER(H108)),(L108-H108)*10000,"n/a") -> 124.28903 | M136: =IF(AND(ISNUMBER(M108),ISNUMBER(I108)),(M108-I108)*10000,"n/a") -> 34.397078 | N136: =IF(AND(ISNUMBER(N108),ISNUMBER(J108)),(N108-J108)*10000,"n/a") -> -164.28385 | ... R136: =IF(AND(ISNUMBER(R108),ISNUMBER(N108)),(R108-N108)*10000,"n/a") -> -30.98771 | U136: n/a | V136: =IF(AND(ISNUMBER(V108),ISNUMBER(U108)),(V108-U108)*10000,"n/a") -> n/a | W136: =IF(AND(ISNUMBER(W108),ISNUMBER(V108)),(W108-V108)*10000,"n/a") -> 38.105386 | X136: =IF(AND(ISNUMBER(X108),ISNUMBER(W108)),(X108-W108)*10000,"n/a") -> -22.223288 | Y136: =IF(AND(ISNUMBER(Y108),ISNUMBER(X108)),(Y108-X108)*10000,"n/a") -> -58.029371 | Z136: =IF(AND(ISNUMBER(Z108),ISNUMBER(Y108)),(Z108-Y108)*10000,"n/a") -> -47.924641 | AA136: =IF(AND(ISNUMBER(AA108),ISNUMBER(Z108)),(AA108-Z108)*10000,"n/a") -> -50.073909 | AB136: =IF(AND(ISNUMBER(AB108),ISNUMBER(AA108)),(AB108-AA108)*10000,"n/a") -> -23.041393
A137: COGS % of revenue (non-GAAP) q/q change (bps) | B137: qbps | C137: n/a | D137: =IF(AND(ISNUMBER(D108),ISNUMBER(C108)),(D108-C108)*10000,"n/a") -> -236.84649 | E137: =IF(AND(ISNUMBER(E108),ISNUMBER(D108)),(E108-D108)*10000,"n/a") -> -104.90435 | F137: =IF(AND(ISNUMBER(F108),ISNUMBER(E108)),(F108-E108)*10000,"n/a") -> 298.10789 | G137: =IF(AND(ISNUMBER(G108),ISNUMBER(F108)),(G108-F108)*10000,"n/a") -> 4.6725557 | H137: =IF(AND(ISNUMBER(H108),ISNUMBER(G108)),(H108-G108)*10000,"n/a") -> -196.99406 | I137: =IF(AND(ISNUMBER(I108),ISNUMBER(H108)),(I108-H108)*10000,"n/a") -> 21.690727 | J137: =IF(AND(ISNUMBER(J108),ISNUMBER(I108)),(J108-I108)*10000,"n/a") -> 214.76397 | K137: =IF(AND(ISNUMBER(K108),ISNUMBER(J108)),(K108-J108)*10000,"n/a") -> -115.37649 | ... R137: =IF(AND(ISNUMBER(R108),ISNUMBER(Q108)),(R108-Q108)*10000,"n/a") -> 33.637748 | U137: n/a | V137: n/a | W137: n/a | X137: n/a | Y137: n/a | Z137: n/a | AA137: n/a | AB137: n/a
A139: R&D % of revenue y/y change (bps) | B139: ybps | C139: n/a | D139: n/a | E139: n/a | F139: n/a | G139: =IF(AND(ISNUMBER(G110),ISNUMBER(C110)),(G110-C110)*10000,"n/a") -> 80.233167 | H139: =IF(AND(ISNUMBER(H110),ISNUMBER(D110)),(H110-D110)*10000,"n/a") -> 87.657857 | I139: =IF(AND(ISNUMBER(I110),ISNUMBER(E110)),(I110-E110)*10000,"n/a") -> -202.23452 | J139: =IF(AND(ISNUMBER(J110),ISNUMBER(F110)),(J110-F110)*10000,"n/a") -> -256.28822 | K139: =IF(AND(ISNUMBER(K110),ISNUMBER(G110)),(K110-G110)*10000,"n/a") -> -124.43087 | L139: =IF(AND(ISNUMBER(L110),ISNUMBER(H110)),(L110-H110)*10000,"n/a") -> -120.32938 | M139: =IF(AND(ISNUMBER(M110),ISNUMBER(I110)),(M110-I110)*10000,"n/a") -> 32.357359 | N139: =IF(AND(ISNUMBER(N110),ISNUMBER(J110)),(N110-J110)*10000,"n/a") -> -10.53653 | ... R139: =IF(AND(ISNUMBER(R110),ISNUMBER(N110)),(R110-N110)*10000,"n/a") -> -44.969779 | U139: n/a | V139: =IF(AND(ISNUMBER(V110),ISNUMBER(U110)),(V110-U110)*10000,"n/a") -> n/a | W139: =IF(AND(ISNUMBER(W110),ISNUMBER(V110)),(W110-V110)*10000,"n/a") -> -79.423294 | X139: =IF(AND(ISNUMBER(X110),ISNUMBER(W110)),(X110-W110)*10000,"n/a") -> -59.33602 | Y139: =IF(AND(ISNUMBER(Y110),ISNUMBER(X110)),(Y110-X110)*10000,"n/a") -> -54.204707 | Z139: =IF(AND(ISNUMBER(Z110),ISNUMBER(Y110)),(Z110-Y110)*10000,"n/a") -> -61.270461 | AA139: =IF(AND(ISNUMBER(AA110),ISNUMBER(Z110)),(AA110-Z110)*10000,"n/a") -> -67.911829 | AB139: =IF(AND(ISNUMBER(AB110),ISNUMBER(AA110)),(AB110-AA110)*10000,"n/a") -> -144.74117
A140: R&D % of revenue q/q change (bps) | B140: qbps | C140: n/a | D140: =IF(AND(ISNUMBER(D110),ISNUMBER(C110)),(D110-C110)*10000,"n/a") -> -27.888778 | E140: =IF(AND(ISNUMBER(E110),ISNUMBER(D110)),(E110-D110)*10000,"n/a") -> 98.595849 | F140: =IF(AND(ISNUMBER(F110),ISNUMBER(E110)),(F110-E110)*10000,"n/a") -> 4.2270531 | G140: =IF(AND(ISNUMBER(G110),ISNUMBER(F110)),(G110-F110)*10000,"n/a") -> 5.2990436 | H140: =IF(AND(ISNUMBER(H110),ISNUMBER(G110)),(H110-G110)*10000,"n/a") -> -20.464089 | I140: =IF(AND(ISNUMBER(I110),ISNUMBER(H110)),(I110-H110)*10000,"n/a") -> -191.29653 | J140: =IF(AND(ISNUMBER(J110),ISNUMBER(I110)),(J110-I110)*10000,"n/a") -> -49.826641 | K140: =IF(AND(ISNUMBER(K110),ISNUMBER(J110)),(K110-J110)*10000,"n/a") -> 137.15639 | ... R140: =IF(AND(ISNUMBER(R110),ISNUMBER(Q110)),(R110-Q110)*10000,"n/a") -> -74.904855 | U140: n/a | V140: n/a | W140: n/a | X140: n/a | Y140: n/a | Z140: n/a | AA140: n/a | AB140: n/a
...
